Workbook

Sheet Salary
B1: EMPLOYEE PAYROLL SHEET/ BẢNG LƯƠNG NHÂN VIÊN
B2: =[1]Overtime!A3 -> Jul 2026/ Tháng 07 năm 2026 (26 Jun 26 - 25 Jul 26)
B3: - Số công quy định trong tháng/ Standard working days: | J3: 26 | CJ3: Ngày công tháng trước | CK3: 27 | CV3: 46234 | CW3: 26 | EB3: 5 | EQ3: 2025
C4: 1 | D4: 2 | I4: 3 | J4: 4 | K4: 5 | L4: 6 | M4: 7 | N4: 8 | O4: 9 | P4: 10 | Q4: 11 | R4: 12 | S4: 13 | X4: 15 | Y4: 20 | Z4: 21 | AA4: 22 | AB4: 23 | AC4: 24 | AD4: 25 | AE4: 26 | AI4: 27 | AJ4: 28 | AK4: 30 | AL4: 31 | AM4: 32 | AN4: 33 | AO4: 19 | AX4: 34 | BE4: 35 | BF4: 36 | BG4: 37 | BH4: 38 | BI4: 39 | BJ4: 40 | BK4: 41 | BL4: 42 | BM4: 43 | BN4: 44 | BO4: 45 | BT4: 46 | BY4: 47 | BZ4: 48 | CA4: 49 | CG4: 50 | CH4: 51 | CI4: 52 | CJ4: 54 | CK4: 55 | CL4: 56 | CM4: 57 | CN4: 58 | CO4: 59 | EF4: 31 | EG4: 32 | EH4: 33 | EN4: 27 | EQ4: 37 | ES4: 50 | EU4: 50
B5: No./ STT | C5: Employee ID/ Mã NV | D5: Full name/ Họ tên | E5: Contract style/ Loại hợp đồng | F5: Accounting code | H5: Direct/ Indirect | I5: Line/ Chuyền | J5: Section/ Bộ phận | K5: Position/Chức vụ | L5: Salary for SI & HI Lương đóng BHXH,BHYT | M5: Salary for UI/ Lương đóng BHTN | N5: Salary in Labour Contract | Y5: Actual Salary in the Month | AK5: Overtime Salary/Lương ngoài giờ | AO5: Lucky money/ Lì xì 2026 | AP5: Tet bonus/ Thưởng Tết | AQ5: Special bonus/ Thưởng đặc biệt | AR5: Shift working support/ Tiền hỗ trợ làm ca | AS5: Children support/ Hỗ trợ con nhỏ | AT5: Process company supporting/ Hỗ trợ công ty gia công | AU5: Fire fighting training allowance/ Phụ cấp tham gia huấn luyện PCCC | AV5: 21,5% SI paid by Company during probation | AW5: Annual leave payment Thanh toán phép năm | AX5: Menstrual allowance Trợ cấp kinh nguyệt | AY5: Adjustment for previous month/ ĐC lương tháng trước | AZ5: KPIs bonus/ Thưởng đánh giá kết quả làm việc | BA5: Commuting supporting Hỗ trợ xăng xe | BE5: Gross salary/ Tổng tiền lương | BF5: Self reduction/ GT cá nhân | BG5: Dependant(s) Reduction/ GTGC | BH5: Deductions/Khác khoảng khấu trừ lương | BP5: Company/ Doanh nghiệp | BT5: Paid Lucky money/ Lì xì 2025 đã trả | BU5: YEP 2024 gifts paid/ Quà tiệc tất niên 2024 đã trả | BV5: Paid YEP 2026 support/ Hỗ trợ tiệc tất niên 2026 đã trả | BW5: Sunday meal support/ Tiền cơm chủ nhật | BX5: Salary advance/ Tạm ứng lương | BY5: Marriage gift/ Quà kết hôn | BZ5: PIT Finalization/ Quyết toán thuế | CA5: Severance allowance/ Trợ cấp thôi việc | CB5: Employee' contract compensation/ Tiền bồi thường hợp đồng của người lao động | CG5: Net Salary/ Lương thực nhận | CH5: Cost to company | CI5: Tet bonus estimation | CJ5: Ngày phép năm còn | CL5: Giờ kinh nguyệt | CN5: Chênh lệch lương tháng trước | CO5: Thanh lý hợp đồng | CP5: Nhập | CQ5: Nhập | CR5: Nhập | CS5: Nhập | CT5: Nhập | CU5: Nhập | CV5: Nhập | CW5: Nhập | EQ5: Dependant(s) Reduction/ GTGC
N6: Basic salary in labour contract/Lương trên HĐLĐ | O6: Technical allowance/Phụ cấp kỹ thuật | P6: Position allowance/Phụ cấp chức vụ | Q6: Accomodation Allowance/Phụ cấp nhà ở | R6: Commuting allowance Phụ cấp xăng xe | S6: Phone allowance Phụ cấp điện thoại | T6: Fire prevention and fighting allowance/Phụ cấp phòng cháy và chữa cháy: | U6: Safety and hygiene allowance/Phụ cấp an toàn vệ sinh viên | V6: Supporting stages allowance/Phụ cấp hỗ trợ công đoạn: | W6: Attendance incentive/Thưởng Chuyên cần | X6: Responsibility incentive Thưởng trách nhiệm | Y6: Working days/ Ngày công | Z6: Basic salary in labour contract/Lương cơ bản | AA6: Technical allowance/Phụ cấp kỹ thuật | AB6: Position allowance/ Phụ cấp chức vụ | AC6: Accomodation Allowance/ Phụ cấp nhà ở | AD6: Commuting bus Phụ cấp xăng xe | AE6: Phone Phụ cấp điện thoại | AF6: Fire prevention and fighting allowance/Phụ cấp phòng cháy và chữa cháy: | AG6: Safety and hygiene allowance/Phụ cấp an toàn vệ sinh viên | AH6: Supporting stages allowance/Phụ cấp hỗ trợ công đoạn: | AI6: Attendance incentive/ Thưởng Chuyên cần | AJ6: Responsibility incentive Thưởng trách nhiệm | AK6: Work hour/Giờ làm | AL6: 100% | AM6: Vượt 100% | AN6: Total/ Tổng tiền | BH6: Social Insurance/ BHXH(8%) | BI6: Health Insurance/ BHYT (1.5%) | BJ6: Unemployment Insurance/ BHTN (1%) | BK6: Union/ Công đoàn | BL6: Taxable income/ Thu nhập chịu thuế | BM6: Assessable income/Thu nhập tính thuế của NV | BN6: PIT/ Thuế thu nhập | BO6: Total deductions/ Tổng khấu trừ | BP6: Social Insurance/ BHXH (17,5%) | BQ6: Health Insurance/ BHYT (3%) | BR6: Unemployment Insurance/ BHTN (1%) | BS6: Union Fund/ KPCĐ (2%) | CJ6: Số ngày | CK6: Số tiền | CL6: Số giờ | CM6: Số tiền | CR6: 46218 | CV6: Chưa đóng BHXH | CW6: Chưa kí HĐ Chính thức đến ngày 25 | CX6: Chi khác ngoài bảng lương | DB6: Làm việc <5 ngày | DC6: Làm CN <=4h/ ngày (x) | DD6: Số ngày nghỉ bù làm CN | DE6: Đi trễ & về sớm | DF6: Tiền trừ đi trễ về sớm | DG6: Nghỉ không lương + Ốm + Con ốm | DH6: Tiền trừ không lương | DI6: Nghỉ Thai sản + Dưỡng sức | DJ6: Tiền CC tính theo thực tế | DK6: Tổng trừ CC | DL6: Ốm hưởng BHXH May | DM6: CO hưởng BHXH May | DN6: Tổng ngày nghỉ hưởng BHXH May | DO6: Tổng nghỉ KL May | DP6: Tổng nghỉ BHXH và KL May | DQ6: Tổng nghỉ ko đóng BH | DR6: Khám thai | DS6: Tiền CC khám thai | DT6: BHXH | DU6: BHYT | DV6: BHTN | DW6: Kinh phí CĐ | DX6: Tổng lương | DY6: Phụ cấp | DZ6: Thưởng | EA6: NKL | EB6: Check PIT Nhà ở | EF6: Check OT | EN6: Attendance incentive/ Thưởng Chuyên cần
D7: Tên | E7: Loại | H7: Phân loại | I7: Chuyền | J7: Bộ phận | K7: Chức vụ | L7: BHXH | M7: BHTN | N7: CB | O7: KT | P7: CV | Q7: NO | R7: XX | S7: ĐT | T7: PCCC | U7: ATVSTP | V7: HTCD | W7: CC | X7: TN | Y7: Ngày công | Z7: CB-TT | AA7: KT-TT | AB7: CV-TT | AC7: NO-TT | AD7: XX-TT | AE7: DT-TT | AF7: PCCC | AG7: ATVSTP | AH7: HTCD | AI7: CC-TT | AJ7: TN-TT | AK7: Giờ OT | AL7: 1 | AM7: Vuot 100% | AN7: OT | AO7: Lucky | AP7: Tet bonus | AQ7: Special bonus | AR7: Shift work | AS7: Child | AT7: Process | AV7: 0.215 | AW7: TL | AX7: KN | AY7: Đ/c lương tháng trc | AZ7: KPI | BA7: 100K XX | BE7: Tổng tiền lương | BF7: GT cá nhân | BG7: GTGC | BH7: BHXH 8% | BI7: BHYT 1,5% | BJ7: BHTN 1% | BK7: CĐ | BL7: TN chịu thuế | BM7: TN tính thuế | BN7: PIT | BO7: Tổng khấu trừ | BP7: BHXH 17.5% | BQ7: BHYT 3% | BR7: BHTN 1% | BS7: KPCD 2% | BT7: Lucky paid | BU7: YEP paid | BV7: YEP support paid | BW7: Sunday meal | BX7: TU | BY7: Quà KH | BZ7: QTT | CA7: TCTV | CB7: BTHD | CG7: Lương thực nhận | CH7: Cost to company | CI7: Tet bonus estimation | CJ7: Ngày phép năm còn | CK7: Tiền phép năm | CL7: Giờ KN | CM7: Tiền KN | CN7: Chênh lệch lương tháng trước | CO7: Thanh lý hợp đồng | CP7: Ngày vào làm | CQ7: Ngày kí HĐ | CR7: Nghĩ việc | CS7: Nghỉ thai sản | CT7: Thai sản đi làm lại | CU7: Tự ý bỏ việc | CV7: Xét tính 21.5% (x) - Chưa đóng BHXH | CW7: Thử việc (x) | CX7: Giỏ quà tết 02/02/2026 | CY7: Lì xì Tết 25/02/2026 | DT7: 0.175 | DU7: 0.03 | DV7: 0.01 | DW7: 0.02 | DX7: Tổng lương | DY7: Phụ cấp | DZ7: Thưởng | EA7: NKL | EB7: 15% TNCT | EC7: PC Nhà ở | ED7: Chênh lệch | EE7: Check 15% | EF7: Chịu thuế | EG7: Không chịu thuế | EH7: OT | EI7: Check OT Tax | EK7: OT150 | EL7: OT200 | EM7: GAP OT | EN7: CC-TT | EO7: Check | EP7: Check | EQ7: GTGC | ER7: Số người phụ thuộc
B8: I. Management
B9: II. Production | L9: =SUM(L10:L25) -> 107550000 | M9: =SUM(M10:M25) -> 107550000 | N9: =SUM(N10:N25) -> 83950000 | O9: =SUM(O10:O25) -> 7400000 | P9: =SUM(P10:P25) -> 0 | Q9: =SUM(Q10:Q25) -> 0 | R9: =SUM(R10:R25) -> 4800000 | S9: =SUM(S10:S25) -> 0 | ... EP9: =SUM(EP10:EP25) -> 0 | EQ9: 1315600000
B10: 1 | C10: TIQN-1457 | D10: Nguyễn Thị Thu Nhi | E10: =IF(CW10="x","Probation",IF(CR10>0,"Resigned - Official","Official")) -> Resigned - Official | F10: =IF(H10="management","6421.11",0) -> 0 | G10: Sewing | H10: Direct | I10: Line 11 | J10: Sewing | K10: Sewing worker | L10: =M10 -> 6800000 | M10: =N10+O10+P10+W10+X10+T10+U10+V10 -> 6800000 | N10: 5000000 | O10: 800000 | P10: 0 | Q10: 0 | R10: 300000 | S10: 0 | T10: 0 | U10: 0 | V10: 0 | W10: 1000000 | X10: 0 | Y10: =_xlfn.XLOOKUP(C10,[1]Timesheet!$B$9:$B$25,[1]Timesheet!$AO$9:$AO$25,0,,1) -> 7.9 | Z10: =ROUND(N10/$J$3*Y10,0) -> 1519231 | AA10: =ROUND(O10/$J$3*(Y10+_xlfn.XLOOKUP(C10,[1]Timesheet!B:B,[1]Timesheet!BS:BS,0)),0) -> 243077 | AB10: =ROUND(IF(Y10>=8,P10,(P10/$J$3)*(Y10+_xlfn.XLOOKUP(C10,[1]Timesheet!B:B,[1]Timesheet!BS:BS,0))),0) -> 0 | AC10: =ROUND(IF(Y10>=14,Q10,(Q10/2)),0) -> 0 | AD10: =IF(_xlfn.XLOOKUP(Salary!C10,[1]Bus!B:B,[1]Bus!G:G,"",,-1)=1,0,ROUND((R10/$J$3)*ROUND(Y10+_xlfn.XLOOKUP(C10,[1]Timesheet!B:B,[1]Timesheet!BS:BS,0,,-1),0),0)) -> 92308 | AE10: =IF(Y10>0,S10,0) -> 0 | AF10: =ROUND(IF(Y10>=8,T10,(T10/$J$3)*(Y10+_xlfn.XLOOKUP(C10,[1]Timesheet!B:B,[1]Timesheet!BS:BS,0))),0) -> 0 | AG10: =ROUND(IF(Y10>=8,U10,(U10/$J$3)*(Y10+_xlfn.XLOOKUP(C10,[1]Timesheet!B:B,[1]Timesheet!BS:BS,0))),0) -> 0 | AH10: =ROUND(IF(OR(CR10>0,Y10<8),(V10/$J$3)*(Y10+_xlfn.XLOOKUP(C10,[1]Timesheet!B:B,[1]Timesheet!BS:BS,0)),V10),0) -> 0 | AI10: =ROUND(IF(DAY(CR10)=26,IF(Y10=0,0,IF(W10=0,0,IF(OR(-(DK10)>DJ10,-(DK10)=DJ10),0,DJ10+DK10+DS10))),IF(CR10>0,0,IF(Y10=0,0,IF(W10=0,0,IF(OR(-(DK10)>DJ10,-(DK10)=DJ10),0,DJ10+DK10+DS10))))),0) -> 0 | AJ10: =IF(Y10>0,ROUND(IF(LEN(CR10)>2,(X10/$J$3)*(Y10+_xlfn.XLOOKUP(C10,[1]Timesheet!B:B,[1]Timesheet!BS:BS,0)),X10),0),0) -> 0 | AK10: =_xlfn.XLOOKUP(C10,[1]Overtime!$B$7:$B$557,[1]Overtime!$AN$7:$AN$557,0) -> 5.1 | AL10: =ROUND(((SUM(N10:P10)+SUM(T10:X10))/($J$3*8))*_xlfn.XLOOKUP(C10,[1]Overtime!$B$9:$B$557,[1]Overtime!$AU$9:$AU$557,0),0) -> 166731 | AM10: =ROUND(((SUM(N10:P10)+SUM(T10:X10))/($J$3*8))*_xlfn.XLOOKUP(C10,[1]Overtime!$B$9:$B$557,[1]Overtime!$AY$9:$AY$557,0),0) -> 83365 | AN10: =ROUND(AM10+AL10,0) -> 250096 | AR10: =ROUND(_xlfn.XLOOKUP(C10,[1]Timesheet!$B$9:$B$458,[1]Timesheet!$BQ$9:$BQ$458,,,-1)*SUM(Salary!N10:P10,Salary!T10:X10)*20%/Salary!$J$3,0) -> 0 | AS10: 0 | AT10: 0 | AV10: =IF(CV10="x",IF(IF(CR10>0,$CW$3-_xlfn.XLOOKUP(C10,[1]Timesheet!B:B,[1]Timesheet!BW:BW,0,,-1),$CW$3-_xlfn.XLOOKUP(C10,[1]Timesheet!B:B,[1]Timesheet!BW:BW,0,,-1)-$EB$3)<14,ROUND(L10*20.5%+M10*1%,0),0),0) -> 0 | AW10: =CK10 -> 654815 | AX10: =CM10 -> 343269 | AZ10: 0 | BE10: =ROUND(SUM(Z10:AJ10)+AN10+AX10+AT10+AO10+AR10+AS10+AW10+AY10+AV10+AP10+AU10+AQ10+AZ10+BA10,0) -> 3102796 | BF10: =IF(OR(CW10="x",CR10>0),0,15500000) -> 0 | BG10: 0 | BI10: =IF(CV10="x",0,ROUND(L10*1.5%,0)) -> 102000 | BJ10: =IF(CV10="x",0,ROUND(IF(BH10>0,M10*1%,0),0)) -> 0 | BK10: =IF(CV10="x",0,ROUND(IF(BH10>0,38948,0),0)) -> 0 | BL10: =ROUND(IF(AC10>0,IF(ROUND((BE10+CX10+CY10-AE10-AN10-AW10-AC10)*15%,0)>AC10,BE10+CX10+CY10-AE10-AN10-AW10,BE10+CX10+CY10-AE10-AN10-AW10-AC10+ROUND((BE10+CX10+CY10-AE10-AN10-AW10-AC10)*15%,0)),BE10+CX10+CY10-AE10-AN10-AW10),0) -> 2197885 | BM10: =IF(OR(CW10="x",CR10>0),BL10,IF(BL10-BF10-BG10-SUM(BH10:BJ10)>0,BL10-BF10-BG10-SUM(BH10:BJ10),0)) -> 2197885 | BN10: =IF(OR(CW10="x",CR10>0),ROUND(IF(BM10>4999999,BM10*10%,0),0),ROUND(IF(BM10>100000000,((BM10-100000000)*0.35+20500000),IF(AND(BM10>60000000,BM10<=100000000),((BM10-60000000)*0.3+8500000),IF(AND(BM10>30000000,BM10<=60000000),((BM10-30000000)*0.2+2500000),IF(AND(BM10>10000000,BM10<=30000000),((BM10-10000000)*0.1+500000),IF(BM10<0,0,(BM10*0.05)))))),0)) -> 0 | BO10: =SUM(BH10:BK10,BN10) -> 102000 | BP10: =IF(CV10="x",0,ROUND(IF(BH10>0,L10*17.5%,0),0)) -> 0 | BQ10: =IF(CV10="x",0,ROUND(IF(BI10>0,L10*3%,0),0)) -> 204000 | BR10: =IF(CV10="x",0,ROUND(IF(BJ10>0,M10*1%,0),0)) -> 0 | BS10: =IF(CV10="x",0,ROUND(IF(BK10>0,L10*2%,0),0)) -> 0 | BW10: 0 | CG10: =ROUND(BE10-BO10+BZ10-BT10-BU10-BX10-BV10+BW10+BY10+CA10-CB10,0) -> 3000796 | CH10: =CG10+BN10+SUM(BH10:BK10)+SUM(BP10:BS10) -> 3306796 | CI10: =IF(BH10=0,0,ROUND((SUM(N10:X10)-(R10+S10))/12,0)) -> 0 | CJ10: 2.6 | CK10: =ROUND((M10/$CK$3*CJ10),0) -> 654815 | CL10: =7*1.5 -> 10.5 | CM10: =ROUND((M10/$J$3/8*CL10),0) -> 343269 | CO10: =CK10+CM10 -> 998084 | CP10: 45786 | CQ10: 45816 | CR10: 46209 | CS10: 0 | CT10: 0 | DC10: =_xlfn.XLOOKUP(C10,[1]Overtime!$B$8:$B$2327,[1]Overtime!$BA$8:$BA$2327,"",,-1) -> 0 | DD10: =_xlfn.XLOOKUP(C10,[1]Timesheet!$B$9:$B$2328,[1]Timesheet!$BS$9:$BS$2328,0,,-1) -> 0 | DE10: =_xlfn.XLOOKUP(C10,[1]Timesheet!$B$7:$B$616,[1]Timesheet!$BK$7:$BK$616,0)+_xlfn.XLOOKUP(C10,[1]Timesheet!$B$7:$B$616,[1]Timesheet!$AV$7:$AV$616,0)-_xlfn.XLOOKUP(C10,[1]Timesheet!$B$7:$B$616,[1]Timesheet!$AX$7:$AX$616,0)+_xlfn.XLOOKUP(C10,[1]Timesheet!$B$7:$B$616,[1]Timesheet!$AW$7:$AW$616,0)-_xlfn.XLOOKUP(C10,[1]Timesheet!$B$7:$B$616,[1]Timesheet!$AY$7:$AY$616,0) -> 1 | DF10: =DE10*(-100000) -> -100000 | DG10: =_xlfn.XLOOKUP(C10,[1]Timesheet!$B$7:$B$616,[1]Timesheet!$BV$7:$BV$616,0)+_xlfn.XLOOKUP(C10,[1]Timesheet!$B$7:$B$616,[1]Timesheet!$AX$7:$AX$616,0)++_xlfn.XLOOKUP(C10,[1]Timesheet!$B$7:$B$616,[1]Timesheet!$AY$7:$AY$616,0) -> 0 | DH10: =IF(DG10>2,-1000000,IF(DG10=2,-500000,IF(DG10=1,-200000,0))) -> 0 | DI10: =_xlfn.XLOOKUP(C10,[1]Timesheet!$B$7:$B$616,[1]Timesheet!$AZ$7:$AZ$616,0)+_xlfn.XLOOKUP(C10,[1]Timesheet!$B$7:$B$616,[1]Timesheet!$BA$7:$BA$616,0) -> 0 | DJ10: =IF(CW10="x",IF((ROUND(Y10*W10/$J$3,0))<0,0,ROUND(Y10*W10/$J$3,0)),IF(OR(CR10>0,CS10>0,CT10>0),W10/$J$3*(Y10+_xlfn.XLOOKUP(C10,[1]Timesheet!B:B,[1]Timesheet!BS:BS,0,,-1)+_xlfn.XLOOKUP(C10,[1]Timesheet!B:B,[1]Timesheet!BU:BU,0,,-1)),IF(OR(DH10<0,DF10<0),IF(DI10>0,W10/$J$3*($J$3-DI10),W10),W10/$J$3*(Y10+_xlfn.XLOOKUP(C10,[1]Timesheet!B:B,[1]Timesheet!BS:BS,0,,-1)+_xlfn.XLOOKUP(C10,[1]Timesheet!B:B,[1]Timesheet!BU:BU,0,,-1))))) -> 303846.15 | DK10: =DF10+DH10 -> -100000 | DL10: =_xlfn.XLOOKUP(C10,[1]Timesheet!$B$7:$B$565,[1]Timesheet!$BB$7:$BB$565,0) -> 0 | DM10: =_xlfn.XLOOKUP(C10,[1]Timesheet!$B$7:$B$565,[1]Timesheet!$BC$7:$BC$565,0) -> 0 | DN10: =_xlfn.XLOOKUP(C10,[1]Timesheet!$B$7:$B$565,[1]Timesheet!$BF$7:$BF$565,0) -> 0 | DO10: =_xlfn.XLOOKUP(C10,[1]Timesheet!$B$7:$B$565,[1]Timesheet!$BJ$7:$BJ$565,0) -> 0 | DP10: =DN10+DO10 -> 0 | DQ10: =_xlfn.XLOOKUP(C10,[1]Timesheet!$B$7:$B$565,[1]Timesheet!$BT$7:$BT$565,0) -> 17 | DR10: =_xlfn.XLOOKUP(C10,[1]Timesheet!$B$7:$B$565,[1]Timesheet!$BM$7:$BM$565,0) -> 0 | DS10: =W10/$J$3*DR10 -> 0 | DT10: =ROUND(IF(BH10>0,L10*$DT$7,0),0) -> 0 | DU10: =ROUND(IF(BI10>0,L10*$DU$7,0),0) -> 204000 | DV10: =ROUND(IF(BJ10>0,M10*$DV$7,0),0) -> 0 | DW10: =ROUND(IF(BK10>0,L10*$DW$7,0),0) -> 0 | DX10: =SUM(N10:X10) -> 7100000 | DY10: =SUM(O10:S10) -> 1100000 | DZ10: =SUM(W10:X10) -> 1000000 | EA10: =_xlfn.XLOOKUP(C10,[1]Timesheet!$B$7:$B$565,[1]Timesheet!$BI$7:$BI$565,0) -> 0 | EB10: =IF(AC10>0,ROUND((BE10+CX10+CY10-AE10-AN10-AW10-AC10)*15%,0),0) -> 0 | EC10: =AC10 -> 0 | ED10: =EB10-EC10 -> 0 | EE10: =BE10+CX10+CY10-AE10-AN10-AW10-BL10 -> 0 | EF10: =ROUND((SUM(N10:P10)+W10+X10+T10+U10+V10)/($J$3*8)*_xlfn.XLOOKUP(C10,[1]Overtime!$B$9:$B$557,[1]Overtime!$AU$9:$AU$557,0),0) -> 166731 | EG10: =ROUND(((SUM(N10:P10)+W10+X10+T10+U10+V10)/($J$3*8))*_xlfn.XLOOKUP(C10,[1]Overtime!$B$9:$B$557,[1]Overtime!$AY$9:$AY$557,0),0) -> 83365 | EH10: =ROUND(EG10+EF10,0) -> 250096 | EI10: =AL10-EF10 -> 0 | EJ10: =AM10-EG10 -> 0 | EK10: =ROUND((SUM(N10:P10)+W10+X10+T10+U10+V10)/($J$3*8)*_xlfn.XLOOKUP(C10,[1]Overtime!$B$9:$B$557,[1]Overtime!$AO$9:$AO$557,0)*1.5,0) -> 250096 | EL10: =ROUND((SUM(N10:P10)+W10+X10+T10+U10+V10)/($J$3*8)*_xlfn.XLOOKUP(C10,[1]Overtime!$B$9:$B$557,[1]Overtime!$AP$9:$AP$557,0)*2,0) -> 0 | EM10: =AN10-EK10-EL10 -> 0 | EN10: =ROUND(Y10*W10/$J$3,0) -> 303846 | EO10: =DJ10-EN10 -> 0.15384615 | EP10: =IF(AI10=0,0,AI10-DK10-EN10) -> 0 | EQ10: 0 | ER10: =EQ10/4400000 -> 0
B11: =B10+1 -> 2 | C11: TIQN-1654 | D11: Đào Thị Bích Chương | E11: =IF(CW11="x","Probation",IF(CR11>0,"Resigned - Official","Official")) -> Resigned - Official | F11: =IF(H11="management","6421.11",0) -> 0 | G11: Preparation | H11: Indirect | I11: 2nd Process | J11: Preparation | K11: Supporting worker | L11: =M11 -> 6700000 | M11: =N11+O11+P11+W11+X11+T11+U11+V11 -> 6700000 | N11: 4900000 | O11: 800000 | P11: 0 | Q11: 0 | R11: 300000 | S11: 0 | T11: 0 | U11: 0 | V11: 0 | W11: 1000000 | X11: 0 | Y11: =_xlfn.XLOOKUP(C11,[1]Timesheet!$B$9:$B$25,[1]Timesheet!$AO$9:$AO$25,0,,1) -> 4 | Z11: =ROUND(N11/$J$3*Y11,0) -> 753846 | AA11: =ROUND(O11/$J$3*(Y11+_xlfn.XLOOKUP(C11,[1]Timesheet!B:B,[1]Timesheet!BS:BS,0)),0) -> 123077 | AB11: =ROUND(IF(Y11>=8,P11,(P11/$J$3)*(Y11+_xlfn.XLOOKUP(C11,[1]Timesheet!B:B,[1]Timesheet!BS:BS,0))),0) -> 0 | AC11: =ROUND(IF(Y11>=14,Q11,(Q11/2)),0) -> 0 | AD11: =IF(_xlfn.XLOOKUP(Salary!C11,[1]Bus!B:B,[1]Bus!G:G,"",,-1)=1,0,ROUND((R11/$J$3)*ROUND(Y11+_xlfn.XLOOKUP(C11,[1]Timesheet!B:B,[1]Timesheet!BS:BS,0,,-1),0),0)) -> 46154 | AE11: =IF(Y11>0,S11,0) -> 0 | AF11: =ROUND(IF(Y11>=8,T11,(T11/$J$3)*(Y11+_xlfn.XLOOKUP(C11,[1]Timesheet!B:B,[1]Timesheet!BS:BS,0))),0) -> 0 | AG11: =ROUND(IF(Y11>=8,U11,(U11/$J$3)*(Y11+_xlfn.XLOOKUP(C11,[1]Timesheet!B:B,[1]Timesheet!BS:BS,0))),0) -> 0 | AH11: =ROUND(IF(OR(CR11>0,Y11<8),(V11/$J$3)*(Y11+_xlfn.XLOOKUP(C11,[1]Timesheet!B:B,[1]Timesheet!BS:BS,0)),V11),0) -> 0 | AI11: =ROUND(IF(DAY(CR11)=26,IF(Y11=0,0,IF(W11=0,0,IF(OR(-(DK11)>DJ11,-(DK11)=DJ11),0,DJ11+DK11+DS11))),IF(CR11>0,0,IF(Y11=0,0,IF(W11=0,0,IF(OR(-(DK11)>DJ11,-(DK11)=DJ11),0,DJ11+DK11+DS11))))),0) -> 0 | AJ11: =IF(Y11>0,ROUND(IF(LEN(CR11)>2,(X11/$J$3)*(Y11+_xlfn.XLOOKUP(C11,[1]Timesheet!B:B,[1]Timesheet!BS:BS,0)),X11),0),0) -> 0 | AK11: =_xlfn.XLOOKUP(C11,[1]Overtime!$B$7:$B$557,[1]Overtime!$AN$7:$AN$557,0) -> 2 | AL11: =ROUND(((SUM(N11:P11)+SUM(T11:X11))/($J$3*8))*_xlfn.XLOOKUP(C11,[1]Overtime!$B$9:$B$557,[1]Overtime!$AU$9:$AU$557,0),0) -> 64423 | AM11: =ROUND(((SUM(N11:P11)+SUM(T11:X11))/($J$3*8))*_xlfn.XLOOKUP(C11,[1]Overtime!$B$9:$B$557,[1]Overtime!$AY$9:$AY$557,0),0) -> 32212 | AN11: =ROUND(AM11+AL11,0) -> 96635 | AR11: =ROUND(_xlfn.XLOOKUP(C11,[1]Timesheet!$B$9:$B$458,[1]Timesheet!$BQ$9:$BQ$458,,,-1)*SUM(Salary!N11:P11,Salary!T11:X11)*20%/Salary!$J$3,0) -> 0 | AS11: 0 | AT11: 0 | AV11: =IF(CV11="x",IF(IF(CR11>0,$CW$3-_xlfn.XLOOKUP(C11,[1]Timesheet!B:B,[1]Timesheet!BW:BW,0,,-1),$CW$3-_xlfn.XLOOKUP(C11,[1]Timesheet!B:B,[1]Timesheet!BW:BW,0,,-1)-$EB$3)<14,ROUND(L11*20.5%+M11*1%,0),0),0) -> 0 | AW11: =CK11 -> -99259 | AX11: =CM11 -> 289904 | AZ11: 0 | BE11: =ROUND(SUM(Z11:AJ11)+AN11+AX11+AT11+AO11+AR11+AS11+AW11+AY11+AV11+AP11+AU11+AQ11+AZ11+BA11,0) -> 1210357 | BF11: =IF(OR(CW11="x",CR11>0),0,15500000) -> 0 | BG11: 0 | BI11: =IF(CV11="x",0,ROUND(L11*1.5%,0)) -> 100500 | BJ11: =IF(CV11="x",0,ROUND(IF(BH11>0,M11*1%,0),0)) -> 0 | BK11: =IF(CV11="x",0,ROUND(IF(BH11>0,38948,0),0)) -> 0 | BL11: =ROUND(IF(AC11>0,IF(ROUND((BE11+CX11+CY11-AE11-AN11-AW11-AC11)*15%,0)>AC11,BE11+CX11+CY11-AE11-AN11-AW11,BE11+CX11+CY11-AE11-AN11-AW11-AC11+ROUND((BE11+CX11+CY11-AE11-AN11-AW11-AC11)*15%,0)),BE11+CX11+CY11-AE11-AN11-AW11),0) -> 1212981 | BM11: =IF(OR(CW11="x",CR11>0),BL11,IF(BL11-BF11-BG11-SUM(BH11:BJ11)>0,BL11-BF11-BG11-SUM(BH11:BJ11),0)) -> 1212981 | BN11: =IF(OR(CW11="x",CR11>0),ROUND(IF(BM11>4999999,BM11*10%,0),0),ROUND(IF(BM11>100000000,((BM11-100000000)*0.35+20500000),IF(AND(BM11>60000000,BM11<=100000000),((BM11-60000000)*0.3+8500000),IF(AND(BM11>30000000,BM11<=60000000),((BM11-30000000)*0.2+2500000),IF(AND(BM11>10000000,BM11<=30000000),((BM11-10000000)*0.1+500000),IF(BM11<0,0,(BM11*0.05)))))),0)) -> 0 | BO11: =SUM(BH11:BK11,BN11) -> 100500 | BP11: =IF(CV11="x",0,ROUND(IF(BH11>0,L11*17.5%,0),0)) -> 0 | BQ11: =IF(CV11="x",0,ROUND(IF(BI11>0,L11*3%,0),0)) -> 201000 | BR11: =IF(CV11="x",0,ROUND(IF(BJ11>0,M11*1%,0),0)) -> 0 | BS11: =IF(CV11="x",0,ROUND(IF(BK11>0,L11*2%,0),0)) -> 0 | BW11: 0 | CG11: =ROUND(BE11-BO11+BZ11-BT11-BU11-BX11-BV11+BW11+BY11+CA11-CB11,0) -> 1109857 | CH11: =CG11+BN11+SUM(BH11:BK11)+SUM(BP11:BS11) -> 1411357 | CI11: =IF(BH11=0,0,ROUND((SUM(N11:X11)-(R11+S11))/12,0)) -> 0 | CJ11: -0.4 | CK11: =ROUND((M11/$CK$3*CJ11),0) -> -99259 | CL11: =6*1.5 -> 9 | CM11: =ROUND((M11/$J$3/8*CL11),0) -> 289904 | CO11: =CK11+CM11 -> 190645 | CP11: 45926 | CQ11: 45956 | CR11: 46209 | CS11: 0 | CT11: 0 | DC11: =_xlfn.XLOOKUP(C11,[1]Overtime!$B$8:$B$2327,[1]Overtime!$BA$8:$BA$2327,"",,-1) -> 0 | DD11: =_xlfn.XLOOKUP(C11,[1]Timesheet!$B$9:$B$2328,[1]Timesheet!$BS$9:$BS$2328,0,,-1) -> 0 | DE11: =_xlfn.XLOOKUP(C11,[1]Timesheet!$B$7:$B$616,[1]Timesheet!$BK$7:$BK$616,0)+_xlfn.XLOOKUP(C11,[1]Timesheet!$B$7:$B$616,[1]Timesheet!$AV$7:$AV$616,0)-_xlfn.XLOOKUP(C11,[1]Timesheet!$B$7:$B$616,[1]Timesheet!$AX$7:$AX$616,0)+_xlfn.XLOOKUP(C11,[1]Timesheet!$B$7:$B$616,[1]Timesheet!$AW$7:$AW$616,0)-_xlfn.XLOOKUP(C11,[1]Timesheet!$B$7:$B$616,[1]Timesheet!$AY$7:$AY$616,0) -> 0 | DF11: =DE11*(-100000) -> 0 | DG11: =_xlfn.XLOOKUP(C11,[1]Timesheet!$B$7:$B$616,[1]Timesheet!$BV$7:$BV$616,0)+_xlfn.XLOOKUP(C11,[1]Timesheet!$B$7:$B$616,[1]Timesheet!$AX$7:$AX$616,0)++_xlfn.XLOOKUP(C11,[1]Timesheet!$B$7:$B$616,[1]Timesheet!$AY$7:$AY$616,0) -> 4 | DH11: =IF(DG11>2,-1000000,IF(DG11=2,-500000,IF(DG11=1,-200000,0))) -> -1000000 | DI11: =_xlfn.XLOOKUP(C11,[1]Timesheet!$B$7:$B$616,[1]Timesheet!$AZ$7:$AZ$616,0)+_xlfn.XLOOKUP(C11,[1]Timesheet!$B$7:$B$616,[1]Timesheet!$BA$7:$BA$616,0) -> 0 | DJ11: =IF(CW11="x",IF((ROUND(Y11*W11/$J$3,0))<0,0,ROUND(Y11*W11/$J$3,0)),IF(OR(CR11>0,CS11>0,CT11>0),W11/$J$3*(Y11+_xlfn.XLOOKUP(C11,[1]Timesheet!B:B,[1]Timesheet!BS:BS,0,,-1)+_xlfn.XLOOKUP(C11,[1]Timesheet!B:B,[1]Timesheet!BU:BU,0,,-1)),IF(OR(DH11<0,DF11<0),IF(DI11>0,W11/$J$3*($J$3-DI11),W11),W11/$J$3*(Y11+_xlfn.XLOOKUP(C11,[1]Timesheet!B:B,[1]Timesheet!BS:BS,0,,-1)+_xlfn.XLOOKUP(C11,[1]Timesheet!B:B,[1]Timesheet!BU:BU,0,,-1))))) -> 153846.15 | DK11: =DF11+DH11 -> -1000000 | DL11: =_xlfn.XLOOKUP(C11,[1]Timesheet!$B$7:$B$565,[1]Timesheet!$BB$7:$BB$565,0) -> 0 | DM11: =_xlfn.XLOOKUP(C11,[1]Timesheet!$B$7:$B$565,[1]Timesheet!$BC$7:$BC$565,0) -> 0 | DN11: =_xlfn.XLOOKUP(C11,[1]Timesheet!$B$7:$B$565,[1]Timesheet!$BF$7:$BF$565,0) -> 0 | DO11: =_xlfn.XLOOKUP(C11,[1]Timesheet!$B$7:$B$565,[1]Timesheet!$BJ$7:$BJ$565,0) -> 4 | DP11: =DN11+DO11 -> 4 | DQ11: =_xlfn.XLOOKUP(C11,[1]Timesheet!$B$7:$B$565,[1]Timesheet!$BT$7:$BT$565,0) -> 21 | DR11: =_xlfn.XLOOKUP(C11,[1]Timesheet!$B$7:$B$565,[1]Timesheet!$BM$7:$BM$565,0) -> 0 | DS11: =W11/$J$3*DR11 -> 0 | DT11: =ROUND(IF(BH11>0,L11*$DT$7,0),0) -> 0 | DU11: =ROUND(IF(BI11>0,L11*$DU$7,0),0) -> 201000 | DV11: =ROUND(IF(BJ11>0,M11*$DV$7,0),0) -> 0 | DW11: =ROUND(IF(BK11>0,L11*$DW$7,0),0) -> 0 | DX11: =SUM(N11:X11) -> 7000000 | DY11: =SUM(O11:S11) -> 1100000 | DZ11: =SUM(W11:X11) -> 1000000 | EA11: =_xlfn.XLOOKUP(C11,[1]Timesheet!$B$7:$B$565,[1]Timesheet!$BI$7:$BI$565,0) -> 4 | EB11: =IF(AC11>0,ROUND((BE11+CX11+CY11-AE11-AN11-AW11-AC11)*15%,0),0) -> 0 | EC11: =AC11 -> 0 | ED11: =EB11-EC11 -> 0 | EE11: =BE11+CX11+CY11-AE11-AN11-AW11-BL11 -> 0 | EF11: =ROUND((SUM(N11:P11)+W11+X11+T11+U11+V11)/($J$3*8)*_xlfn.XLOOKUP(C11,[1]Overtime!$B$9:$B$557,[1]Overtime!$AU$9:$AU$557,0),0) -> 64423 | EG11: =ROUND(((SUM(N11:P11)+W11+X11+T11+U11+V11)/($J$3*8))*_xlfn.XLOOKUP(C11,[1]Overtime!$B$9:$B$557,[1]Overtime!$AY$9:$AY$557,0),0) -> 32212 | EH11: =ROUND(EG11+EF11,0) -> 96635 | EI11: =AL11-EF11 -> 0 | EJ11: =AM11-EG11 -> 0 | EK11: =ROUND((SUM(N11:P11)+W11+X11+T11+U11+V11)/($J$3*8)*_xlfn.XLOOKUP(C11,[1]Overtime!$B$9:$B$557,[1]Overtime!$AO$9:$AO$557,0)*1.5,0) -> 96635 | EL11: =ROUND((SUM(N11:P11)+W11+X11+T11+U11+V11)/($J$3*8)*_xlfn.XLOOKUP(C11,[1]Overtime!$B$9:$B$557,[1]Overtime!$AP$9:$AP$557,0)*2,0) -> 0 | EM11: =AN11-EK11-EL11 -> 0 | EN11: =ROUND(Y11*W11/$J$3,0) -> 153846 | EO11: =DJ11-EN11 -> 0.15384615 | EP11: =IF(AI11=0,0,AI11-DK11-EN11) -> 0 | EQ11: 0 | ER11: =EQ11/4400000 -> 0
B12: =B11+1 -> 3 | C12: TIQN-1663 | D12: Nguyễn Thị Hương | E12: =IF(CW12="x","Probation",IF(CR12>0,"Resigned - Official","Official")) -> Resigned - Official | F12: =IF(H12="management","6421.11",0) -> 0 | G12: Sewing | H12: Direct | I12: Line 15 | J12: Sewing | K12: Sewing worker | L12: =M12 -> 6500000 | M12: =N12+O12+P12+W12+X12+T12+U12+V12 -> 6500000 | N12: 4700000 | O12: 800000 | P12: 0 | Q12: 0 | R12: 300000 | S12: 0 | T12: 0 | U12: 0 | V12: 0 | W12: 1000000 | X12: 0 | Y12: =_xlfn.XLOOKUP(C12,[1]Timesheet!$B$9:$B$25,[1]Timesheet!$AO$9:$AO$25,0,,1) -> 0 | Z12: =ROUND(N12/$J$3*Y12,0) -> 0 | AA12: =ROUND(O12/$J$3*(Y12+_xlfn.XLOOKUP(C12,[1]Timesheet!B:B,[1]Timesheet!BS:BS,0)),0) -> 0 | AB12: =ROUND(IF(Y12>=8,P12,(P12/$J$3)*(Y12+_xlfn.XLOOKUP(C12,[1]Timesheet!B:B,[1]Timesheet!BS:BS,0))),0) -> 0 | AC12: =ROUND(IF(Y12>=14,Q12,(Q12/2)),0) -> 0 | AD12: =IF(_xlfn.XLOOKUP(Salary!C12,[1]Bus!B:B,[1]Bus!G:G,"",,-1)=1,0,ROUND((R12/$J$3)*ROUND(Y12+_xlfn.XLOOKUP(C12,[1]Timesheet!B:B,[1]Timesheet!BS:BS,0,,-1),0),0)) -> 0 | AE12: =IF(Y12>0,S12,0) -> 0 | AF12: =ROUND(IF(Y12>=8,T12,(T12/$J$3)*(Y12+_xlfn.XLOOKUP(C12,[1]Timesheet!B:B,[1]Timesheet!BS:BS,0))),0) -> 0 | AG12: =ROUND(IF(Y12>=8,U12,(U12/$J$3)*(Y12+_xlfn.XLOOKUP(C12,[1]Timesheet!B:B,[1]Timesheet!BS:BS,0))),0) -> 0 | AH12: =ROUND(IF(OR(CR12>0,Y12<8),(V12/$J$3)*(Y12+_xlfn.XLOOKUP(C12,[1]Timesheet!B:B,[1]Timesheet!BS:BS,0)),V12),0) -> 0 | AI12: =ROUND(IF(DAY(CR12)=26,IF(Y12=0,0,IF(W12=0,0,IF(OR(-(DK12)>DJ12,-(DK12)=DJ12),0,DJ12+DK12+DS12))),IF(CR12>0,0,IF(Y12=0,0,IF(W12=0,0,IF(OR(-(DK12)>DJ12,-(DK12)=DJ12),0,DJ12+DK12+DS12))))),0) -> 0 | AJ12: =IF(Y12>0,ROUND(IF(LEN(CR12)>2,(X12/$J$3)*(Y12+_xlfn.XLOOKUP(C12,[1]Timesheet!B:B,[1]Timesheet!BS:BS,0)),X12),0),0) -> 0 | AK12: =_xlfn.XLOOKUP(C12,[1]Overtime!$B$7:$B$557,[1]Overtime!$AN$7:$AN$557,0) -> 0 | AL12: =ROUND(((SUM(N12:P12)+SUM(T12:X12))/($J$3*8))*_xlfn.XLOOKUP(C12,[1]Overtime!$B$9:$B$557,[1]Overtime!$AU$9:$AU$557,0),0) -> 0 | AM12: =ROUND(((SUM(N12:P12)+SUM(T12:X12))/($J$3*8))*_xlfn.XLOOKUP(C12,[1]Overtime!$B$9:$B$557,[1]Overtime!$AY$9:$AY$557,0),0) -> 0 | AN12: =ROUND(AM12+AL12,0) -> 0 | AR12: =ROUND(_xlfn.XLOOKUP(C12,[1]Timesheet!$B$9:$B$458,[1]Timesheet!$BQ$9:$BQ$458,,,-1)*SUM(Salary!N12:P12,Salary!T12:X12)*20%/Salary!$J$3,0) -> 0 | AS12: 0 | AT12: 0 | AV12: =IF(CV12="x",IF(IF(CR12>0,$CW$3-_xlfn.XLOOKUP(C12,[1]Timesheet!B:B,[1]Timesheet!BW:BW,0,,-1),$CW$3-_xlfn.XLOOKUP(C12,[1]Timesheet!B:B,[1]Timesheet!BW:BW,0,,-1)-$EB$3)<14,ROUND(L12*20.5%+M12*1%,0),0),0) -> 0 | AW12: =CK12 -> 264815 | AX12: =CM12 -> 281250 | AZ12: 0 | BE12: =ROUND(SUM(Z12:AJ12)+AN12+AX12+AT12+AO12+AR12+AS12+AW12+AY12+AV12+AP12+AU12+AQ12+AZ12+BA12,0) -> 546065 | BF12: =IF(OR(CW12="x",CR12>0),0,15500000) -> 0 | BG12: 0 | BJ12: =IF(CV12="x",0,ROUND(IF(BH12>0,M12*1%,0),0)) -> 0 | BK12: =IF(CV12="x",0,ROUND(IF(BH12>0,38948,0),0)) -> 0 | BL12: =ROUND(IF(AC12>0,IF(ROUND((BE12+CX12+CY12-AE12-AN12-AW12-AC12)*15%,0)>AC12,BE12+CX12+CY12-AE12-AN12-AW12,BE12+CX12+CY12-AE12-AN12-AW12-AC12+ROUND((BE12+CX12+CY12-AE12-AN12-AW12-AC12)*15%,0)),BE12+CX12+CY12-AE12-AN12-AW12),0) -> 281250 | BM12: =IF(OR(CW12="x",CR12>0),BL12,IF(BL12-BF12-BG12-SUM(BH12:BJ12)>0,BL12-BF12-BG12-SUM(BH12:BJ12),0)) -> 281250 | BN12: =IF(OR(CW12="x",CR12>0),ROUND(IF(BM12>4999999,BM12*10%,0),0),ROUND(IF(BM12>100000000,((BM12-100000000)*0.35+20500000),IF(AND(BM12>60000000,BM12<=100000000),((BM12-60000000)*0.3+8500000),IF(AND(BM12>30000000,BM12<=60000000),((BM12-30000000)*0.2+2500000),IF(AND(BM12>10000000,BM12<=30000000),((BM12-10000000)*0.1+500000),IF(BM12<0,0,(BM12*0.05)))))),0)) -> 0 | BO12: =SUM(BH12:BK12,BN12) -> 0 | BP12: =IF(CV12="x",0,ROUND(IF(BH12>0,L12*17.5%,0),0)) -> 0 | BQ12: =IF(CV12="x",0,ROUND(IF(BI12>0,L12*3%,0),0)) -> 0 | BR12: =IF(CV12="x",0,ROUND(IF(BJ12>0,M12*1%,0),0)) -> 0 | BS12: =IF(CV12="x",0,ROUND(IF(BK12>0,L12*2%,0),0)) -> 0 | BW12: 0 | CB12: 546065 | CG12: =ROUND(BE12-BO12+BZ12-BT12-BU12-BX12-BV12+BW12+BY12+CA12-CB12,0) -> 0 | CH12: =CG12+BN12+SUM(BH12:BK12)+SUM(BP12:BS12) -> 0 | CI12: =IF(BH12=0,0,ROUND((SUM(N12:X12)-(R12+S12))/12,0)) -> 0 | CJ12: 1.1 | CK12: =ROUND((M12/$CK$3*CJ12),0) -> 264815 | CL12: =6*1.5 -> 9 | CM12: =ROUND((M12/$J$3/8*CL12),0) -> 281250 | CO12: =CK12+CM12 -> 546065 | CP12: 45930 | CQ12: 45960 | CR12: 46207 | CS12: 0 | CT12: 0 | CU12: x | DC12: =_xlfn.XLOOKUP(C12,[1]Overtime!$B$8:$B$2327,[1]Overtime!$BA$8:$BA$2327,"",,-1) -> 0 | DD12: =_xlfn.XLOOKUP(C12,[1]Timesheet!$B$9:$B$2328,[1]Timesheet!$BS$9:$BS$2328,0,,-1) -> 0 | DE12: =_xlfn.XLOOKUP(C12,[1]Timesheet!$B$7:$B$616,[1]Timesheet!$BK$7:$BK$616,0)+_xlfn.XLOOKUP(C12,[1]Timesheet!$B$7:$B$616,[1]Timesheet!$AV$7:$AV$616,0)-_xlfn.XLOOKUP(C12,[1]Timesheet!$B$7:$B$616,[1]Timesheet!$AX$7:$AX$616,0)+_xlfn.XLOOKUP(C12,[1]Timesheet!$B$7:$B$616,[1]Timesheet!$AW$7:$AW$616,0)-_xlfn.XLOOKUP(C12,[1]Timesheet!$B$7:$B$616,[1]Timesheet!$AY$7:$AY$616,0) -> 0 | DF12: =DE12*(-100000) -> 0 | DG12: =_xlfn.XLOOKUP(C12,[1]Timesheet!$B$7:$B$616,[1]Timesheet!$BV$7:$BV$616,0)+_xlfn.XLOOKUP(C12,[1]Timesheet!$B$7:$B$616,[1]Timesheet!$AX$7:$AX$616,0)++_xlfn.XLOOKUP(C12,[1]Timesheet!$B$7:$B$616,[1]Timesheet!$AY$7:$AY$616,0) -> 7 | DH12: =IF(DG12>2,-1000000,IF(DG12=2,-500000,IF(DG12=1,-200000,0))) -> -1000000 | DI12: =_xlfn.XLOOKUP(C12,[1]Timesheet!$B$7:$B$616,[1]Timesheet!$AZ$7:$AZ$616,0)+_xlfn.XLOOKUP(C12,[1]Timesheet!$B$7:$B$616,[1]Timesheet!$BA$7:$BA$616,0) -> 0 | DJ12: =IF(CW12="x",IF((ROUND(Y12*W12/$J$3,0))<0,0,ROUND(Y12*W12/$J$3,0)),IF(OR(CR12>0,CS12>0,CT12>0),W12/$J$3*(Y12+_xlfn.XLOOKUP(C12,[1]Timesheet!B:B,[1]Timesheet!BS:BS,0,,-1)+_xlfn.XLOOKUP(C12,[1]Timesheet!B:B,[1]Timesheet!BU:BU,0,,-1)),IF(OR(DH12<0,DF12<0),IF(DI12>0,W12/$J$3*($J$3-DI12),W12),W12/$J$3*(Y12+_xlfn.XLOOKUP(C12,[1]Timesheet!B:B,[1]Timesheet!BS:BS,0,,-1)+_xlfn.XLOOKUP(C12,[1]Timesheet!B:B,[1]Timesheet!BU:BU,0,,-1))))) -> 0 | DK12: =DF12+DH12 -> -1000000 | DL12: =_xlfn.XLOOKUP(C12,[1]Timesheet!$B$7:$B$565,[1]Timesheet!$BB$7:$BB$565,0) -> 0 | DM12: =_xlfn.XLOOKUP(C12,[1]Timesheet!$B$7:$B$565,[1]Timesheet!$BC$7:$BC$565,0) -> 0 | DN12: =_xlfn.XLOOKUP(C12,[1]Timesheet!$B$7:$B$565,[1]Timesheet!$BF$7:$BF$565,0) -> 0 | DO12: =_xlfn.XLOOKUP(C12,[1]Timesheet!$B$7:$B$565,[1]Timesheet!$BJ$7:$BJ$565,0) -> 3 | DP12: =DN12+DO12 -> 3 | DQ12: =_xlfn.XLOOKUP(C12,[1]Timesheet!$B$7:$B$565,[1]Timesheet!$BT$7:$BT$565,0) -> 21 | DR12: =_xlfn.XLOOKUP(C12,[1]Timesheet!$B$7:$B$565,[1]Timesheet!$BM$7:$BM$565,0) -> 0 | DS12: =W12/$J$3*DR12 -> 0 | DT12: =ROUND(IF(BH12>0,L12*$DT$7,0),0) -> 0 | DU12: =ROUND(IF(BI12>0,L12*$DU$7,0),0) -> 0 | DV12: =ROUND(IF(BJ12>0,M12*$DV$7,0),0) -> 0 | DW12: =ROUND(IF(BK12>0,L12*$DW$7,0),0) -> 0 | DX12: =SUM(N12:X12) -> 6800000 | DY12: =SUM(O12:S12) -> 1100000 | DZ12: =SUM(W12:X12) -> 1000000 | EA12: =_xlfn.XLOOKUP(C12,[1]Timesheet!$B$7:$B$565,[1]Timesheet!$BI$7:$BI$565,0) -> 7 | EB12: =IF(AC12>0,ROUND((BE12+CX12+CY12-AE12-AN12-AW12-AC12)*15%,0),0) -> 0 | EC12: =AC12 -> 0 | ED12: =EB12-EC12 -> 0 | EE12: =BE12+CX12+CY12-AE12-AN12-AW12-BL12 -> 0 | EF12: =ROUND((SUM(N12:P12)+W12+X12+T12+U12+V12)/($J$3*8)*_xlfn.XLOOKUP(C12,[1]Overtime!$B$9:$B$557,[1]Overtime!$AU$9:$AU$557,0),0) -> 0 | EG12: =ROUND(((SUM(N12:P12)+W12+X12+T12+U12+V12)/($J$3*8))*_xlfn.XLOOKUP(C12,[1]Overtime!$B$9:$B$557,[1]Overtime!$AY$9:$AY$557,0),0) -> 0 | EH12: =ROUND(EG12+EF12,0) -> 0 | EI12: =AL12-EF12 -> 0 | EJ12: =AM12-EG12 -> 0 | EK12: =ROUND((SUM(N12:P12)+W12+X12+T12+U12+V12)/($J$3*8)*_xlfn.XLOOKUP(C12,[1]Overtime!$B$9:$B$557,[1]Overtime!$AO$9:$AO$557,0)*1.5,0) -> 0 | EL12: =ROUND((SUM(N12:P12)+W12+X12+T12+U12+V12)/($J$3*8)*_xlfn.XLOOKUP(C12,[1]Overtime!$B$9:$B$557,[1]Overtime!$AP$9:$AP$557,0)*2,0) -> 0 | EM12: =AN12-EK12-EL12 -> 0 | EN12: =ROUND(Y12*W12/$J$3,0) -> 0 | EO12: =DJ12-EN12 -> 0 | EP12: =IF(AI12=0,0,AI12-DK12-EN12) -> 0 | EQ12: 0 | ER12: =EQ12/4400000 -> 0
B13: =B12+1 -> 4 | C13: TIQN-2062 | D13: Mai Thị Tú Nhi | E13: =IF(CW13="x","Probation",IF(CR13>0,"Resigned - Official","Official")) -> Resigned - Official | F13: =IF(H13="management","6421.11",0) -> 0 | G13: Sewing | H13: Direct | I13: Line 02 | J13: Sewing | K13: Sewing worker | L13: =M13 -> 6500000 | M13: =N13+O13+P13+W13+X13+T13+U13+V13 -> 6500000 | N13: 5200000 | O13: 300000 | P13: 0 | Q13: 0 | R13: 300000 | S13: 0 | T13: 0 | U13: 0 | V13: 0 | W13: 1000000 | X13: 0 | Y13: =_xlfn.XLOOKUP(C13,[1]Timesheet!$B$9:$B$25,[1]Timesheet!$AO$9:$AO$25,0,,1) -> 0 | Z13: =ROUND(N13/$J$3*Y13,0) -> 0 | AA13: =ROUND(O13/$J$3*(Y13+_xlfn.XLOOKUP(C13,[1]Timesheet!B:B,[1]Timesheet!BS:BS,0)),0) -> 0 | AB13: =ROUND(IF(Y13>=8,P13,(P13/$J$3)*(Y13+_xlfn.XLOOKUP(C13,[1]Timesheet!B:B,[1]Timesheet!BS:BS,0))),0) -> 0 | AC13: =ROUND(IF(Y13>=14,Q13,(Q13/2)),0) -> 0 | AD13: =IF(_xlfn.XLOOKUP(Salary!C13,[1]Bus!B:B,[1]Bus!G:G,"",,-1)=1,0,ROUND((R13/$J$3)*ROUND(Y13+_xlfn.XLOOKUP(C13,[1]Timesheet!B:B,[1]Timesheet!BS:BS,0,,-1),0),0)) -> 0 | AE13: =IF(Y13>0,S13,0) -> 0 | AF13: =ROUND(IF(Y13>=8,T13,(T13/$J$3)*(Y13+_xlfn.XLOOKUP(C13,[1]Timesheet!B:B,[1]Timesheet!BS:BS,0))),0) -> 0 | AG13: =ROUND(IF(Y13>=8,U13,(U13/$J$3)*(Y13+_xlfn.XLOOKUP(C13,[1]Timesheet!B:B,[1]Timesheet!BS:BS,0))),0) -> 0 | AH13: =ROUND(IF(OR(CR13>0,Y13<8),(V13/$J$3)*(Y13+_xlfn.XLOOKUP(C13,[1]Timesheet!B:B,[1]Timesheet!BS:BS,0)),V13),0) -> 0 | AI13: =ROUND(IF(DAY(CR13)=26,IF(Y13=0,0,IF(W13=0,0,IF(OR(-(DK13)>DJ13,-(DK13)=DJ13),0,DJ13+DK13+DS13))),IF(CR13>0,0,IF(Y13=0,0,IF(W13=0,0,IF(OR(-(DK13)>DJ13,-(DK13)=DJ13),0,DJ13+DK13+DS13))))),0) -> 0 | AJ13: =IF(Y13>0,ROUND(IF(LEN(CR13)>2,(X13/$J$3)*(Y13+_xlfn.XLOOKUP(C13,[1]Timesheet!B:B,[1]Timesheet!BS:BS,0)),X13),0),0) -> 0 | AK13: =_xlfn.XLOOKUP(C13,[1]Overtime!$B$7:$B$557,[1]Overtime!$AN$7:$AN$557,0) -> 0 | AL13: =ROUND(((SUM(N13:P13)+SUM(T13:X13))/($J$3*8))*_xlfn.XLOOKUP(C13,[1]Overtime!$B$9:$B$557,[1]Overtime!$AU$9:$AU$557,0),0) -> 0 | AM13: =ROUND(((SUM(N13:P13)+SUM(T13:X13))/($J$3*8))*_xlfn.XLOOKUP(C13,[1]Overtime!$B$9:$B$557,[1]Overtime!$AY$9:$AY$557,0),0) -> 0 | AN13: =ROUND(AM13+AL13,0) -> 0 | AR13: =ROUND(_xlfn.XLOOKUP(C13,[1]Timesheet!$B$9:$B$458,[1]Timesheet!$BQ$9:$BQ$458,,,-1)*SUM(Salary!N13:P13,Salary!T13:X13)*20%/Salary!$J$3,0) -> 0 | AS13: 20000 | AT13: 0 | AV13: =IF(CV13="x",IF(IF(CR13>0,$CW$3-_xlfn.XLOOKUP(C13,[1]Timesheet!B:B,[1]Timesheet!BW:BW,0,,-1),$CW$3-_xlfn.XLOOKUP(C13,[1]Timesheet!B:B,[1]Timesheet!BW:BW,0,,-1)-$EB$3)<14,ROUND(L13*20.5%+M13*1%,0),0),0) -> 0 | AW13: =CK13 -> 0 | AX13: =CM13 -> 140625 | AZ13: 0 | BE13: =ROUND(SUM(Z13:AJ13)+AN13+AX13+AT13+AO13+AR13+AS13+AW13+AY13+AV13+AP13+AU13+AQ13+AZ13+BA13,0) -> 160625 | BF13: =IF(OR(CW13="x",CR13>0),0,15500000) -> 0 | BG13: 0 | BI13: =IF(CV13="x",0,ROUND(L13*1.5%,0)) -> 97500 | BJ13: =IF(CV13="x",0,ROUND(IF(BH13>0,M13*1%,0),0)) -> 0 | BK13: =IF(CV13="x",0,ROUND(IF(BH13>0,38948,0),0)) -> 0 | BL13: =ROUND(IF(AC13>0,IF(ROUND((BE13+CX13+CY13-AE13-AN13-AW13-AC13)*15%,0)>AC13,BE13+CX13+CY13-AE13-AN13-AW13,BE13+CX13+CY13-AE13-AN13-AW13-AC13+ROUND((BE13+CX13+CY13-AE13-AN13-AW13-AC13)*15%,0)),BE13+CX13+CY13-AE13-AN13-AW13),0) -> 160625 | BM13: =IF(OR(CW13="x",CR13>0),BL13,IF(BL13-BF13-BG13-SUM(BH13:BJ13)>0,BL13-BF13-BG13-SUM(BH13:BJ13),0)) -> 160625 | BN13: =IF(OR(CW13="x",CR13>0),ROUND(IF(BM13>4999999,BM13*10%,0),0),ROUND(IF(BM13>100000000,((BM13-100000000)*0.35+20500000),IF(AND(BM13>60000000,BM13<=100000000),((BM13-60000000)*0.3+8500000),IF(AND(BM13>30000000,BM13<=60000000),((BM13-30000000)*0.2+2500000),IF(AND(BM13>10000000,BM13<=30000000),((BM13-10000000)*0.1+500000),IF(BM13<0,0,(BM13*0.05)))))),0)) -> 0 | BO13: =SUM(BH13:BK13,BN13) -> 97500 | BP13: =IF(CV13="x",0,ROUND(IF(BH13>0,L13*17.5%,0),0)) -> 0 | BQ13: =IF(CV13="x",0,ROUND(IF(BI13>0,L13*3%,0),0)) -> 195000 | BR13: =IF(CV13="x",0,ROUND(IF(BJ13>0,M13*1%,0),0)) -> 0 | BS13: =IF(CV13="x",0,ROUND(IF(BK13>0,L13*2%,0),0)) -> 0 | BW13: 0 | CG13: =ROUND(BE13-BO13+BZ13-BT13-BU13-BX13-BV13+BW13+BY13+CA13-CB13,0) -> 63125 | CH13: =CG13+BN13+SUM(BH13:BK13)+SUM(BP13:BS13) -> 355625 | CI13: =IF(BH13=0,0,ROUND((SUM(N13:X13)-(R13+S13))/12,0)) -> 0 | CJ13: 0 | CK13: =ROUND((M13/$CK$3*CJ13),0) -> 0 | CL13: =3*1.5 -> 4.5 | CM13: =ROUND((M13/$J$3/8*CL13),0) -> 140625 | CO13: =CK13+CM13 -> 140625 | CP13: 46133 | CQ13: 46163 | CR13: 46207 | CS13: 0 | CT13: 0 | DC13: =_xlfn.XLOOKUP(C13,[1]Overtime!$B$8:$B$2327,[1]Overtime!$BA$8:$BA$2327,"",,-1) -> 0 | DD13: =_xlfn.XLOOKUP(C13,[1]Timesheet!$B$9:$B$2328,[1]Timesheet!$BS$9:$BS$2328,0,,-1) -> 0 | DE13: =_xlfn.XLOOKUP(C13,[1]Timesheet!$B$7:$B$616,[1]Timesheet!$BK$7:$BK$616,0)+_xlfn.XLOOKUP(C13,[1]Timesheet!$B$7:$B$616,[1]Timesheet!$AV$7:$AV$616,0)-_xlfn.XLOOKUP(C13,[1]Timesheet!$B$7:$B$616,[1]Timesheet!$AX$7:$AX$616,0)+_xlfn.XLOOKUP(C13,[1]Timesheet!$B$7:$B$616,[1]Timesheet!$AW$7:$AW$616,0)-_xlfn.XLOOKUP(C13,[1]Timesheet!$B$7:$B$616,[1]Timesheet!$AY$7:$AY$616,0) -> 0 | DF13: =DE13*(-100000) -> 0 | DG13: =_xlfn.XLOOKUP(C13,[1]Timesheet!$B$7:$B$616,[1]Timesheet!$BV$7:$BV$616,0)+_xlfn.XLOOKUP(C13,[1]Timesheet!$B$7:$B$616,[1]Timesheet!$AX$7:$AX$616,0)++_xlfn.XLOOKUP(C13,[1]Timesheet!$B$7:$B$616,[1]Timesheet!$AY$7:$AY$616,0) -> 7 | DH13: =IF(DG13>2,-1000000,IF(DG13=2,-500000,IF(DG13=1,-200000,0))) -> -1000000 | DI13: =_xlfn.XLOOKUP(C13,[1]Timesheet!$B$7:$B$616,[1]Timesheet!$AZ$7:$AZ$616,0)+_xlfn.XLOOKUP(C13,[1]Timesheet!$B$7:$B$616,[1]Timesheet!$BA$7:$BA$616,0) -> 0 | DJ13: =IF(CW13="x",IF((ROUND(Y13*W13/$J$3,0))<0,0,ROUND(Y13*W13/$J$3,0)),IF(OR(CR13>0,CS13>0,CT13>0),W13/$J$3*(Y13+_xlfn.XLOOKUP(C13,[1]Timesheet!B:B,[1]Timesheet!BS:BS,0,,-1)+_xlfn.XLOOKUP(C13,[1]Timesheet!B:B,[1]Timesheet!BU:BU,0,,-1)),IF(OR(DH13<0,DF13<0),IF(DI13>0,W13/$J$3*($J$3-DI13),W13),W13/$J$3*(Y13+_xlfn.XLOOKUP(C13,[1]Timesheet!B:B,[1]Timesheet!BS:BS,0,,-1)+_xlfn.XLOOKUP(C13,[1]Timesheet!B:B,[1]Timesheet!BU:BU,0,,-1))))) -> 0 | DK13: =DF13+DH13 -> -1000000 | DL13: =_xlfn.XLOOKUP(C13,[1]Timesheet!$B$7:$B$565,[1]Timesheet!$BB$7:$BB$565,0) -> 0 | DM13: =_xlfn.XLOOKUP(C13,[1]Timesheet!$B$7:$B$565,[1]Timesheet!$BC$7:$BC$565,0) -> 0 | DN13: =_xlfn.XLOOKUP(C13,[1]Timesheet!$B$7:$B$565,[1]Timesheet!$BF$7:$BF$565,0) -> 0 | DO13: =_xlfn.XLOOKUP(C13,[1]Timesheet!$B$7:$B$565,[1]Timesheet!$BJ$7:$BJ$565,0) -> 3 | DP13: =DN13+DO13 -> 3 | DQ13: =_xlfn.XLOOKUP(C13,[1]Timesheet!$B$7:$B$565,[1]Timesheet!$BT$7:$BT$565,0) -> 21 | DR13: =_xlfn.XLOOKUP(C13,[1]Timesheet!$B$7:$B$565,[1]Timesheet!$BM$7:$BM$565,0) -> 0 | DS13: =W13/$J$3*DR13 -> 0 | DT13: =ROUND(IF(BH13>0,L13*$DT$7,0),0) -> 0 | DU13: =ROUND(IF(BI13>0,L13*$DU$7,0),0) -> 195000 | DV13: =ROUND(IF(BJ13>0,M13*$DV$7,0),0) -> 0 | DW13: =ROUND(IF(BK13>0,L13*$DW$7,0),0) -> 0 | DX13: =SUM(N13:X13) -> 6800000 | DY13: =SUM(O13:S13) -> 600000 | DZ13: =SUM(W13:X13) -> 1000000 | EA13: =_xlfn.XLOOKUP(C13,[1]Timesheet!$B$7:$B$565,[1]Timesheet!$BI$7:$BI$565,0) -> 7 | EB13: =IF(AC13>0,ROUND((BE13+CX13+CY13-AE13-AN13-AW13-AC13)*15%,0),0) -> 0 | EC13: =AC13 -> 0 | ED13: =EB13-EC13 -> 0 | EE13: =BE13+CX13+CY13-AE13-AN13-AW13-BL13 -> 0 | EF13: =ROUND((SUM(N13:P13)+W13+X13+T13+U13+V13)/($J$3*8)*_xlfn.XLOOKUP(C13,[1]Overtime!$B$9:$B$557,[1]Overtime!$AU$9:$AU$557,0),0) -> 0 | EG13: =ROUND(((SUM(N13:P13)+W13+X13+T13+U13+V13)/($J$3*8))*_xlfn.XLOOKUP(C13,[1]Overtime!$B$9:$B$557,[1]Overtime!$AY$9:$AY$557,0),0) -> 0 | EH13: =ROUND(EG13+EF13,0) -> 0 | EI13: =AL13-EF13 -> 0 | EJ13: =AM13-EG13 -> 0 | EK13: =ROUND((SUM(N13:P13)+W13+X13+T13+U13+V13)/($J$3*8)*_xlfn.XLOOKUP(C13,[1]Overtime!$B$9:$B$557,[1]Overtime!$AO$9:$AO$557,0)*1.5,0) -> 0 | EL13: =ROUND((SUM(N13:P13)+W13+X13+T13+U13+V13)/($J$3*8)*_xlfn.XLOOKUP(C13,[1]Overtime!$B$9:$B$557,[1]Overtime!$AP$9:$AP$557,0)*2,0) -> 0 | EM13: =AN13-EK13-EL13 -> 0 | EN13: =ROUND(Y13*W13/$J$3,0) -> 0 | EO13: =DJ13-EN13 -> 0 | EP13: =IF(AI13=0,0,AI13-DK13-EN13) -> 0 | EQ13: 0 | ER13: =EQ13/4400000 -> 0
B14: =B13+1 -> 5 | C14: TIQN-2181 | D14: Ngô Minh Vinh | E14: =IF(CW14="x","Probation",IF(CR14>0,"Resigned - Official","Official")) -> Probation | F14: =IF(H14="management","6421.11",0) -> 0 | G14: Preparation | H14: Indirect | I14: 2nd Process | J14: Preparation | K14: Supporting worker | L14: =M14 -> 6700000 | M14: =N14+O14+P14+W14+X14+T14+U14+V14 -> 6700000 | N14: 5400000 | O14: 300000 | P14: 0 | Q14: 0 | R14: 300000 | S14: 0 | T14: 0 | U14: 0 | V14: 0 | W14: 1000000 | X14: 0 | Y14: =_xlfn.XLOOKUP(C14,[1]Timesheet!$B$9:$B$25,[1]Timesheet!$AO$9:$AO$25,0,,1) -> 0.5 | Z14: =ROUND(N14/$J$3*Y14,0) -> 103846 | AA14: =ROUND(O14/$J$3*(Y14+_xlfn.XLOOKUP(C14,[1]Timesheet!B:B,[1]Timesheet!BS:BS,0)),0) -> 5769 | AB14: =ROUND(IF(Y14>=8,P14,(P14/$J$3)*(Y14+_xlfn.XLOOKUP(C14,[1]Timesheet!B:B,[1]Timesheet!BS:BS,0))),0) -> 0 | AC14: =ROUND(IF(Y14>=14,Q14,(Q14/2)),0) -> 0 | AD14: =IF(_xlfn.XLOOKUP(Salary!C14,[1]Bus!B:B,[1]Bus!G:G,"",,-1)=1,0,ROUND((R14/$J$3)*ROUND(Y14+_xlfn.XLOOKUP(C14,[1]Timesheet!B:B,[1]Timesheet!BS:BS,0,,-1),0),0)) -> 11538 | AE14: =IF(Y14>0,S14,0) -> 0 | AF14: =ROUND(IF(Y14>=8,T14,(T14/$J$3)*(Y14+_xlfn.XLOOKUP(C14,[1]Timesheet!B:B,[1]Timesheet!BS:BS,0))),0) -> 0 | AG14: =ROUND(IF(Y14>=8,U14,(U14/$J$3)*(Y14+_xlfn.XLOOKUP(C14,[1]Timesheet!B:B,[1]Timesheet!BS:BS,0))),0) -> 0 | AH14: =ROUND(IF(OR(CR14>0,Y14<8),(V14/$J$3)*(Y14+_xlfn.XLOOKUP(C14,[1]Timesheet!B:B,[1]Timesheet!BS:BS,0)),V14),0) -> 0 | AI14: =ROUND(IF(DAY(CR14)=26,IF(Y14=0,0,IF(W14=0,0,IF(OR(-(DK14)>DJ14,-(DK14)=DJ14),0,DJ14+DK14+DS14))),IF(CR14>0,0,IF(Y14=0,0,IF(W14=0,0,IF(OR(-(DK14)>DJ14,-(DK14)=DJ14),0,DJ14+DK14+DS14))))),0) -> 0 | AJ14: =IF(Y14>0,ROUND(IF(LEN(CR14)>2,(X14/$J$3)*(Y14+_xlfn.XLOOKUP(C14,[1]Timesheet!B:B,[1]Timesheet!BS:BS,0)),X14),0),0) -> 0 | AK14: =_xlfn.XLOOKUP(C14,[1]Overtime!$B$7:$B$557,[1]Overtime!$AN$7:$AN$557,0) -> 0 | AL14: =ROUND(((SUM(N14:P14)+SUM(T14:X14))/($J$3*8))*_xlfn.XLOOKUP(C14,[1]Overtime!$B$9:$B$557,[1]Overtime!$AU$9:$AU$557,0),0) -> 0 | AM14: =ROUND(((SUM(N14:P14)+SUM(T14:X14))/($J$3*8))*_xlfn.XLOOKUP(C14,[1]Overtime!$B$9:$B$557,[1]Overtime!$AY$9:$AY$557,0),0) -> 0 | AN14: =ROUND(AM14+AL14,0) -> 0 | AR14: =ROUND(_xlfn.XLOOKUP(C14,[1]Timesheet!$B$9:$B$458,[1]Timesheet!$BQ$9:$BQ$458,,,-1)*SUM(Salary!N14:P14,Salary!T14:X14)*20%/Salary!$J$3,0) -> 0 | AS14: 0 | AT14: 0 | AV14: =IF(CV14="x",IF(IF(CR14>0,$CW$3-_xlfn.XLOOKUP(C14,[1]Timesheet!B:B,[1]Timesheet!BW:BW,0,,-1),$CW$3-_xlfn.XLOOKUP(C14,[1]Timesheet!B:B,[1]Timesheet!BW:BW,0,,-1)-$EB$3)<14,ROUND(L14*20.5%+M14*1%,0),0),0) -> 0 | AW14: =CK14 -> 0 | AX14: =CM14 -> 0 | AZ14: 0 | BE14: =ROUND(SUM(Z14:AJ14)+AN14+AX14+AT14+AO14+AR14+AS14+AW14+AY14+AV14+AP14+AU14+AQ14+AZ14+BA14,0) -> 121153 | BF14: =IF(OR(CW14="x",CR14>0),0,15500000) -> 0 | BG14: 0 | BJ14: =IF(CV14="x",0,ROUND(IF(BH14>0,M14*1%,0),0)) -> 0 | BK14: =IF(CV14="x",0,ROUND(IF(BH14>0,38948,0),0)) -> 0 | BL14: =ROUND(IF(AC14>0,IF(ROUND((BE14+CX14+CY14-AE14-AN14-AW14-AC14)*15%,0)>AC14,BE14+CX14+CY14-AE14-AN14-AW14,BE14+CX14+CY14-AE14-AN14-AW14-AC14+ROUND((BE14+CX14+CY14-AE14-AN14-AW14-AC14)*15%,0)),BE14+CX14+CY14-AE14-AN14-AW14),0) -> 121153 | BM14: =IF(OR(CW14="x",CR14>0),BL14,IF(BL14-BF14-BG14-SUM(BH14:BJ14)>0,BL14-BF14-BG14-SUM(BH14:BJ14),0)) -> 121153 | BN14: =IF(OR(CW14="x",CR14>0),ROUND(IF(BM14>4999999,BM14*10%,0),0),ROUND(IF(BM14>100000000,((BM14-100000000)*0.35+20500000),IF(AND(BM14>60000000,BM14<=100000000),((BM14-60000000)*0.3+8500000),IF(AND(BM14>30000000,BM14<=60000000),((BM14-30000000)*0.2+2500000),IF(AND(BM14>10000000,BM14<=30000000),((BM14-10000000)*0.1+500000),IF(BM14<0,0,(BM14*0.05)))))),0)) -> 0 | BO14: =SUM(BH14:BK14,BN14) -> 0 | BP14: =IF(CV14="x",0,ROUND(IF(BH14>0,L14*17.5%,0),0)) -> 0 | BQ14: =IF(CV14="x",0,ROUND(IF(BI14>0,L14*3%,0),0)) -> 0 | BR14: =IF(CV14="x",0,ROUND(IF(BJ14>0,M14*1%,0),0)) -> 0 | BS14: =IF(CV14="x",0,ROUND(IF(BK14>0,L14*2%,0),0)) -> 0 | BW14: 0 | CG14: =ROUND(BE14-BO14+BZ14-BT14-BU14-BX14-BV14+BW14+BY14+CA14-CB14,0) -> 121153 | CH14: =CG14+BN14+SUM(BH14:BK14)+SUM(BP14:BS14) -> 121153 | CI14: =IF(BH14=0,0,ROUND((SUM(N14:X14)-(R14+S14))/12,0)) -> 0 | CK14: =ROUND((M14/$CK$3*CJ14),0) -> 0 | CM14: =ROUND((M14/$J$3/8*CL14),0) -> 0 | CO14: =CK14+CM14 -> 0 | CP14: 46178 | CQ14: 46208 | CR14: 46202 | CS14: 0 | CT14: 0 | CV14: x | CW14: x | DC14: =_xlfn.XLOOKUP(C14,[1]Overtime!$B$8:$B$2327,[1]Overtime!$BA$8:$BA$2327,"",,-1) -> 0 | DD14: =_xlfn.XLOOKUP(C14,[1]Timesheet!$B$9:$B$2328,[1]Timesheet!$BS$9:$BS$2328,0,,-1) -> 0 | DE14: =_xlfn.XLOOKUP(C14,[1]Timesheet!$B$7:$B$616,[1]Timesheet!$BK$7:$BK$616,0)+_xlfn.XLOOKUP(C14,[1]Timesheet!$B$7:$B$616,[1]Timesheet!$AV$7:$AV$616,0)-_xlfn.XLOOKUP(C14,[1]Timesheet!$B$7:$B$616,[1]Timesheet!$AX$7:$AX$616,0)+_xlfn.XLOOKUP(C14,[1]Timesheet!$B$7:$B$616,[1]Timesheet!$AW$7:$AW$616,0)-_xlfn.XLOOKUP(C14,[1]Timesheet!$B$7:$B$616,[1]Timesheet!$AY$7:$AY$616,0) -> 1 | DF14: =DE14*(-100000) -> -100000 | DG14: =_xlfn.XLOOKUP(C14,[1]Timesheet!$B$7:$B$616,[1]Timesheet!$BV$7:$BV$616,0)+_xlfn.XLOOKUP(C14,[1]Timesheet!$B$7:$B$616,[1]Timesheet!$AX$7:$AX$616,0)++_xlfn.XLOOKUP(C14,[1]Timesheet!$B$7:$B$616,[1]Timesheet!$AY$7:$AY$616,0) -> 1 | DH14: =IF(DG14>2,-1000000,IF(DG14=2,-500000,IF(DG14=1,-200000,0))) -> -200000 | DI14: =_xlfn.XLOOKUP(C14,[1]Timesheet!$B$7:$B$616,[1]Timesheet!$AZ$7:$AZ$616,0)+_xlfn.XLOOKUP(C14,[1]Timesheet!$B$7:$B$616,[1]Timesheet!$BA$7:$BA$616,0) -> 0 | DJ14: =IF(CW14="x",IF((ROUND(Y14*W14/$J$3,0))<0,0,ROUND(Y14*W14/$J$3,0)),IF(OR(CR14>0,CS14>0,CT14>0),W14/$J$3*(Y14+_xlfn.XLOOKUP(C14,[1]Timesheet!B:B,[1]Timesheet!BS:BS,0,,-1)+_xlfn.XLOOKUP(C14,[1]Timesheet!B:B,[1]Timesheet!BU:BU,0,,-1)),IF(OR(DH14<0,DF14<0),IF(DI14>0,W14/$J$3*($J$3-DI14),W14),W14/$J$3*(Y14+_xlfn.XLOOKUP(C14,[1]Timesheet!B:B,[1]Timesheet!BS:BS,0,,-1)+_xlfn.XLOOKUP(C14,[1]Timesheet!B:B,[1]Timesheet!BU:BU,0,,-1))))) -> 19231 | DK14: =DF14+DH14 -> -300000 | DL14: =_xlfn.XLOOKUP(C14,[1]Timesheet!$B$7:$B$565,[1]Timesheet!$BB$7:$BB$565,0) -> 0 | DM14: =_xlfn.XLOOKUP(C14,[1]Timesheet!$B$7:$B$565,[1]Timesheet!$BC$7:$BC$565,0) -> 0 | DN14: =_xlfn.XLOOKUP(C14,[1]Timesheet!$B$7:$B$565,[1]Timesheet!$BF$7:$BF$565,0) -> 0 | DO14: =_xlfn.XLOOKUP(C14,[1]Timesheet!$B$7:$B$565,[1]Timesheet!$BJ$7:$BJ$565,0) -> 0 | DP14: =DN14+DO14 -> 0 | DQ14: =_xlfn.XLOOKUP(C14,[1]Timesheet!$B$7:$B$565,[1]Timesheet!$BT$7:$BT$565,0) -> 21 | DR14: =_xlfn.XLOOKUP(C14,[1]Timesheet!$B$7:$B$565,[1]Timesheet!$BM$7:$BM$565,0) -> 0 | DS14: =W14/$J$3*DR14 -> 0 | DT14: =ROUND(IF(BH14>0,L14*$DT$7,0),0) -> 0 | DU14: =ROUND(IF(BI14>0,L14*$DU$7,0),0) -> 0 | DV14: =ROUND(IF(BJ14>0,M14*$DV$7,0),0) -> 0 | DW14: =ROUND(IF(BK14>0,L14*$DW$7,0),0) -> 0 | DX14: =SUM(N14:X14) -> 7000000 | DY14: =SUM(O14:S14) -> 600000 | DZ14: =SUM(W14:X14) -> 1000000 | EA14: =_xlfn.XLOOKUP(C14,[1]Timesheet!$B$7:$B$565,[1]Timesheet!$BI$7:$BI$565,0) -> 1 | EB14: =IF(AC14>0,ROUND((BE14+CX14+CY14-AE14-AN14-AW14-AC14)*15%,0),0) -> 0 | EC14: =AC14 -> 0 | ED14: =EB14-EC14 -> 0 | EE14: =BE14+CX14+CY14-AE14-AN14-AW14-BL14 -> 0 | EF14: =ROUND((SUM(N14:P14)+W14+X14+T14+U14+V14)/($J$3*8)*_xlfn.XLOOKUP(C14,[1]Overtime!$B$9:$B$557,[1]Overtime!$AU$9:$AU$557,0),0) -> 0 | EG14: =ROUND(((SUM(N14:P14)+W14+X14+T14+U14+V14)/($J$3*8))*_xlfn.XLOOKUP(C14,[1]Overtime!$B$9:$B$557,[1]Overtime!$AY$9:$AY$557,0),0) -> 0 | EH14: =ROUND(EG14+EF14,0) -> 0 | EI14: =AL14-EF14 -> 0 | EJ14: =AM14-EG14 -> 0 | EK14: =ROUND((SUM(N14:P14)+W14+X14+T14+U14+V14)/($J$3*8)*_xlfn.XLOOKUP(C14,[1]Overtime!$B$9:$B$557,[1]Overtime!$AO$9:$AO$557,0)*1.5,0) -> 0 | EL14: =ROUND((SUM(N14:P14)+W14+X14+T14+U14+V14)/($J$3*8)*_xlfn.XLOOKUP(C14,[1]Overtime!$B$9:$B$557,[1]Overtime!$AP$9:$AP$557,0)*2,0) -> 0 | EM14: =AN14-EK14-EL14 -> 0 | EN14: =ROUND(Y14*W14/$J$3,0) -> 19231 | EO14: =DJ14-EN14 -> 0 | EP14: =IF(AI14=0,0,AI14-DK14-EN14) -> 0 | EQ14: 0 | ER14: =EQ14/4400000 -> 0
B15: =B14+1 -> 6 | C15: TIQN-2192 | D15: Nguyễn Thị Hiền | E15: =IF(CW15="x","Probation",IF(CR15>0,"Resigned - Official","Official")) -> Probation | F15: =IF(H15="management","6421.11",0) -> 0 | G15: Sewing | H15: Direct | I15: Supporting line | J15: Sewing | K15: Supporting worker | L15: =M15 -> 6300000 | M15: =N15+O15+P15+W15+X15+T15+U15+V15 -> 6300000 | N15: 5200000 | O15: 100000 | P15: 0 | Q15: 0 | R15: 300000 | S15: 0 | T15: 0 | U15: 0 | V15: 0 | W15: 1000000 | X15: 0 | Y15: =_xlfn.XLOOKUP(C15,[1]Timesheet!$B$9:$B$25,[1]Timesheet!$AO$9:$AO$25,0,,1) -> 0 | Z15: =ROUND(N15/$J$3*Y15,0) -> 0 | AA15: =ROUND(O15/$J$3*(Y15+_xlfn.XLOOKUP(C15,[1]Timesheet!B:B,[1]Timesheet!BS:BS,0)),0) -> 0 | AB15: =ROUND(IF(Y15>=8,P15,(P15/$J$3)*(Y15+_xlfn.XLOOKUP(C15,[1]Timesheet!B:B,[1]Timesheet!BS:BS,0))),0) -> 0 | AC15: =ROUND(IF(Y15>=14,Q15,(Q15/2)),0) -> 0 | AD15: =IF(_xlfn.XLOOKUP(Salary!C15,[1]Bus!B:B,[1]Bus!G:G,"",,-1)=1,0,ROUND((R15/$J$3)*ROUND(Y15+_xlfn.XLOOKUP(C15,[1]Timesheet!B:B,[1]Timesheet!BS:BS,0,,-1),0),0)) -> 0 | AE15: =IF(Y15>0,S15,0) -> 0 | AF15: =ROUND(IF(Y15>=8,T15,(T15/$J$3)*(Y15+_xlfn.XLOOKUP(C15,[1]Timesheet!B:B,[1]Timesheet!BS:BS,0))),0) -> 0 | AG15: =ROUND(IF(Y15>=8,U15,(U15/$J$3)*(Y15+_xlfn.XLOOKUP(C15,[1]Timesheet!B:B,[1]Timesheet!BS:BS,0))),0) -> 0 | AH15: =ROUND(IF(OR(CR15>0,Y15<8),(V15/$J$3)*(Y15+_xlfn.XLOOKUP(C15,[1]Timesheet!B:B,[1]Timesheet!BS:BS,0)),V15),0) -> 0 | AI15: =ROUND(IF(DAY(CR15)=26,IF(Y15=0,0,IF(W15=0,0,IF(OR(-(DK15)>DJ15,-(DK15)=DJ15),0,DJ15+DK15+DS15))),IF(CR15>0,0,IF(Y15=0,0,IF(W15=0,0,IF(OR(-(DK15)>DJ15,-(DK15)=DJ15),0,DJ15+DK15+DS15))))),0) -> 0 | AJ15: =IF(Y15>0,ROUND(IF(LEN(CR15)>2,(X15/$J$3)*(Y15+_xlfn.XLOOKUP(C15,[1]Timesheet!B:B,[1]Timesheet!BS:BS,0)),X15),0),0) -> 0 | AK15: =_xlfn.XLOOKUP(C15,[1]Overtime!$B$7:$B$557,[1]Overtime!$AN$7:$AN$557,0) -> 0 | AL15: =ROUND(((SUM(N15:P15)+SUM(T15:X15))/($J$3*8))*_xlfn.XLOOKUP(C15,[1]Overtime!$B$9:$B$557,[1]Overtime!$AU$9:$AU$557,0),0) -> 0 | AM15: =ROUND(((SUM(N15:P15)+SUM(T15:X15))/($J$3*8))*_xlfn.XLOOKUP(C15,[1]Overtime!$B$9:$B$557,[1]Overtime!$AY$9:$AY$557,0),0) -> 0 | AN15: =ROUND(AM15+AL15,0) -> 0 | AR15: =ROUND(_xlfn.XLOOKUP(C15,[1]Timesheet!$B$9:$B$458,[1]Timesheet!$BQ$9:$BQ$458,,,-1)*SUM(Salary!N15:P15,Salary!T15:X15)*20%/Salary!$J$3,0) -> 0 | AS15: 20000 | AT15: 0 | AV15: =IF(CV15="x",IF(IF(CR15>0,$CW$3-_xlfn.XLOOKUP(C15,[1]Timesheet!B:B,[1]Timesheet!BW:BW,0,,-1),$CW$3-_xlfn.XLOOKUP(C15,[1]Timesheet!B:B,[1]Timesheet!BW:BW,0,,-1)-$EB$3)<14,ROUND(L15*20.5%+M15*1%,0),0),0) -> 0 | AW15: =CK15 -> 0 | AX15: =CM15 -> 45433 | AZ15: 0 | BE15: =ROUND(SUM(Z15:AJ15)+AN15+AX15+AT15+AO15+AR15+AS15+AW15+AY15+AV15+AP15+AU15+AQ15+AZ15+BA15,0) -> 65433 | BF15: =IF(OR(CW15="x",CR15>0),0,15500000) -> 0 | BG15: 0 | BJ15: =IF(CV15="x",0,ROUND(IF(BH15>0,M15*1%,0),0)) -> 0 | BK15: =IF(CV15="x",0,ROUND(IF(BH15>0,38948,0),0)) -> 0 | BL15: =ROUND(IF(AC15>0,IF(ROUND((BE15+CX15+CY15-AE15-AN15-AW15-AC15)*15%,0)>AC15,BE15+CX15+CY15-AE15-AN15-AW15,BE15+CX15+CY15-AE15-AN15-AW15-AC15+ROUND((BE15+CX15+CY15-AE15-AN15-AW15-AC15)*15%,0)),BE15+CX15+CY15-AE15-AN15-AW15),0) -> 65433 | BM15: =IF(OR(CW15="x",CR15>0),BL15,IF(BL15-BF15-BG15-SUM(BH15:BJ15)>0,BL15-BF15-BG15-SUM(BH15:BJ15),0)) -> 65433 | BN15: =IF(OR(CW15="x",CR15>0),ROUND(IF(BM15>4999999,BM15*10%,0),0),ROUND(IF(BM15>100000000,((BM15-100000000)*0.35+20500000),IF(AND(BM15>60000000,BM15<=100000000),((BM15-60000000)*0.3+8500000),IF(AND(BM15>30000000,BM15<=60000000),((BM15-30000000)*0.2+2500000),IF(AND(BM15>10000000,BM15<=30000000),((BM15-10000000)*0.1+500000),IF(BM15<0,0,(BM15*0.05)))))),0)) -> 0 | BO15: =SUM(BH15:BK15,BN15) -> 0 | BP15: =IF(CV15="x",0,ROUND(IF(BH15>0,L15*17.5%,0),0)) -> 0 | BQ15: =IF(CV15="x",0,ROUND(IF(BI15>0,L15*3%,0),0)) -> 0 | BR15: =IF(CV15="x",0,ROUND(IF(BJ15>0,M15*1%,0),0)) -> 0 | BS15: =IF(CV15="x",0,ROUND(IF(BK15>0,L15*2%,0),0)) -> 0 | BW15: 0 | CG15: =ROUND(BE15-BO15+BZ15-BT15-BU15-BX15-BV15+BW15+BY15+CA15-CB15,0) -> 65433 | CH15: =CG15+BN15+SUM(BH15:BK15)+SUM(BP15:BS15) -> 65433 | CI15: =IF(BH15=0,0,ROUND((SUM(N15:X15)-(R15+S15))/12,0)) -> 0 | CK15: =ROUND((M15/$CK$3*CJ15),0) -> 0 | CL15: 1.5 | CM15: =ROUND((M15/$J$3/8*CL15),0) -> 45433 | CO15: =CK15+CM15 -> 45433 | CP15: 46182 | CQ15: 46212 | CR15: 46202 | CS15: 0 | CT15: 0 | CV15: x | CW15: x | DC15: =_xlfn.XLOOKUP(C15,[1]Overtime!$B$8:$B$2327,[1]Overtime!$BA$8:$BA$2327,"",,-1) -> 0 | DD15: =_xlfn.XLOOKUP(C15,[1]Timesheet!$B$9:$B$2328,[1]Timesheet!$BS$9:$BS$2328,0,,-1) -> 0 | DE15: =_xlfn.XLOOKUP(C15,[1]Timesheet!$B$7:$B$616,[1]Timesheet!$BK$7:$BK$616,0)+_xlfn.XLOOKUP(C15,[1]Timesheet!$B$7:$B$616,[1]Timesheet!$AV$7:$AV$616,0)-_xlfn.XLOOKUP(C15,[1]Timesheet!$B$7:$B$616,[1]Timesheet!$AX$7:$AX$616,0)+_xlfn.XLOOKUP(C15,[1]Timesheet!$B$7:$B$616,[1]Timesheet!$AW$7:$AW$616,0)-_xlfn.XLOOKUP(C15,[1]Timesheet!$B$7:$B$616,[1]Timesheet!$AY$7:$AY$616,0) -> 0 | DF15: =DE15*(-100000) -> 0 | DG15: =_xlfn.XLOOKUP(C15,[1]Timesheet!$B$7:$B$616,[1]Timesheet!$BV$7:$BV$616,0)+_xlfn.XLOOKUP(C15,[1]Timesheet!$B$7:$B$616,[1]Timesheet!$AX$7:$AX$616,0)++_xlfn.XLOOKUP(C15,[1]Timesheet!$B$7:$B$616,[1]Timesheet!$AY$7:$AY$616,0) -> 2 | DH15: =IF(DG15>2,-1000000,IF(DG15=2,-500000,IF(DG15=1,-200000,0))) -> -500000 | DI15: =_xlfn.XLOOKUP(C15,[1]Timesheet!$B$7:$B$616,[1]Timesheet!$AZ$7:$AZ$616,0)+_xlfn.XLOOKUP(C15,[1]Timesheet!$B$7:$B$616,[1]Timesheet!$BA$7:$BA$616,0) -> 0 | DJ15: =IF(CW15="x",IF((ROUND(Y15*W15/$J$3,0))<0,0,ROUND(Y15*W15/$J$3,0)),IF(OR(CR15>0,CS15>0,CT15>0),W15/$J$3*(Y15+_xlfn.XLOOKUP(C15,[1]Timesheet!B:B,[1]Timesheet!BS:BS,0,,-1)+_xlfn.XLOOKUP(C15,[1]Timesheet!B:B,[1]Timesheet!BU:BU,0,,-1)),IF(OR(DH15<0,DF15<0),IF(DI15>0,W15/$J$3*($J$3-DI15),W15),W15/$J$3*(Y15+_xlfn.XLOOKUP(C15,[1]Timesheet!B:B,[1]Timesheet!BS:BS,0,,-1)+_xlfn.XLOOKUP(C15,[1]Timesheet!B:B,[1]Timesheet!BU:BU,0,,-1))))) -> 0 | DK15: =DF15+DH15 -> -500000 | DL15: =_xlfn.XLOOKUP(C15,[1]Timesheet!$B$7:$B$565,[1]Timesheet!$BB$7:$BB$565,0) -> 0 | DM15: =_xlfn.XLOOKUP(C15,[1]Timesheet!$B$7:$B$565,[1]Timesheet!$BC$7:$BC$565,0) -> 0 | DN15: =_xlfn.XLOOKUP(C15,[1]Timesheet!$B$7:$B$565,[1]Timesheet!$BF$7:$BF$565,0) -> 0 | DO15: =_xlfn.XLOOKUP(C15,[1]Timesheet!$B$7:$B$565,[1]Timesheet!$BJ$7:$BJ$565,0) -> 0 | DP15: =DN15+DO15 -> 0 | DQ15: =_xlfn.XLOOKUP(C15,[1]Timesheet!$B$7:$B$565,[1]Timesheet!$BT$7:$BT$565,0) -> 21 | DR15: =_xlfn.XLOOKUP(C15,[1]Timesheet!$B$7:$B$565,[1]Timesheet!$BM$7:$BM$565,0) -> 0 | DS15: =W15/$J$3*DR15 -> 0 | DT15: =ROUND(IF(BH15>0,L15*$DT$7,0),0) -> 0 | DU15: =ROUND(IF(BI15>0,L15*$DU$7,0),0) -> 0 | DV15: =ROUND(IF(BJ15>0,M15*$DV$7,0),0) -> 0 | DW15: =ROUND(IF(BK15>0,L15*$DW$7,0),0) -> 0 | DX15: =SUM(N15:X15) -> 6600000 | DY15: =SUM(O15:S15) -> 400000 | DZ15: =SUM(W15:X15) -> 1000000 | EA15: =_xlfn.XLOOKUP(C15,[1]Timesheet!$B$7:$B$565,[1]Timesheet!$BI$7:$BI$565,0) -> 2 | EB15: =IF(AC15>0,ROUND((BE15+CX15+CY15-AE15-AN15-AW15-AC15)*15%,0),0) -> 0 | EC15: =AC15 -> 0 | ED15: =EB15-EC15 -> 0 | EE15: =BE15+CX15+CY15-AE15-AN15-AW15-BL15 -> 0 | EF15: =ROUND((SUM(N15:P15)+W15+X15+T15+U15+V15)/($J$3*8)*_xlfn.XLOOKUP(C15,[1]Overtime!$B$9:$B$557,[1]Overtime!$AU$9:$AU$557,0),0) -> 0 | EG15: =ROUND(((SUM(N15:P15)+W15+X15+T15+U15+V15)/($J$3*8))*_xlfn.XLOOKUP(C15,[1]Overtime!$B$9:$B$557,[1]Overtime!$AY$9:$AY$557,0),0) -> 0 | EH15: =ROUND(EG15+EF15,0) -> 0 | EI15: =AL15-EF15 -> 0 | EJ15: =AM15-EG15 -> 0 | EK15: =ROUND((SUM(N15:P15)+W15+X15+T15+U15+V15)/($J$3*8)*_xlfn.XLOOKUP(C15,[1]Overtime!$B$9:$B$557,[1]Overtime!$AO$9:$AO$557,0)*1.5,0) -> 0 | EL15: =ROUND((SUM(N15:P15)+W15+X15+T15+U15+V15)/($J$3*8)*_xlfn.XLOOKUP(C15,[1]Overtime!$B$9:$B$557,[1]Overtime!$AP$9:$AP$557,0)*2,0) -> 0 | EM15: =AN15-EK15-EL15 -> 0 | EN15: =ROUND(Y15*W15/$J$3,0) -> 0 | EO15: =DJ15-EN15 -> 0 | EP15: =IF(AI15=0,0,AI15-DK15-EN15) -> 0 | EQ15: 0 | ER15: =EQ15/4400000 -> 0
B16: =B15+1 -> 7 | C16: TIQN-2208 | D16: Trương Thế Trọng | E16: =IF(CW16="x","Probation",IF(CR16>0,"Resigned - Official","Official")) -> Probation | F16: =IF(H16="management","6421.11",0) -> 0 | G16: Preparation | H16: Indirect | I16: 2nd Process | J16: Preparation | K16: Supporting worker | L16: =M16 -> 6500000 | M16: =N16+O16+P16+W16+X16+T16+U16+V16 -> 6500000 | N16: 5200000 | O16: 300000 | P16: 0 | Q16: 0 | R16: 300000 | S16: 0 | T16: 0 | U16: 0 | V16: 0 | W16: 1000000 | X16: 0 | Y16: =_xlfn.XLOOKUP(C16,[1]Timesheet!$B$9:$B$25,[1]Timesheet!$AO$9:$AO$25,0,,1) -> 7 | Z16: =ROUND(N16/$J$3*Y16,0) -> 1400000 | AA16: =ROUND(O16/$J$3*(Y16+_xlfn.XLOOKUP(C16,[1]Timesheet!B:B,[1]Timesheet!BS:BS,0)),0) -> 80769 | AB16: =ROUND(IF(Y16>=8,P16,(P16/$J$3)*(Y16+_xlfn.XLOOKUP(C16,[1]Timesheet!B:B,[1]Timesheet!BS:BS,0))),0) -> 0 | AC16: =ROUND(IF(Y16>=14,Q16,(Q16/2)),0) -> 0 | AD16: =IF(_xlfn.XLOOKUP(Salary!C16,[1]Bus!B:B,[1]Bus!G:G,"",,-1)=1,0,ROUND((R16/$J$3)*ROUND(Y16+_xlfn.XLOOKUP(C16,[1]Timesheet!B:B,[1]Timesheet!BS:BS,0,,-1),0),0)) -> 80769 | AE16: =IF(Y16>0,S16,0) -> 0 | AF16: =ROUND(IF(Y16>=8,T16,(T16/$J$3)*(Y16+_xlfn.XLOOKUP(C16,[1]Timesheet!B:B,[1]Timesheet!BS:BS,0))),0) -> 0 | AG16: =ROUND(IF(Y16>=8,U16,(U16/$J$3)*(Y16+_xlfn.XLOOKUP(C16,[1]Timesheet!B:B,[1]Timesheet!BS:BS,0))),0) -> 0 | AH16: =ROUND(IF(OR(CR16>0,Y16<8),(V16/$J$3)*(Y16+_xlfn.XLOOKUP(C16,[1]Timesheet!B:B,[1]Timesheet!BS:BS,0)),V16),0) -> 0 | AI16: =ROUND(IF(DAY(CR16)=26,IF(Y16=0,0,IF(W16=0,0,IF(OR(-(DK16)>DJ16,-(DK16)=DJ16),0,DJ16+DK16+DS16))),IF(CR16>0,0,IF(Y16=0,0,IF(W16=0,0,IF(OR(-(DK16)>DJ16,-(DK16)=DJ16),0,DJ16+DK16+DS16))))),0) -> 0 | AJ16: =IF(Y16>0,ROUND(IF(LEN(CR16)>2,(X16/$J$3)*(Y16+_xlfn.XLOOKUP(C16,[1]Timesheet!B:B,[1]Timesheet!BS:BS,0)),X16),0),0) -> 0 | AK16: =_xlfn.XLOOKUP(C16,[1]Overtime!$B$7:$B$557,[1]Overtime!$AN$7:$AN$557,0) -> 9 | AL16: =ROUND(((SUM(N16:P16)+SUM(T16:X16))/($J$3*8))*_xlfn.XLOOKUP(C16,[1]Overtime!$B$9:$B$557,[1]Overtime!$AU$9:$AU$557,0),0) -> 281250 | AM16: =ROUND(((SUM(N16:P16)+SUM(T16:X16))/($J$3*8))*_xlfn.XLOOKUP(C16,[1]Overtime!$B$9:$B$557,[1]Overtime!$AY$9:$AY$557,0),0) -> 140625 | AN16: =ROUND(AM16+AL16,0) -> 421875 | AR16: =ROUND(_xlfn.XLOOKUP(C16,[1]Timesheet!$B$9:$B$458,[1]Timesheet!$BQ$9:$BQ$458,,,-1)*SUM(Salary!N16:P16,Salary!T16:X16)*20%/Salary!$J$3,0) -> 0 | AS16: 0 | AT16: 0 | AV16: =IF(CV16="x",IF(IF(CR16>0,$CW$3-_xlfn.XLOOKUP(C16,[1]Timesheet!B:B,[1]Timesheet!BW:BW,0,,-1),$CW$3-_xlfn.XLOOKUP(C16,[1]Timesheet!B:B,[1]Timesheet!BW:BW,0,,-1)-$EB$3)<14,ROUND(L16*20.5%+M16*1%,0),0),0) -> 0 | AW16: =CK16 -> 0 | AX16: =CM16 -> 0 | AZ16: 0 | BE16: =ROUND(SUM(Z16:AJ16)+AN16+AX16+AT16+AO16+AR16+AS16+AW16+AY16+AV16+AP16+AU16+AQ16+AZ16+BA16,0) -> 1983413 | BF16: =IF(OR(CW16="x",CR16>0),0,15500000) -> 0 | BG16: 0 | BJ16: =IF(CV16="x",0,ROUND(IF(BH16>0,M16*1%,0),0)) -> 0 | BK16: =IF(CV16="x",0,ROUND(IF(BH16>0,38948,0),0)) -> 0 | BL16: =ROUND(IF(AC16>0,IF(ROUND((BE16+CX16+CY16-AE16-AN16-AW16-AC16)*15%,0)>AC16,BE16+CX16+CY16-AE16-AN16-AW16,BE16+CX16+CY16-AE16-AN16-AW16-AC16+ROUND((BE16+CX16+CY16-AE16-AN16-AW16-AC16)*15%,0)),BE16+CX16+CY16-AE16-AN16-AW16),0) -> 1561538 | BM16: =IF(OR(CW16="x",CR16>0),BL16,IF(BL16-BF16-BG16-SUM(BH16:BJ16)>0,BL16-BF16-BG16-SUM(BH16:BJ16),0)) -> 1561538 | BN16: =IF(OR(CW16="x",CR16>0),ROUND(IF(BM16>4999999,BM16*10%,0),0),ROUND(IF(BM16>100000000,((BM16-100000000)*0.35+20500000),IF(AND(BM16>60000000,BM16<=100000000),((BM16-60000000)*0.3+8500000),IF(AND(BM16>30000000,BM16<=60000000),((BM16-30000000)*0.2+2500000),IF(AND(BM16>10000000,BM16<=30000000),((BM16-10000000)*0.1+500000),IF(BM16<0,0,(BM16*0.05)))))),0)) -> 0 | BO16: =SUM(BH16:BK16,BN16) -> 0 | BP16: =IF(CV16="x",0,ROUND(IF(BH16>0,L16*17.5%,0),0)) -> 0 | BQ16: =IF(CV16="x",0,ROUND(IF(BI16>0,L16*3%,0),0)) -> 0 | BR16: =IF(CV16="x",0,ROUND(IF(BJ16>0,M16*1%,0),0)) -> 0 | BS16: =IF(CV16="x",0,ROUND(IF(BK16>0,L16*2%,0),0)) -> 0 | BW16: 0 | CG16: =ROUND(BE16-BO16+BZ16-BT16-BU16-BX16-BV16+BW16+BY16+CA16-CB16,0) -> 1983413 | CH16: =CG16+BN16+SUM(BH16:BK16)+SUM(BP16:BS16) -> 1983413 | CI16: =IF(BH16=0,0,ROUND((SUM(N16:X16)-(R16+S16))/12,0)) -> 0 | CK16: =ROUND((M16/$CK$3*CJ16),0) -> 0 | CM16: =ROUND((M16/$J$3/8*CL16),0) -> 0 | CO16: =CK16+CM16 -> 0 | CP16: 46185 | CQ16: 46215 | CR16: 46207 | CS16: 0 | CT16: 0 | CV16: x | CW16: x | DC16: =_xlfn.XLOOKUP(C16,[1]Overtime!$B$8:$B$2327,[1]Overtime!$BA$8:$BA$2327,"",,-1) -> 0 | DD16: =_xlfn.XLOOKUP(C16,[1]Timesheet!$B$9:$B$2328,[1]Timesheet!$BS$9:$BS$2328,0,,-1) -> 0 | DE16: =_xlfn.XLOOKUP(C16,[1]Timesheet!$B$7:$B$616,[1]Timesheet!$BK$7:$BK$616,0)+_xlfn.XLOOKUP(C16,[1]Timesheet!$B$7:$B$616,[1]Timesheet!$AV$7:$AV$616,0)-_xlfn.XLOOKUP(C16,[1]Timesheet!$B$7:$B$616,[1]Timesheet!$AX$7:$AX$616,0)+_xlfn.XLOOKUP(C16,[1]Timesheet!$B$7:$B$616,[1]Timesheet!$AW$7:$AW$616,0)-_xlfn.XLOOKUP(C16,[1]Timesheet!$B$7:$B$616,[1]Timesheet!$AY$7:$AY$616,0) -> 0 | DF16: =DE16*(-100000) -> 0 | DG16: =_xlfn.XLOOKUP(C16,[1]Timesheet!$B$7:$B$616,[1]Timesheet!$BV$7:$BV$616,0)+_xlfn.XLOOKUP(C16,[1]Timesheet!$B$7:$B$616,[1]Timesheet!$AX$7:$AX$616,0)++_xlfn.XLOOKUP(C16,[1]Timesheet!$B$7:$B$616,[1]Timesheet!$AY$7:$AY$616,0) -> 0 | DH16: =IF(DG16>2,-1000000,IF(DG16=2,-500000,IF(DG16=1,-200000,0))) -> 0 | DI16: =_xlfn.XLOOKUP(C16,[1]Timesheet!$B$7:$B$616,[1]Timesheet!$AZ$7:$AZ$616,0)+_xlfn.XLOOKUP(C16,[1]Timesheet!$B$7:$B$616,[1]Timesheet!$BA$7:$BA$616,0) -> 0 | DJ16: =IF(CW16="x",IF((ROUND(Y16*W16/$J$3,0))<0,0,ROUND(Y16*W16/$J$3,0)),IF(OR(CR16>0,CS16>0,CT16>0),W16/$J$3*(Y16+_xlfn.XLOOKUP(C16,[1]Timesheet!B:B,[1]Timesheet!BS:BS,0,,-1)+_xlfn.XLOOKUP(C16,[1]Timesheet!B:B,[1]Timesheet!BU:BU,0,,-1)),IF(OR(DH16<0,DF16<0),IF(DI16>0,W16/$J$3*($J$3-DI16),W16),W16/$J$3*(Y16+_xlfn.XLOOKUP(C16,[1]Timesheet!B:B,[1]Timesheet!BS:BS,0,,-1)+_xlfn.XLOOKUP(C16,[1]Timesheet!B:B,[1]Timesheet!BU:BU,0,,-1))))) -> 269231 | DK16: =DF16+DH16 -> 0 | DL16: =_xlfn.XLOOKUP(C16,[1]Timesheet!$B$7:$B$565,[1]Timesheet!$BB$7:$BB$565,0) -> 0 | DM16: =_xlfn.XLOOKUP(C16,[1]Timesheet!$B$7:$B$565,[1]Timesheet!$BC$7:$BC$565,0) -> 0 | DN16: =_xlfn.XLOOKUP(C16,[1]Timesheet!$B$7:$B$565,[1]Timesheet!$BF$7:$BF$565,0) -> 0 | DO16: =_xlfn.XLOOKUP(C16,[1]Timesheet!$B$7:$B$565,[1]Timesheet!$BJ$7:$BJ$565,0) -> 0 | DP16: =DN16+DO16 -> 0 | DQ16: =_xlfn.XLOOKUP(C16,[1]Timesheet!$B$7:$B$565,[1]Timesheet!$BT$7:$BT$565,0) -> 18 | DR16: =_xlfn.XLOOKUP(C16,[1]Timesheet!$B$7:$B$565,[1]Timesheet!$BM$7:$BM$565,0) -> 0 | DS16: =W16/$J$3*DR16 -> 0 | DT16: =ROUND(IF(BH16>0,L16*$DT$7,0),0) -> 0 | DU16: =ROUND(IF(BI16>0,L16*$DU$7,0),0) -> 0 | DV16: =ROUND(IF(BJ16>0,M16*$DV$7,0),0) -> 0 | DW16: =ROUND(IF(BK16>0,L16*$DW$7,0),0) -> 0 | DX16: =SUM(N16:X16) -> 6800000 | DY16: =SUM(O16:S16) -> 600000 | DZ16: =SUM(W16:X16) -> 1000000 | EA16: =_xlfn.XLOOKUP(C16,[1]Timesheet!$B$7:$B$565,[1]Timesheet!$BI$7:$BI$565,0) -> 0 | EB16: =IF(AC16>0,ROUND((BE16+CX16+CY16-AE16-AN16-AW16-AC16)*15%,0),0) -> 0 | EC16: =AC16 -> 0 | ED16: =EB16-EC16 -> 0 | EE16: =BE16+CX16+CY16-AE16-AN16-AW16-BL16 -> 0 | EF16: =ROUND((SUM(N16:P16)+W16+X16+T16+U16+V16)/($J$3*8)*_xlfn.XLOOKUP(C16,[1]Overtime!$B$9:$B$557,[1]Overtime!$AU$9:$AU$557,0),0) -> 281250 | EG16: =ROUND(((SUM(N16:P16)+W16+X16+T16+U16+V16)/($J$3*8))*_xlfn.XLOOKUP(C16,[1]Overtime!$B$9:$B$557,[1]Overtime!$AY$9:$AY$557,0),0) -> 140625 | EH16: =ROUND(EG16+EF16,0) -> 421875 | EI16: =AL16-EF16 -> 0 | EJ16: =AM16-EG16 -> 0 | EK16: =ROUND((SUM(N16:P16)+W16+X16+T16+U16+V16)/($J$3*8)*_xlfn.XLOOKUP(C16,[1]Overtime!$B$9:$B$557,[1]Overtime!$AO$9:$AO$557,0)*1.5,0) -> 421875 | EL16: =ROUND((SUM(N16:P16)+W16+X16+T16+U16+V16)/($J$3*8)*_xlfn.XLOOKUP(C16,[1]Overtime!$B$9:$B$557,[1]Overtime!$AP$9:$AP$557,0)*2,0) -> 0 | EM16: =AN16-EK16-EL16 -> 0 | EN16: =ROUND(Y16*W16/$J$3,0) -> 269231 | EO16: =DJ16-EN16 -> 0 | EP16: =IF(AI16=0,0,AI16-DK16-EN16) -> 0 | EQ16: 0 | ER16: =EQ16/4400000 -> 0
B17: =B16+1 -> 8 | C17: TIQN-2219 | D17: Trần Văn Anh | E17: =IF(CW17="x","Probation",IF(CR17>0,"Resigned - Official","Official")) -> Probation | F17: =IF(H17="management","6421.11",0) -> 0 | G17: Sewing | H17: Direct | I17: Line 17 | J17: Sewing | K17: Sewing worker | L17: =M17 -> 6500000 | M17: =N17+O17+P17+W17+X17+T17+U17+V17 -> 6500000 | N17: 5200000 | O17: 300000 | P17: 0 | Q17: 0 | R17: 300000 | S17: 0 | T17: 0 | U17: 0 | V17: 0 | W17: 1000000 | X17: 0 | Y17: =_xlfn.XLOOKUP(C17,[1]Timesheet!$B$9:$B$25,[1]Timesheet!$AO$9:$AO$25,0,,1) -> 0 | Z17: =ROUND(N17/$J$3*Y17,0) -> 0 | AA17: =ROUND(O17/$J$3*(Y17+_xlfn.XLOOKUP(C17,[1]Timesheet!B:B,[1]Timesheet!BS:BS,0)),0) -> 0 | AB17: =ROUND(IF(Y17>=8,P17,(P17/$J$3)*(Y17+_xlfn.XLOOKUP(C17,[1]Timesheet!B:B,[1]Timesheet!BS:BS,0))),0) -> 0 | AC17: =ROUND(IF(Y17>=14,Q17,(Q17/2)),0) -> 0 | AD17: =IF(_xlfn.XLOOKUP(Salary!C17,[1]Bus!B:B,[1]Bus!G:G,"",,-1)=1,0,ROUND((R17/$J$3)*ROUND(Y17+_xlfn.XLOOKUP(C17,[1]Timesheet!B:B,[1]Timesheet!BS:BS,0,,-1),0),0)) -> 0 | AE17: =IF(Y17>0,S17,0) -> 0 | AF17: =ROUND(IF(Y17>=8,T17,(T17/$J$3)*(Y17+_xlfn.XLOOKUP(C17,[1]Timesheet!B:B,[1]Timesheet!BS:BS,0))),0) -> 0 | AG17: =ROUND(IF(Y17>=8,U17,(U17/$J$3)*(Y17+_xlfn.XLOOKUP(C17,[1]Timesheet!B:B,[1]Timesheet!BS:BS,0))),0) -> 0 | AH17: =ROUND(IF(OR(CR17>0,Y17<8),(V17/$J$3)*(Y17+_xlfn.XLOOKUP(C17,[1]Timesheet!B:B,[1]Timesheet!BS:BS,0)),V17),0) -> 0 | AI17: =ROUND(IF(DAY(CR17)=26,IF(Y17=0,0,IF(W17=0,0,IF(OR(-(DK17)>DJ17,-(DK17)=DJ17),0,DJ17+DK17+DS17))),IF(CR17>0,0,IF(Y17=0,0,IF(W17=0,0,IF(OR(-(DK17)>DJ17,-(DK17)=DJ17),0,DJ17+DK17+DS17))))),0) -> 0 | AJ17: =IF(Y17>0,ROUND(IF(LEN(CR17)>2,(X17/$J$3)*(Y17+_xlfn.XLOOKUP(C17,[1]Timesheet!B:B,[1]Timesheet!BS:BS,0)),X17),0),0) -> 0 | AK17: =_xlfn.XLOOKUP(C17,[1]Overtime!$B$7:$B$557,[1]Overtime!$AN$7:$AN$557,0) -> 0 | AL17: =ROUND(((SUM(N17:P17)+SUM(T17:X17))/($J$3*8))*_xlfn.XLOOKUP(C17,[1]Overtime!$B$9:$B$557,[1]Overtime!$AU$9:$AU$557,0),0) -> 0 | AM17: =ROUND(((SUM(N17:P17)+SUM(T17:X17))/($J$3*8))*_xlfn.XLOOKUP(C17,[1]Overtime!$B$9:$B$557,[1]Overtime!$AY$9:$AY$557,0),0) -> 0 | AN17: =ROUND(AM17+AL17,0) -> 0 | AR17: =ROUND(_xlfn.XLOOKUP(C17,[1]Timesheet!$B$9:$B$458,[1]Timesheet!$BQ$9:$BQ$458,,,-1)*SUM(Salary!N17:P17,Salary!T17:X17)*20%/Salary!$J$3,0) -> 0 | AS17: 0 | AT17: 0 | AV17: =IF(CV17="x",IF(IF(CR17>0,$CW$3-_xlfn.XLOOKUP(C17,[1]Timesheet!B:B,[1]Timesheet!BW:BW,0,,-1),$CW$3-_xlfn.XLOOKUP(C17,[1]Timesheet!B:B,[1]Timesheet!BW:BW,0,,-1)-$EB$3)<14,ROUND(L17*20.5%+M17*1%,0),0),0) -> 0 | AW17: =CK17 -> 0 | AX17: =CM17 -> 0 | AZ17: 0 | BE17: =ROUND(SUM(Z17:AJ17)+AN17+AX17+AT17+AO17+AR17+AS17+AW17+AY17+AV17+AP17+AU17+AQ17+AZ17+BA17,0) -> 0 | BF17: =IF(OR(CW17="x",CR17>0),0,15500000) -> 0 | BG17: 0 | BJ17: =IF(CV17="x",0,ROUND(IF(BH17>0,M17*1%,0),0)) -> 0 | BK17: =IF(CV17="x",0,ROUND(IF(BH17>0,38948,0),0)) -> 0 | BL17: =ROUND(IF(AC17>0,IF(ROUND((BE17+CX17+CY17-AE17-AN17-AW17-AC17)*15%,0)>AC17,BE17+CX17+CY17-AE17-AN17-AW17,BE17+CX17+CY17-AE17-AN17-AW17-AC17+ROUND((BE17+CX17+CY17-AE17-AN17-AW17-AC17)*15%,0)),BE17+CX17+CY17-AE17-AN17-AW17),0) -> 0 | BM17: =IF(OR(CW17="x",CR17>0),BL17,IF(BL17-BF17-BG17-SUM(BH17:BJ17)>0,BL17-BF17-BG17-SUM(BH17:BJ17),0)) -> 0 | BN17: =IF(OR(CW17="x",CR17>0),ROUND(IF(BM17>4999999,BM17*10%,0),0),ROUND(IF(BM17>100000000,((BM17-100000000)*0.35+20500000),IF(AND(BM17>60000000,BM17<=100000000),((BM17-60000000)*0.3+8500000),IF(AND(BM17>30000000,BM17<=60000000),((BM17-30000000)*0.2+2500000),IF(AND(BM17>10000000,BM17<=30000000),((BM17-10000000)*0.1+500000),IF(BM17<0,0,(BM17*0.05)))))),0)) -> 0 | BO17: =SUM(BH17:BK17,BN17) -> 0 | BP17: =IF(CV17="x",0,ROUND(IF(BH17>0,L17*17.5%,0),0)) -> 0 | BQ17: =IF(CV17="x",0,ROUND(IF(BI17>0,L17*3%,0),0)) -> 0 | BR17: =IF(CV17="x",0,ROUND(IF(BJ17>0,M17*1%,0),0)) -> 0 | BS17: =IF(CV17="x",0,ROUND(IF(BK17>0,L17*2%,0),0)) -> 0 | BW17: 0 | CG17: =ROUND(BE17-BO17+BZ17-BT17-BU17-BX17-BV17+BW17+BY17+CA17-CB17,0) -> 0 | CH17: =CG17+BN17+SUM(BH17:BK17)+SUM(BP17:BS17) -> 0 | CI17: =IF(BH17=0,0,ROUND((SUM(N17:X17)-(R17+S17))/12,0)) -> 0 | CK17: =ROUND((M17/$CK$3*CJ17),0) -> 0 | CM17: =ROUND((M17/$J$3/8*CL17),0) -> 0 | CO17: =CK17+CM17 -> 0 | CP17: 46189 | CQ17: 46219 | CR17: 46202 | CS17: 0 | CT17: 0 | CV17: x | CW17: x | DC17: =_xlfn.XLOOKUP(C17,[1]Overtime!$B$8:$B$2327,[1]Overtime!$BA$8:$BA$2327,"",,-1) -> 0 | DD17: =_xlfn.XLOOKUP(C17,[1]Timesheet!$B$9:$B$2328,[1]Timesheet!$BS$9:$BS$2328,0,,-1) -> 0 | DE17: =_xlfn.XLOOKUP(C17,[1]Timesheet!$B$7:$B$616,[1]Timesheet!$BK$7:$BK$616,0)+_xlfn.XLOOKUP(C17,[1]Timesheet!$B$7:$B$616,[1]Timesheet!$AV$7:$AV$616,0)-_xlfn.XLOOKUP(C17,[1]Timesheet!$B$7:$B$616,[1]Timesheet!$AX$7:$AX$616,0)+_xlfn.XLOOKUP(C17,[1]Timesheet!$B$7:$B$616,[1]Timesheet!$AW$7:$AW$616,0)-_xlfn.XLOOKUP(C17,[1]Timesheet!$B$7:$B$616,[1]Timesheet!$AY$7:$AY$616,0) -> 0 | DF17: =DE17*(-100000) -> 0 | DG17: =_xlfn.XLOOKUP(C17,[1]Timesheet!$B$7:$B$616,[1]Timesheet!$BV$7:$BV$616,0)+_xlfn.XLOOKUP(C17,[1]Timesheet!$B$7:$B$616,[1]Timesheet!$AX$7:$AX$616,0)++_xlfn.XLOOKUP(C17,[1]Timesheet!$B$7:$B$616,[1]Timesheet!$AY$7:$AY$616,0) -> 2 | DH17: =IF(DG17>2,-1000000,IF(DG17=2,-500000,IF(DG17=1,-200000,0))) -> -500000 | DI17: =_xlfn.XLOOKUP(C17,[1]Timesheet!$B$7:$B$616,[1]Timesheet!$AZ$7:$AZ$616,0)+_xlfn.XLOOKUP(C17,[1]Timesheet!$B$7:$B$616,[1]Timesheet!$BA$7:$BA$616,0) -> 0 | DJ17: =IF(CW17="x",IF((ROUND(Y17*W17/$J$3,0))<0,0,ROUND(Y17*W17/$J$3,0)),IF(OR(CR17>0,CS17>0,CT17>0),W17/$J$3*(Y17+_xlfn.XLOOKUP(C17,[1]Timesheet!B:B,[1]Timesheet!BS:BS,0,,-1)+_xlfn.XLOOKUP(C17,[1]Timesheet!B:B,[1]Timesheet!BU:BU,0,,-1)),IF(OR(DH17<0,DF17<0),IF(DI17>0,W17/$J$3*($J$3-DI17),W17),W17/$J$3*(Y17+_xlfn.XLOOKUP(C17,[1]Timesheet!B:B,[1]Timesheet!BS:BS,0,,-1)+_xlfn.XLOOKUP(C17,[1]Timesheet!B:B,[1]Timesheet!BU:BU,0,,-1))))) -> 0 | DK17: =DF17+DH17 -> -500000 | DL17: =_xlfn.XLOOKUP(C17,[1]Timesheet!$B$7:$B$565,[1]Timesheet!$BB$7:$BB$565,0) -> 0 | DM17: =_xlfn.XLOOKUP(C17,[1]Timesheet!$B$7:$B$565,[1]Timesheet!$BC$7:$BC$565,0) -> 0 | DN17: =_xlfn.XLOOKUP(C17,[1]Timesheet!$B$7:$B$565,[1]Timesheet!$BF$7:$BF$565,0) -> 0 | DO17: =_xlfn.XLOOKUP(C17,[1]Timesheet!$B$7:$B$565,[1]Timesheet!$BJ$7:$BJ$565,0) -> 0 | DP17: =DN17+DO17 -> 0 | DQ17: =_xlfn.XLOOKUP(C17,[1]Timesheet!$B$7:$B$565,[1]Timesheet!$BT$7:$BT$565,0) -> 21 | DR17: =_xlfn.XLOOKUP(C17,[1]Timesheet!$B$7:$B$565,[1]Timesheet!$BM$7:$BM$565,0) -> 0 | DS17: =W17/$J$3*DR17 -> 0 | DT17: =ROUND(IF(BH17>0,L17*$DT$7,0),0) -> 0 | DU17: =ROUND(IF(BI17>0,L17*$DU$7,0),0) -> 0 | DV17: =ROUND(IF(BJ17>0,M17*$DV$7,0),0) -> 0 | DW17: =ROUND(IF(BK17>0,L17*$DW$7,0),0) -> 0 | DX17: =SUM(N17:X17) -> 6800000 | DY17: =SUM(O17:S17) -> 600000 | DZ17: =SUM(W17:X17) -> 1000000 | EA17: =_xlfn.XLOOKUP(C17,[1]Timesheet!$B$7:$B$565,[1]Timesheet!$BI$7:$BI$565,0) -> 2 | EB17: =IF(AC17>0,ROUND((BE17+CX17+CY17-AE17-AN17-AW17-AC17)*15%,0),0) -> 0 | EC17: =AC17 -> 0 | ED17: =EB17-EC17 -> 0 | EE17: =BE17+CX17+CY17-AE17-AN17-AW17-BL17 -> 0 | EF17: =ROUND((SUM(N17:P17)+W17+X17+T17+U17+V17)/($J$3*8)*_xlfn.XLOOKUP(C17,[1]Overtime!$B$9:$B$557,[1]Overtime!$AU$9:$AU$557,0),0) -> 0 | EG17: =ROUND(((SUM(N17:P17)+W17+X17+T17+U17+V17)/($J$3*8))*_xlfn.XLOOKUP(C17,[1]Overtime!$B$9:$B$557,[1]Overtime!$AY$9:$AY$557,0),0) -> 0 | EH17: =ROUND(EG17+EF17,0) -> 0 | EI17: =AL17-EF17 -> 0 | EJ17: =AM17-EG17 -> 0 | EK17: =ROUND((SUM(N17:P17)+W17+X17+T17+U17+V17)/($J$3*8)*_xlfn.XLOOKUP(C17,[1]Overtime!$B$9:$B$557,[1]Overtime!$AO$9:$AO$557,0)*1.5,0) -> 0 | EL17: =ROUND((SUM(N17:P17)+W17+X17+T17+U17+V17)/($J$3*8)*_xlfn.XLOOKUP(C17,[1]Overtime!$B$9:$B$557,[1]Overtime!$AP$9:$AP$557,0)*2,0) -> 0 | EM17: =AN17-EK17-EL17 -> 0 | EN17: =ROUND(Y17*W17/$J$3,0) -> 0 | EO17: =DJ17-EN17 -> 0 | EP17: =IF(AI17=0,0,AI17-DK17-EN17) -> 0 | EQ17: 0 | ER17: =EQ17/4400000 -> 0
B18: =B17+1 -> 9 | C18: TIQN-2231 | D18: Nguyễn Văn Vũ | E18: =IF(CW18="x","Probation",IF(CR18>0,"Resigned - Official","Official")) -> Probation | F18: =IF(H18="management","6421.11",0) -> 0 | G18: Sewing | H18: Direct | I18: Line 15 | J18: Sewing | K18: Supporting worker | L18: =M18 -> 6500000 | M18: =N18+O18+P18+W18+X18+T18+U18+V18 -> 6500000 | N18: 5200000 | O18: 300000 | P18: 0 | Q18: 0 | R18: 300000 | S18: 0 | T18: 0 | U18: 0 | V18: 0 | W18: 1000000 | X18: 0 | Y18: =_xlfn.XLOOKUP(C18,[1]Timesheet!$B$9:$B$25,[1]Timesheet!$AO$9:$AO$25,0,,1) -> 0.5 | Z18: =ROUND(N18/$J$3*Y18,0) -> 100000 | AA18: =ROUND(O18/$J$3*(Y18+_xlfn.XLOOKUP(C18,[1]Timesheet!B:B,[1]Timesheet!BS:BS,0)),0) -> 5769 | AB18: =ROUND(IF(Y18>=8,P18,(P18/$J$3)*(Y18+_xlfn.XLOOKUP(C18,[1]Timesheet!B:B,[1]Timesheet!BS:BS,0))),0) -> 0 | AC18: =ROUND(IF(Y18>=14,Q18,(Q18/2)),0) -> 0 | AD18: =IF(_xlfn.XLOOKUP(Salary!C18,[1]Bus!B:B,[1]Bus!G:G,"",,-1)=1,0,ROUND((R18/$J$3)*ROUND(Y18+_xlfn.XLOOKUP(C18,[1]Timesheet!B:B,[1]Timesheet!BS:BS,0,,-1),0),0)) -> 11538 | AE18: =IF(Y18>0,S18,0) -> 0 | AF18: =ROUND(IF(Y18>=8,T18,(T18/$J$3)*(Y18+_xlfn.XLOOKUP(C18,[1]Timesheet!B:B,[1]Timesheet!BS:BS,0))),0) -> 0 | AG18: =ROUND(IF(Y18>=8,U18,(U18/$J$3)*(Y18+_xlfn.XLOOKUP(C18,[1]Timesheet!B:B,[1]Timesheet!BS:BS,0))),0) -> 0 | AH18: =ROUND(IF(OR(CR18>0,Y18<8),(V18/$J$3)*(Y18+_xlfn.XLOOKUP(C18,[1]Timesheet!B:B,[1]Timesheet!BS:BS,0)),V18),0) -> 0 | AI18: =ROUND(IF(DAY(CR18)=26,IF(Y18=0,0,IF(W18=0,0,IF(OR(-(DK18)>DJ18,-(DK18)=DJ18),0,DJ18+DK18+DS18))),IF(CR18>0,0,IF(Y18=0,0,IF(W18=0,0,IF(OR(-(DK18)>DJ18,-(DK18)=DJ18),0,DJ18+DK18+DS18))))),0) -> 0 | AJ18: =IF(Y18>0,ROUND(IF(LEN(CR18)>2,(X18/$J$3)*(Y18+_xlfn.XLOOKUP(C18,[1]Timesheet!B:B,[1]Timesheet!BS:BS,0)),X18),0),0) -> 0 | AK18: =_xlfn.XLOOKUP(C18,[1]Overtime!$B$7:$B$557,[1]Overtime!$AN$7:$AN$557,0) -> 2 | AL18: =ROUND(((SUM(N18:P18)+SUM(T18:X18))/($J$3*8))*_xlfn.XLOOKUP(C18,[1]Overtime!$B$9:$B$557,[1]Overtime!$AU$9:$AU$557,0),0) -> 62500 | AM18: =ROUND(((SUM(N18:P18)+SUM(T18:X18))/($J$3*8))*_xlfn.XLOOKUP(C18,[1]Overtime!$B$9:$B$557,[1]Overtime!$AY$9:$AY$557,0),0) -> 31250 | AN18: =ROUND(AM18+AL18,0) -> 93750 | AR18: =ROUND(_xlfn.XLOOKUP(C18,[1]Timesheet!$B$9:$B$458,[1]Timesheet!$BQ$9:$BQ$458,,,-1)*SUM(Salary!N18:P18,Salary!T18:X18)*20%/Salary!$J$3,0) -> 0 | AS18: 0 | AT18: 0 | AV18: =IF(CV18="x",IF(IF(CR18>0,$CW$3-_xlfn.XLOOKUP(C18,[1]Timesheet!B:B,[1]Timesheet!BW:BW,0,,-1),$CW$3-_xlfn.XLOOKUP(C18,[1]Timesheet!B:B,[1]Timesheet!BW:BW,0,,-1)-$EB$3)<14,ROUND(L18*20.5%+M18*1%,0),0),0) -> 0 | AW18: =CK18 -> 0 | AX18: =CM18 -> 0 | AZ18: 0 | BE18: =ROUND(SUM(Z18:AJ18)+AN18+AX18+AT18+AO18+AR18+AS18+AW18+AY18+AV18+AP18+AU18+AQ18+AZ18+BA18,0) -> 211057 | BF18: =IF(OR(CW18="x",CR18>0),0,15500000) -> 0 | BG18: 0 | BJ18: =IF(CV18="x",0,ROUND(IF(BH18>0,M18*1%,0),0)) -> 0 | BK18: =IF(CV18="x",0,ROUND(IF(BH18>0,38948,0),0)) -> 0 | BL18: =ROUND(IF(AC18>0,IF(ROUND((BE18+CX18+CY18-AE18-AN18-AW18-AC18)*15%,0)>AC18,BE18+CX18+CY18-AE18-AN18-AW18,BE18+CX18+CY18-AE18-AN18-AW18-AC18+ROUND((BE18+CX18+CY18-AE18-AN18-AW18-AC18)*15%,0)),BE18+CX18+CY18-AE18-AN18-AW18),0) -> 117307 | BM18: =IF(OR(CW18="x",CR18>0),BL18,IF(BL18-BF18-BG18-SUM(BH18:BJ18)>0,BL18-BF18-BG18-SUM(BH18:BJ18),0)) -> 117307 | BN18: =IF(OR(CW18="x",CR18>0),ROUND(IF(BM18>4999999,BM18*10%,0),0),ROUND(IF(BM18>100000000,((BM18-100000000)*0.35+20500000),IF(AND(BM18>60000000,BM18<=100000000),((BM18-60000000)*0.3+8500000),IF(AND(BM18>30000000,BM18<=60000000),((BM18-30000000)*0.2+2500000),IF(AND(BM18>10000000,BM18<=30000000),((BM18-10000000)*0.1+500000),IF(BM18<0,0,(BM18*0.05)))))),0)) -> 0 | BO18: =SUM(BH18:BK18,BN18) -> 0 | BP18: =IF(CV18="x",0,ROUND(IF(BH18>0,L18*17.5%,0),0)) -> 0 | BQ18: =IF(CV18="x",0,ROUND(IF(BI18>0,L18*3%,0),0)) -> 0 | BR18: =IF(CV18="x",0,ROUND(IF(BJ18>0,M18*1%,0),0)) -> 0 | BS18: =IF(CV18="x",0,ROUND(IF(BK18>0,L18*2%,0),0)) -> 0 | BW18: 0 | CG18: =ROUND(BE18-BO18+BZ18-BT18-BU18-BX18-BV18+BW18+BY18+CA18-CB18,0) -> 211057 | CH18: =CG18+BN18+SUM(BH18:BK18)+SUM(BP18:BS18) -> 211057 | CI18: =IF(BH18=0,0,ROUND((SUM(N18:X18)-(R18+S18))/12,0)) -> 0 | CK18: =ROUND((M18/$CK$3*CJ18),0) -> 0 | CM18: =ROUND((M18/$J$3/8*CL18),0) -> 0 | CO18: =CK18+CM18 -> 0 | CP18: 46192 | CQ18: 46222 | CR18: 46200 | CS18: 0 | CT18: 0 | CV18: x | CW18: x | DC18: =_xlfn.XLOOKUP(C18,[1]Overtime!$B$8:$B$2327,[1]Overtime!$BA$8:$BA$2327,"",,-1) -> 0 | DD18: =_xlfn.XLOOKUP(C18,[1]Timesheet!$B$9:$B$2328,[1]Timesheet!$BS$9:$BS$2328,0,,-1) -> 0 | DE18: =_xlfn.XLOOKUP(C18,[1]Timesheet!$B$7:$B$616,[1]Timesheet!$BK$7:$BK$616,0)+_xlfn.XLOOKUP(C18,[1]Timesheet!$B$7:$B$616,[1]Timesheet!$AV$7:$AV$616,0)-_xlfn.XLOOKUP(C18,[1]Timesheet!$B$7:$B$616,[1]Timesheet!$AX$7:$AX$616,0)+_xlfn.XLOOKUP(C18,[1]Timesheet!$B$7:$B$616,[1]Timesheet!$AW$7:$AW$616,0)-_xlfn.XLOOKUP(C18,[1]Timesheet!$B$7:$B$616,[1]Timesheet!$AY$7:$AY$616,0) -> 1 | DF18: =DE18*(-100000) -> -100000 | DG18: =_xlfn.XLOOKUP(C18,[1]Timesheet!$B$7:$B$616,[1]Timesheet!$BV$7:$BV$616,0)+_xlfn.XLOOKUP(C18,[1]Timesheet!$B$7:$B$616,[1]Timesheet!$AX$7:$AX$616,0)++_xlfn.XLOOKUP(C18,[1]Timesheet!$B$7:$B$616,[1]Timesheet!$AY$7:$AY$616,0) -> 0 | DH18: =IF(DG18>2,-1000000,IF(DG18=2,-500000,IF(DG18=1,-200000,0))) -> 0 | DI18: =_xlfn.XLOOKUP(C18,[1]Timesheet!$B$7:$B$616,[1]Timesheet!$AZ$7:$AZ$616,0)+_xlfn.XLOOKUP(C18,[1]Timesheet!$B$7:$B$616,[1]Timesheet!$BA$7:$BA$616,0) -> 0 | DJ18: =IF(CW18="x",IF((ROUND(Y18*W18/$J$3,0))<0,0,ROUND(Y18*W18/$J$3,0)),IF(OR(CR18>0,CS18>0,CT18>0),W18/$J$3*(Y18+_xlfn.XLOOKUP(C18,[1]Timesheet!B:B,[1]Timesheet!BS:BS,0,,-1)+_xlfn.XLOOKUP(C18,[1]Timesheet!B:B,[1]Timesheet!BU:BU,0,,-1)),IF(OR(DH18<0,DF18<0),IF(DI18>0,W18/$J$3*($J$3-DI18),W18),W18/$J$3*(Y18+_xlfn.XLOOKUP(C18,[1]Timesheet!B:B,[1]Timesheet!BS:BS,0,,-1)+_xlfn.XLOOKUP(C18,[1]Timesheet!B:B,[1]Timesheet!BU:BU,0,,-1))))) -> 19231 | DK18: =DF18+DH18 -> -100000 | DL18: =_xlfn.XLOOKUP(C18,[1]Timesheet!$B$7:$B$565,[1]Timesheet!$BB$7:$BB$565,0) -> 0 | DM18: =_xlfn.XLOOKUP(C18,[1]Timesheet!$B$7:$B$565,[1]Timesheet!$BC$7:$BC$565,0) -> 0 | DN18: =_xlfn.XLOOKUP(C18,[1]Timesheet!$B$7:$B$565,[1]Timesheet!$BF$7:$BF$565,0) -> 0 | DO18: =_xlfn.XLOOKUP(C18,[1]Timesheet!$B$7:$B$565,[1]Timesheet!$BJ$7:$BJ$565,0) -> 0 | DP18: =DN18+DO18 -> 0 | DQ18: =_xlfn.XLOOKUP(C18,[1]Timesheet!$B$7:$B$565,[1]Timesheet!$BT$7:$BT$565,0) -> 21 | DR18: =_xlfn.XLOOKUP(C18,[1]Timesheet!$B$7:$B$565,[1]Timesheet!$BM$7:$BM$565,0) -> 0 | DS18: =W18/$J$3*DR18 -> 0 | DT18: =ROUND(IF(BH18>0,L18*$DT$7,0),0) -> 0 | DU18: =ROUND(IF(BI18>0,L18*$DU$7,0),0) -> 0 | DV18: =ROUND(IF(BJ18>0,M18*$DV$7,0),0) -> 0 | DW18: =ROUND(IF(BK18>0,L18*$DW$7,0),0) -> 0 | DX18: =SUM(N18:X18) -> 6800000 | DY18: =SUM(O18:S18) -> 600000 | DZ18: =SUM(W18:X18) -> 1000000 | EA18: =_xlfn.XLOOKUP(C18,[1]Timesheet!$B$7:$B$565,[1]Timesheet!$BI$7:$BI$565,0) -> 0 | EB18: =IF(AC18>0,ROUND((BE18+CX18+CY18-AE18-AN18-AW18-AC18)*15%,0),0) -> 0 | EC18: =AC18 -> 0 | ED18: =EB18-EC18 -> 0 | EE18: =BE18+CX18+CY18-AE18-AN18-AW18-BL18 -> 0 | EF18: =ROUND((SUM(N18:P18)+W18+X18+T18+U18+V18)/($J$3*8)*_xlfn.XLOOKUP(C18,[1]Overtime!$B$9:$B$557,[1]Overtime!$AU$9:$AU$557,0),0) -> 62500 | EG18: =ROUND(((SUM(N18:P18)+W18+X18+T18+U18+V18)/($J$3*8))*_xlfn.XLOOKUP(C18,[1]Overtime!$B$9:$B$557,[1]Overtime!$AY$9:$AY$557,0),0) -> 31250 | EH18: =ROUND(EG18+EF18,0) -> 93750 | EI18: =AL18-EF18 -> 0 | EJ18: =AM18-EG18 -> 0 | EK18: =ROUND((SUM(N18:P18)+W18+X18+T18+U18+V18)/($J$3*8)*_xlfn.XLOOKUP(C18,[1]Overtime!$B$9:$B$557,[1]Overtime!$AO$9:$AO$557,0)*1.5,0) -> 93750 | EL18: =ROUND((SUM(N18:P18)+W18+X18+T18+U18+V18)/($J$3*8)*_xlfn.XLOOKUP(C18,[1]Overtime!$B$9:$B$557,[1]Overtime!$AP$9:$AP$557,0)*2,0) -> 0 | EM18: =AN18-EK18-EL18 -> 0 | EN18: =ROUND(Y18*W18/$J$3,0) -> 19231 | EO18: =DJ18-EN18 -> 0 | EP18: =IF(AI18=0,0,AI18-DK18-EN18) -> 0 | EQ18: 0 | ER18: =EQ18/4400000 -> 0
B19: =B18+1 -> 10 | C19: TIQN-2236 | D19: Nguyễn Thị Thu Hằng | E19: =IF(CW19="x","Probation",IF(CR19>0,"Resigned - Official","Official")) -> Probation | F19: =IF(H19="management","6421.11",0) -> 0 | G19: Sewing | H19: Direct | I19: Line 01 | J19: Sewing | K19: Sewing worker | L19: =M19 -> 6500000 | M19: =N19+O19+P19+W19+X19+T19+U19+V19 -> 6500000 | N19: 5200000 | O19: 300000 | P19: 0 | Q19: 0 | R19: 300000 | S19: 0 | T19: 0 | U19: 0 | V19: 0 | W19: 1000000 | X19: 0 | Y19: =_xlfn.XLOOKUP(C19,[1]Timesheet!$B$9:$B$25,[1]Timesheet!$AO$9:$AO$25,0,,1) -> 1 | Z19: =ROUND(N19/$J$3*Y19,0) -> 200000 | AA19: =ROUND(O19/$J$3*(Y19+_xlfn.XLOOKUP(C19,[1]Timesheet!B:B,[1]Timesheet!BS:BS,0)),0) -> 11538 | AB19: =ROUND(IF(Y19>=8,P19,(P19/$J$3)*(Y19+_xlfn.XLOOKUP(C19,[1]Timesheet!B:B,[1]Timesheet!BS:BS,0))),0) -> 0 | AC19: =ROUND(IF(Y19>=14,Q19,(Q19/2)),0) -> 0 | AD19: =IF(_xlfn.XLOOKUP(Salary!C19,[1]Bus!B:B,[1]Bus!G:G,"",,-1)=1,0,ROUND((R19/$J$3)*ROUND(Y19+_xlfn.XLOOKUP(C19,[1]Timesheet!B:B,[1]Timesheet!BS:BS,0,,-1),0),0)) -> 11538 | AE19: =IF(Y19>0,S19,0) -> 0 | AF19: =ROUND(IF(Y19>=8,T19,(T19/$J$3)*(Y19+_xlfn.XLOOKUP(C19,[1]Timesheet!B:B,[1]Timesheet!BS:BS,0))),0) -> 0 | AG19: =ROUND(IF(Y19>=8,U19,(U19/$J$3)*(Y19+_xlfn.XLOOKUP(C19,[1]Timesheet!B:B,[1]Timesheet!BS:BS,0))),0) -> 0 | AH19: =ROUND(IF(OR(CR19>0,Y19<8),(V19/$J$3)*(Y19+_xlfn.XLOOKUP(C19,[1]Timesheet!B:B,[1]Timesheet!BS:BS,0)),V19),0) -> 0 | AI19: =ROUND(IF(DAY(CR19)=26,IF(Y19=0,0,IF(W19=0,0,IF(OR(-(DK19)>DJ19,-(DK19)=DJ19),0,DJ19+DK19+DS19))),IF(CR19>0,0,IF(Y19=0,0,IF(W19=0,0,IF(OR(-(DK19)>DJ19,-(DK19)=DJ19),0,DJ19+DK19+DS19))))),0) -> 0 | AJ19: =IF(Y19>0,ROUND(IF(LEN(CR19)>2,(X19/$J$3)*(Y19+_xlfn.XLOOKUP(C19,[1]Timesheet!B:B,[1]Timesheet!BS:BS,0)),X19),0),0) -> 0 | AK19: =_xlfn.XLOOKUP(C19,[1]Overtime!$B$7:$B$557,[1]Overtime!$AN$7:$AN$557,0) -> 0 | AL19: =ROUND(((SUM(N19:P19)+SUM(T19:X19))/($J$3*8))*_xlfn.XLOOKUP(C19,[1]Overtime!$B$9:$B$557,[1]Overtime!$AU$9:$AU$557,0),0) -> 0 | AM19: =ROUND(((SUM(N19:P19)+SUM(T19:X19))/($J$3*8))*_xlfn.XLOOKUP(C19,[1]Overtime!$B$9:$B$557,[1]Overtime!$AY$9:$AY$557,0),0) -> 0 | AN19: =ROUND(AM19+AL19,0) -> 0 | AR19: =ROUND(_xlfn.XLOOKUP(C19,[1]Timesheet!$B$9:$B$458,[1]Timesheet!$BQ$9:$BQ$458,,,-1)*SUM(Salary!N19:P19,Salary!T19:X19)*20%/Salary!$J$3,0) -> 0 | AS19: 20000 | AT19: 0 | AV19: =IF(CV19="x",IF(IF(CR19>0,$CW$3-_xlfn.XLOOKUP(C19,[1]Timesheet!B:B,[1]Timesheet!BW:BW,0,,-1),$CW$3-_xlfn.XLOOKUP(C19,[1]Timesheet!B:B,[1]Timesheet!BW:BW,0,,-1)-$EB$3)<14,ROUND(L19*20.5%+M19*1%,0),0),0) -> 0 | AW19: =CK19 -> 0 | AX19: =CM19 -> 46875 | AZ19: 0 | BE19: =ROUND(SUM(Z19:AJ19)+AN19+AX19+AT19+AO19+AR19+AS19+AW19+AY19+AV19+AP19+AU19+AQ19+AZ19+BA19,0) -> 289951 | BF19: =IF(OR(CW19="x",CR19>0),0,15500000) -> 0 | BG19: 0 | BJ19: =IF(CV19="x",0,ROUND(IF(BH19>0,M19*1%,0),0)) -> 0 | BK19: =IF(CV19="x",0,ROUND(IF(BH19>0,38948,0),0)) -> 0 | BL19: =ROUND(IF(AC19>0,IF(ROUND((BE19+CX19+CY19-AE19-AN19-AW19-AC19)*15%,0)>AC19,BE19+CX19+CY19-AE19-AN19-AW19,BE19+CX19+CY19-AE19-AN19-AW19-AC19+ROUND((BE19+CX19+CY19-AE19-AN19-AW19-AC19)*15%,0)),BE19+CX19+CY19-AE19-AN19-AW19),0) -> 289951 | BM19: =IF(OR(CW19="x",CR19>0),BL19,IF(BL19-BF19-BG19-SUM(BH19:BJ19)>0,BL19-BF19-BG19-SUM(BH19:BJ19),0)) -> 289951 | BN19: =IF(OR(CW19="x",CR19>0),ROUND(IF(BM19>4999999,BM19*10%,0),0),ROUND(IF(BM19>100000000,((BM19-100000000)*0.35+20500000),IF(AND(BM19>60000000,BM19<=100000000),((BM19-60000000)*0.3+8500000),IF(AND(BM19>30000000,BM19<=60000000),((BM19-30000000)*0.2+2500000),IF(AND(BM19>10000000,BM19<=30000000),((BM19-10000000)*0.1+500000),IF(BM19<0,0,(BM19*0.05)))))),0)) -> 0 | BO19: =SUM(BH19:BK19,BN19) -> 0 | BP19: =IF(CV19="x",0,ROUND(IF(BH19>0,L19*17.5%,0),0)) -> 0 | BQ19: =IF(CV19="x",0,ROUND(IF(BI19>0,L19*3%,0),0)) -> 0 | BR19: =IF(CV19="x",0,ROUND(IF(BJ19>0,M19*1%,0),0)) -> 0 | BS19: =IF(CV19="x",0,ROUND(IF(BK19>0,L19*2%,0),0)) -> 0 | BW19: 0 | CG19: =ROUND(BE19-BO19+BZ19-BT19-BU19-BX19-BV19+BW19+BY19+CA19-CB19,0) -> 289951 | CH19: =CG19+BN19+SUM(BH19:BK19)+SUM(BP19:BS19) -> 289951 | CI19: =IF(BH19=0,0,ROUND((SUM(N19:X19)-(R19+S19))/12,0)) -> 0 | CK19: =ROUND((M19/$CK$3*CJ19),0) -> 0 | CL19: 1.5 | CM19: =ROUND((M19/$J$3/8*CL19),0) -> 46875 | CO19: =CK19+CM19 -> 46875 | CP19: 46196 | CQ19: 46226 | CR19: 46202 | CS19: 0 | CT19: 0 | CV19: x | CW19: x | DC19: =_xlfn.XLOOKUP(C19,[1]Overtime!$B$8:$B$2327,[1]Overtime!$BA$8:$BA$2327,"",,-1) -> 0 | DD19: =_xlfn.XLOOKUP(C19,[1]Timesheet!$B$9:$B$2328,[1]Timesheet!$BS$9:$BS$2328,0,,-1) -> 0 | DE19: =_xlfn.XLOOKUP(C19,[1]Timesheet!$B$7:$B$616,[1]Timesheet!$BK$7:$BK$616,0)+_xlfn.XLOOKUP(C19,[1]Timesheet!$B$7:$B$616,[1]Timesheet!$AV$7:$AV$616,0)-_xlfn.XLOOKUP(C19,[1]Timesheet!$B$7:$B$616,[1]Timesheet!$AX$7:$AX$616,0)+_xlfn.XLOOKUP(C19,[1]Timesheet!$B$7:$B$616,[1]Timesheet!$AW$7:$AW$616,0)-_xlfn.XLOOKUP(C19,[1]Timesheet!$B$7:$B$616,[1]Timesheet!$AY$7:$AY$616,0) -> 0 | DF19: =DE19*(-100000) -> 0 | DG19: =_xlfn.XLOOKUP(C19,[1]Timesheet!$B$7:$B$616,[1]Timesheet!$BV$7:$BV$616,0)+_xlfn.XLOOKUP(C19,[1]Timesheet!$B$7:$B$616,[1]Timesheet!$AX$7:$AX$616,0)++_xlfn.XLOOKUP(C19,[1]Timesheet!$B$7:$B$616,[1]Timesheet!$AY$7:$AY$616,0) -> 1 | DH19: =IF(DG19>2,-1000000,IF(DG19=2,-500000,IF(DG19=1,-200000,0))) -> -200000 | DI19: =_xlfn.XLOOKUP(C19,[1]Timesheet!$B$7:$B$616,[1]Timesheet!$AZ$7:$AZ$616,0)+_xlfn.XLOOKUP(C19,[1]Timesheet!$B$7:$B$616,[1]Timesheet!$BA$7:$BA$616,0) -> 0 | DJ19: =IF(CW19="x",IF((ROUND(Y19*W19/$J$3,0))<0,0,ROUND(Y19*W19/$J$3,0)),IF(OR(CR19>0,CS19>0,CT19>0),W19/$J$3*(Y19+_xlfn.XLOOKUP(C19,[1]Timesheet!B:B,[1]Timesheet!BS:BS,0,,-1)+_xlfn.XLOOKUP(C19,[1]Timesheet!B:B,[1]Timesheet!BU:BU,0,,-1)),IF(OR(DH19<0,DF19<0),IF(DI19>0,W19/$J$3*($J$3-DI19),W19),W19/$J$3*(Y19+_xlfn.XLOOKUP(C19,[1]Timesheet!B:B,[1]Timesheet!BS:BS,0,,-1)+_xlfn.XLOOKUP(C19,[1]Timesheet!B:B,[1]Timesheet!BU:BU,0,,-1))))) -> 38462 | DK19: =DF19+DH19 -> -200000 | DL19: =_xlfn.XLOOKUP(C19,[1]Timesheet!$B$7:$B$565,[1]Timesheet!$BB$7:$BB$565,0) -> 0 | DM19: =_xlfn.XLOOKUP(C19,[1]Timesheet!$B$7:$B$565,[1]Timesheet!$BC$7:$BC$565,0) -> 0 | DN19: =_xlfn.XLOOKUP(C19,[1]Timesheet!$B$7:$B$565,[1]Timesheet!$BF$7:$BF$565,0) -> 0 | DO19: =_xlfn.XLOOKUP(C19,[1]Timesheet!$B$7:$B$565,[1]Timesheet!$BJ$7:$BJ$565,0) -> 0 | DP19: =DN19+DO19 -> 0 | DQ19: =_xlfn.XLOOKUP(C19,[1]Timesheet!$B$7:$B$565,[1]Timesheet!$BT$7:$BT$565,0) -> 21 | DR19: =_xlfn.XLOOKUP(C19,[1]Timesheet!$B$7:$B$565,[1]Timesheet!$BM$7:$BM$565,0) -> 0 | DS19: =W19/$J$3*DR19 -> 0 | DT19: =ROUND(IF(BH19>0,L19*$DT$7,0),0) -> 0 | DU19: =ROUND(IF(BI19>0,L19*$DU$7,0),0) -> 0 | DV19: =ROUND(IF(BJ19>0,M19*$DV$7,0),0) -> 0 | DW19: =ROUND(IF(BK19>0,L19*$DW$7,0),0) -> 0 | DX19: =SUM(N19:X19) -> 6800000 | DY19: =SUM(O19:S19) -> 600000 | DZ19: =SUM(W19:X19) -> 1000000 | EA19: =_xlfn.XLOOKUP(C19,[1]Timesheet!$B$7:$B$565,[1]Timesheet!$BI$7:$BI$565,0) -> 1 | EB19: =IF(AC19>0,ROUND((BE19+CX19+CY19-AE19-AN19-AW19-AC19)*15%,0),0) -> 0 | EC19: =AC19 -> 0 | ED19: =EB19-EC19 -> 0 | EE19: =BE19+CX19+CY19-AE19-AN19-AW19-BL19 -> 0 | EF19: =ROUND((SUM(N19:P19)+W19+X19+T19+U19+V19)/($J$3*8)*_xlfn.XLOOKUP(C19,[1]Overtime!$B$9:$B$557,[1]Overtime!$AU$9:$AU$557,0),0) -> 0 | EG19: =ROUND(((SUM(N19:P19)+W19+X19+T19+U19+V19)/($J$3*8))*_xlfn.XLOOKUP(C19,[1]Overtime!$B$9:$B$557,[1]Overtime!$AY$9:$AY$557,0),0) -> 0 | EH19: =ROUND(EG19+EF19,0) -> 0 | EI19: =AL19-EF19 -> 0 | EJ19: =AM19-EG19 -> 0 | EK19: =ROUND((SUM(N19:P19)+W19+X19+T19+U19+V19)/($J$3*8)*_xlfn.XLOOKUP(C19,[1]Overtime!$B$9:$B$557,[1]Overtime!$AO$9:$AO$557,0)*1.5,0) -> 0 | EL19: =ROUND((SUM(N19:P19)+W19+X19+T19+U19+V19)/($J$3*8)*_xlfn.XLOOKUP(C19,[1]Overtime!$B$9:$B$557,[1]Overtime!$AP$9:$AP$557,0)*2,0) -> 0 | EM19: =AN19-EK19-EL19 -> 0 | EN19: =ROUND(Y19*W19/$J$3,0) -> 38462 | EO19: =DJ19-EN19 -> 0 | EP19: =IF(AI19=0,0,AI19-DK19-EN19) -> 0 | EQ19: 0 | ER19: =EQ19/4400000 -> 0
B20: =B19+1 -> 11 | C20: TIQN-2247 | D20: Trần Văn Viên | E20: =IF(CW20="x","Probation",IF(CR20>0,"Resigned - Official","Official")) -> Probation | F20: =IF(H20="management","6421.11",0) -> 0 | G20: Preparation | H20: Indirect | I20: Cutting | J20: Preparation | K20: Cutter-Trainee | L20: =M20 -> 6500000 | M20: =N20+O20+P20+W20+X20+T20+U20+V20 -> 6500000 | N20: 5200000 | O20: 300000 | P20: 0 | Q20: 0 | R20: 300000 | S20: 0 | T20: 0 | U20: 0 | V20: 0 | W20: 1000000 | X20: 0 | Y20: =_xlfn.XLOOKUP(C20,[1]Timesheet!$B$9:$B$25,[1]Timesheet!$AO$9:$AO$25,0,,1) -> 2 | Z20: =ROUND(N20/$J$3*Y20,0) -> 400000 | AA20: =ROUND(O20/$J$3*(Y20+_xlfn.XLOOKUP(C20,[1]Timesheet!B:B,[1]Timesheet!BS:BS,0)),0) -> 23077 | AB20: =ROUND(IF(Y20>=8,P20,(P20/$J$3)*(Y20+_xlfn.XLOOKUP(C20,[1]Timesheet!B:B,[1]Timesheet!BS:BS,0))),0) -> 0 | AC20: =ROUND(IF(Y20>=14,Q20,(Q20/2)),0) -> 0 | AD20: =IF(_xlfn.XLOOKUP(Salary!C20,[1]Bus!B:B,[1]Bus!G:G,"",,-1)=1,0,ROUND((R20/$J$3)*ROUND(Y20+_xlfn.XLOOKUP(C20,[1]Timesheet!B:B,[1]Timesheet!BS:BS,0,,-1),0),0)) -> 23077 | AE20: =IF(Y20>0,S20,0) -> 0 | AF20: =ROUND(IF(Y20>=8,T20,(T20/$J$3)*(Y20+_xlfn.XLOOKUP(C20,[1]Timesheet!B:B,[1]Timesheet!BS:BS,0))),0) -> 0 | AG20: =ROUND(IF(Y20>=8,U20,(U20/$J$3)*(Y20+_xlfn.XLOOKUP(C20,[1]Timesheet!B:B,[1]Timesheet!BS:BS,0))),0) -> 0 | AH20: =ROUND(IF(OR(CR20>0,Y20<8),(V20/$J$3)*(Y20+_xlfn.XLOOKUP(C20,[1]Timesheet!B:B,[1]Timesheet!BS:BS,0)),V20),0) -> 0 | AI20: =ROUND(IF(DAY(CR20)=26,IF(Y20=0,0,IF(W20=0,0,IF(OR(-(DK20)>DJ20,-(DK20)=DJ20),0,DJ20+DK20+DS20))),IF(CR20>0,0,IF(Y20=0,0,IF(W20=0,0,IF(OR(-(DK20)>DJ20,-(DK20)=DJ20),0,DJ20+DK20+DS20))))),0) -> 0 | AJ20: =IF(Y20>0,ROUND(IF(LEN(CR20)>2,(X20/$J$3)*(Y20+_xlfn.XLOOKUP(C20,[1]Timesheet!B:B,[1]Timesheet!BS:BS,0)),X20),0),0) -> 0 | AK20: =_xlfn.XLOOKUP(C20,[1]Overtime!$B$7:$B$557,[1]Overtime!$AN$7:$AN$557,0) -> 0 | AL20: =ROUND(((SUM(N20:P20)+SUM(T20:X20))/($J$3*8))*_xlfn.XLOOKUP(C20,[1]Overtime!$B$9:$B$557,[1]Overtime!$AU$9:$AU$557,0),0) -> 0 | AM20: =ROUND(((SUM(N20:P20)+SUM(T20:X20))/($J$3*8))*_xlfn.XLOOKUP(C20,[1]Overtime!$B$9:$B$557,[1]Overtime!$AY$9:$AY$557,0),0) -> 0 | AN20: =ROUND(AM20+AL20,0) -> 0 | AR20: =ROUND(_xlfn.XLOOKUP(C20,[1]Timesheet!$B$9:$B$458,[1]Timesheet!$BQ$9:$BQ$458,,,-1)*SUM(Salary!N20:P20,Salary!T20:X20)*20%/Salary!$J$3,0) -> 0 | AS20: 0 | AT20: 0 | AV20: =IF(CV20="x",IF(IF(CR20>0,$CW$3-_xlfn.XLOOKUP(C20,[1]Timesheet!B:B,[1]Timesheet!BW:BW,0,,-1),$CW$3-_xlfn.XLOOKUP(C20,[1]Timesheet!B:B,[1]Timesheet!BW:BW,0,,-1)-$EB$3)<14,ROUND(L20*20.5%+M20*1%,0),0),0) -> 0 | AW20: =CK20 -> 0 | AX20: =CM20 -> 0 | AZ20: 0 | BE20: =ROUND(SUM(Z20:AJ20)+AN20+AX20+AT20+AO20+AR20+AS20+AW20+AY20+AV20+AP20+AU20+AQ20+AZ20+BA20,0) -> 446154 | BF20: =IF(OR(CW20="x",CR20>0),0,15500000) -> 0 | BG20: 0 | BJ20: =IF(CV20="x",0,ROUND(IF(BH20>0,M20*1%,0),0)) -> 0 | BK20: =IF(CV20="x",0,ROUND(IF(BH20>0,38948,0),0)) -> 0 | BL20: =ROUND(IF(AC20>0,IF(ROUND((BE20+CX20+CY20-AE20-AN20-AW20-AC20)*15%,0)>AC20,BE20+CX20+CY20-AE20-AN20-AW20,BE20+CX20+CY20-AE20-AN20-AW20-AC20+ROUND((BE20+CX20+CY20-AE20-AN20-AW20-AC20)*15%,0)),BE20+CX20+CY20-AE20-AN20-AW20),0) -> 446154 | BM20: =IF(OR(CW20="x",CR20>0),BL20,IF(BL20-BF20-BG20-SUM(BH20:BJ20)>0,BL20-BF20-BG20-SUM(BH20:BJ20),0)) -> 446154 | BN20: =IF(OR(CW20="x",CR20>0),ROUND(IF(BM20>4999999,BM20*10%,0),0),ROUND(IF(BM20>100000000,((BM20-100000000)*0.35+20500000),IF(AND(BM20>60000000,BM20<=100000000),((BM20-60000000)*0.3+8500000),IF(AND(BM20>30000000,BM20<=60000000),((BM20-30000000)*0.2+2500000),IF(AND(BM20>10000000,BM20<=30000000),((BM20-10000000)*0.1+500000),IF(BM20<0,0,(BM20*0.05)))))),0)) -> 0 | BO20: =SUM(BH20:BK20,BN20) -> 0 | BP20: =IF(CV20="x",0,ROUND(IF(BH20>0,L20*17.5%,0),0)) -> 0 | BQ20: =IF(CV20="x",0,ROUND(IF(BI20>0,L20*3%,0),0)) -> 0 | BR20: =IF(CV20="x",0,ROUND(IF(BJ20>0,M20*1%,0),0)) -> 0 | BS20: =IF(CV20="x",0,ROUND(IF(BK20>0,L20*2%,0),0)) -> 0 | BW20: 0 | CG20: =ROUND(BE20-BO20+BZ20-BT20-BU20-BX20-BV20+BW20+BY20+CA20-CB20,0) -> 446154 | CH20: =CG20+BN20+SUM(BH20:BK20)+SUM(BP20:BS20) -> 446154 | CI20: =IF(BH20=0,0,ROUND((SUM(N20:X20)-(R20+S20))/12,0)) -> 0 | CK20: =ROUND((M20/$CK$3*CJ20),0) -> 0 | CM20: =ROUND((M20/$J$3/8*CL20),0) -> 0 | CO20: =CK20+CM20 -> 0 | CP20: 46199 | CQ20: 46229 | CR20: 46206 | CS20: 0 | CT20: 0 | CV20: x | CW20: x | DC20: =_xlfn.XLOOKUP(C20,[1]Overtime!$B$8:$B$2327,[1]Overtime!$BA$8:$BA$2327,"",,-1) -> 0 | DD20: =_xlfn.XLOOKUP(C20,[1]Timesheet!$B$9:$B$2328,[1]Timesheet!$BS$9:$BS$2328,0,,-1) -> 0 | DE20: =_xlfn.XLOOKUP(C20,[1]Timesheet!$B$7:$B$616,[1]Timesheet!$BK$7:$BK$616,0)+_xlfn.XLOOKUP(C20,[1]Timesheet!$B$7:$B$616,[1]Timesheet!$AV$7:$AV$616,0)-_xlfn.XLOOKUP(C20,[1]Timesheet!$B$7:$B$616,[1]Timesheet!$AX$7:$AX$616,0)+_xlfn.XLOOKUP(C20,[1]Timesheet!$B$7:$B$616,[1]Timesheet!$AW$7:$AW$616,0)-_xlfn.XLOOKUP(C20,[1]Timesheet!$B$7:$B$616,[1]Timesheet!$AY$7:$AY$616,0) -> 0 | DF20: =DE20*(-100000) -> 0 | DG20: =_xlfn.XLOOKUP(C20,[1]Timesheet!$B$7:$B$616,[1]Timesheet!$BV$7:$BV$616,0)+_xlfn.XLOOKUP(C20,[1]Timesheet!$B$7:$B$616,[1]Timesheet!$AX$7:$AX$616,0)++_xlfn.XLOOKUP(C20,[1]Timesheet!$B$7:$B$616,[1]Timesheet!$AY$7:$AY$616,0) -> 4 | DH20: =IF(DG20>2,-1000000,IF(DG20=2,-500000,IF(DG20=1,-200000,0))) -> -1000000 | DI20: =_xlfn.XLOOKUP(C20,[1]Timesheet!$B$7:$B$616,[1]Timesheet!$AZ$7:$AZ$616,0)+_xlfn.XLOOKUP(C20,[1]Timesheet!$B$7:$B$616,[1]Timesheet!$BA$7:$BA$616,0) -> 0 | DJ20: =IF(CW20="x",IF((ROUND(Y20*W20/$J$3,0))<0,0,ROUND(Y20*W20/$J$3,0)),IF(OR(CR20>0,CS20>0,CT20>0),W20/$J$3*(Y20+_xlfn.XLOOKUP(C20,[1]Timesheet!B:B,[1]Timesheet!BS:BS,0,,-1)+_xlfn.XLOOKUP(C20,[1]Timesheet!B:B,[1]Timesheet!BU:BU,0,,-1)),IF(OR(DH20<0,DF20<0),IF(DI20>0,W20/$J$3*($J$3-DI20),W20),W20/$J$3*(Y20+_xlfn.XLOOKUP(C20,[1]Timesheet!B:B,[1]Timesheet!BS:BS,0,,-1)+_xlfn.XLOOKUP(C20,[1]Timesheet!B:B,[1]Timesheet!BU:BU,0,,-1))))) -> 76923 | DK20: =DF20+DH20 -> -1000000 | DL20: =_xlfn.XLOOKUP(C20,[1]Timesheet!$B$7:$B$565,[1]Timesheet!$BB$7:$BB$565,0) -> 0 | DM20: =_xlfn.XLOOKUP(C20,[1]Timesheet!$B$7:$B$565,[1]Timesheet!$BC$7:$BC$565,0) -> 0 | DN20: =_xlfn.XLOOKUP(C20,[1]Timesheet!$B$7:$B$565,[1]Timesheet!$BF$7:$BF$565,0) -> 0 | DO20: =_xlfn.XLOOKUP(C20,[1]Timesheet!$B$7:$B$565,[1]Timesheet!$BJ$7:$BJ$565,0) -> 2 | DP20: =DN20+DO20 -> 2 | DQ20: =_xlfn.XLOOKUP(C20,[1]Timesheet!$B$7:$B$565,[1]Timesheet!$BT$7:$BT$565,0) -> 21 | DR20: =_xlfn.XLOOKUP(C20,[1]Timesheet!$B$7:$B$565,[1]Timesheet!$BM$7:$BM$565,0) -> 0 | DS20: =W20/$J$3*DR20 -> 0 | DT20: =ROUND(IF(BH20>0,L20*$DT$7,0),0) -> 0 | DU20: =ROUND(IF(BI20>0,L20*$DU$7,0),0) -> 0 | DV20: =ROUND(IF(BJ20>0,M20*$DV$7,0),0) -> 0 | DW20: =ROUND(IF(BK20>0,L20*$DW$7,0),0) -> 0 | DX20: =SUM(N20:X20) -> 6800000 | DY20: =SUM(O20:S20) -> 600000 | DZ20: =SUM(W20:X20) -> 1000000 | EA20: =_xlfn.XLOOKUP(C20,[1]Timesheet!$B$7:$B$565,[1]Timesheet!$BI$7:$BI$565,0) -> 4 | EB20: =IF(AC20>0,ROUND((BE20+CX20+CY20-AE20-AN20-AW20-AC20)*15%,0),0) -> 0 | EC20: =AC20 -> 0 | ED20: =EB20-EC20 -> 0 | EE20: =BE20+CX20+CY20-AE20-AN20-AW20-BL20 -> 0 | EF20: =ROUND((SUM(N20:P20)+W20+X20+T20+U20+V20)/($J$3*8)*_xlfn.XLOOKUP(C20,[1]Overtime!$B$9:$B$557,[1]Overtime!$AU$9:$AU$557,0),0) -> 0 | EG20: =ROUND(((SUM(N20:P20)+W20+X20+T20+U20+V20)/($J$3*8))*_xlfn.XLOOKUP(C20,[1]Overtime!$B$9:$B$557,[1]Overtime!$AY$9:$AY$557,0),0) -> 0 | EH20: =ROUND(EG20+EF20,0) -> 0 | EI20: =AL20-EF20 -> 0 | EJ20: =AM20-EG20 -> 0 | EK20: =ROUND((SUM(N20:P20)+W20+X20+T20+U20+V20)/($J$3*8)*_xlfn.XLOOKUP(C20,[1]Overtime!$B$9:$B$557,[1]Overtime!$AO$9:$AO$557,0)*1.5,0) -> 0 | EL20: =ROUND((SUM(N20:P20)+W20+X20+T20+U20+V20)/($J$3*8)*_xlfn.XLOOKUP(C20,[1]Overtime!$B$9:$B$557,[1]Overtime!$AP$9:$AP$557,0)*2,0) -> 0 | EM20: =AN20-EK20-EL20 -> 0 | EN20: =ROUND(Y20*W20/$J$3,0) -> 76923 | EO20: =DJ20-EN20 -> 0 | EP20: =IF(AI20=0,0,AI20-DK20-EN20) -> 0 | EQ20: 0 | ER20: =EQ20/4400000 -> 0
B21: =B20+1 -> 12 | C21: TIQN-2249 | D21: Phạm Văn Hưng | E21: =IF(CW21="x","Probation",IF(CR21>0,"Resigned - Official","Official")) -> Probation | F21: =IF(H21="management","6421.11",0) -> 0 | G21: Sewing | H21: Direct | I21: Line 10 | J21: Sewing | K21: Supporting worker | L21: =M21 -> 6500000 | M21: =N21+O21+P21+W21+X21+T21+U21+V21 -> 6500000 | N21: 5200000 | O21: 300000 | P21: 0 | Q21: 0 | R21: 300000 | S21: 0 | T21: 0 | U21: 0 | V21: 0 | W21: 1000000 | X21: 0 | Y21: =_xlfn.XLOOKUP(C21,[1]Timesheet!$B$9:$B$25,[1]Timesheet!$AO$9:$AO$25,0,,1) -> 2 | Z21: =ROUND(N21/$J$3*Y21,0) -> 400000 | AA21: =ROUND(O21/$J$3*(Y21+_xlfn.XLOOKUP(C21,[1]Timesheet!B:B,[1]Timesheet!BS:BS,0)),0) -> 23077 | AB21: =ROUND(IF(Y21>=8,P21,(P21/$J$3)*(Y21+_xlfn.XLOOKUP(C21,[1]Timesheet!B:B,[1]Timesheet!BS:BS,0))),0) -> 0 | AC21: =ROUND(IF(Y21>=14,Q21,(Q21/2)),0) -> 0 | AD21: =IF(_xlfn.XLOOKUP(Salary!C21,[1]Bus!B:B,[1]Bus!G:G,"",,-1)=1,0,ROUND((R21/$J$3)*ROUND(Y21+_xlfn.XLOOKUP(C21,[1]Timesheet!B:B,[1]Timesheet!BS:BS,0,,-1),0),0)) -> 23077 | AE21: =IF(Y21>0,S21,0) -> 0 | AF21: =ROUND(IF(Y21>=8,T21,(T21/$J$3)*(Y21+_xlfn.XLOOKUP(C21,[1]Timesheet!B:B,[1]Timesheet!BS:BS,0))),0) -> 0 | AG21: =ROUND(IF(Y21>=8,U21,(U21/$J$3)*(Y21+_xlfn.XLOOKUP(C21,[1]Timesheet!B:B,[1]Timesheet!BS:BS,0))),0) -> 0 | AH21: =ROUND(IF(OR(CR21>0,Y21<8),(V21/$J$3)*(Y21+_xlfn.XLOOKUP(C21,[1]Timesheet!B:B,[1]Timesheet!BS:BS,0)),V21),0) -> 0 | AI21: =ROUND(IF(DAY(CR21)=26,IF(Y21=0,0,IF(W21=0,0,IF(OR(-(DK21)>DJ21,-(DK21)=DJ21),0,DJ21+DK21+DS21))),IF(CR21>0,0,IF(Y21=0,0,IF(W21=0,0,IF(OR(-(DK21)>DJ21,-(DK21)=DJ21),0,DJ21+DK21+DS21))))),0) -> 0 | AJ21: =IF(Y21>0,ROUND(IF(LEN(CR21)>2,(X21/$J$3)*(Y21+_xlfn.XLOOKUP(C21,[1]Timesheet!B:B,[1]Timesheet!BS:BS,0)),X21),0),0) -> 0 | AK21: =_xlfn.XLOOKUP(C21,[1]Overtime!$B$7:$B$557,[1]Overtime!$AN$7:$AN$557,0) -> 0 | AL21: =ROUND(((SUM(N21:P21)+SUM(T21:X21))/($J$3*8))*_xlfn.XLOOKUP(C21,[1]Overtime!$B$9:$B$557,[1]Overtime!$AU$9:$AU$557,0),0) -> 0 | AM21: =ROUND(((SUM(N21:P21)+SUM(T21:X21))/($J$3*8))*_xlfn.XLOOKUP(C21,[1]Overtime!$B$9:$B$557,[1]Overtime!$AY$9:$AY$557,0),0) -> 0 | AN21: =ROUND(AM21+AL21,0) -> 0 | AR21: =ROUND(_xlfn.XLOOKUP(C21,[1]Timesheet!$B$9:$B$458,[1]Timesheet!$BQ$9:$BQ$458,,,-1)*SUM(Salary!N21:P21,Salary!T21:X21)*20%/Salary!$J$3,0) -> 0 | AS21: 0 | AT21: 0 | AV21: =IF(CV21="x",IF(IF(CR21>0,$CW$3-_xlfn.XLOOKUP(C21,[1]Timesheet!B:B,[1]Timesheet!BW:BW,0,,-1),$CW$3-_xlfn.XLOOKUP(C21,[1]Timesheet!B:B,[1]Timesheet!BW:BW,0,,-1)-$EB$3)<14,ROUND(L21*20.5%+M21*1%,0),0),0) -> 0 | AW21: =CK21 -> 0 | AX21: =CM21 -> 0 | AZ21: 0 | BE21: =ROUND(SUM(Z21:AJ21)+AN21+AX21+AT21+AO21+AR21+AS21+AW21+AY21+AV21+AP21+AU21+AQ21+AZ21+BA21,0) -> 446154 | BF21: =IF(OR(CW21="x",CR21>0),0,15500000) -> 0 | BG21: 0 | BJ21: =IF(CV21="x",0,ROUND(IF(BH21>0,M21*1%,0),0)) -> 0 | BK21: =IF(CV21="x",0,ROUND(IF(BH21>0,38948,0),0)) -> 0 | BL21: =ROUND(IF(AC21>0,IF(ROUND((BE21+CX21+CY21-AE21-AN21-AW21-AC21)*15%,0)>AC21,BE21+CX21+CY21-AE21-AN21-AW21,BE21+CX21+CY21-AE21-AN21-AW21-AC21+ROUND((BE21+CX21+CY21-AE21-AN21-AW21-AC21)*15%,0)),BE21+CX21+CY21-AE21-AN21-AW21),0) -> 446154 | BM21: =IF(OR(CW21="x",CR21>0),BL21,IF(BL21-BF21-BG21-SUM(BH21:BJ21)>0,BL21-BF21-BG21-SUM(BH21:BJ21),0)) -> 446154 | BN21: =IF(OR(CW21="x",CR21>0),ROUND(IF(BM21>4999999,BM21*10%,0),0),ROUND(IF(BM21>100000000,((BM21-100000000)*0.35+20500000),IF(AND(BM21>60000000,BM21<=100000000),((BM21-60000000)*0.3+8500000),IF(AND(BM21>30000000,BM21<=60000000),((BM21-30000000)*0.2+2500000),IF(AND(BM21>10000000,BM21<=30000000),((BM21-10000000)*0.1+500000),IF(BM21<0,0,(BM21*0.05)))))),0)) -> 0 | BO21: =SUM(BH21:BK21,BN21) -> 0 | BP21: =IF(CV21="x",0,ROUND(IF(BH21>0,L21*17.5%,0),0)) -> 0 | BQ21: =IF(CV21="x",0,ROUND(IF(BI21>0,L21*3%,0),0)) -> 0 | BR21: =IF(CV21="x",0,ROUND(IF(BJ21>0,M21*1%,0),0)) -> 0 | BS21: =IF(CV21="x",0,ROUND(IF(BK21>0,L21*2%,0),0)) -> 0 | BW21: 0 | CG21: =ROUND(BE21-BO21+BZ21-BT21-BU21-BX21-BV21+BW21+BY21+CA21-CB21,0) -> 446154 | CH21: =CG21+BN21+SUM(BH21:BK21)+SUM(BP21:BS21) -> 446154 | CI21: =IF(BH21=0,0,ROUND((SUM(N21:X21)-(R21+S21))/12,0)) -> 0 | CK21: =ROUND((M21/$CK$3*CJ21),0) -> 0 | CM21: =ROUND((M21/$J$3/8*CL21),0) -> 0 | CO21: =CK21+CM21 -> 0 | CP21: 46199 | CQ21: 46229 | CR21: 46205 | CS21: 0 | CT21: 0 | CV21: x | CW21: x | DC21: =_xlfn.XLOOKUP(C21,[1]Overtime!$B$8:$B$2327,[1]Overtime!$BA$8:$BA$2327,"",,-1) -> 0 | DD21: =_xlfn.XLOOKUP(C21,[1]Timesheet!$B$9:$B$2328,[1]Timesheet!$BS$9:$BS$2328,0,,-1) -> 0 | DE21: =_xlfn.XLOOKUP(C21,[1]Timesheet!$B$7:$B$616,[1]Timesheet!$BK$7:$BK$616,0)+_xlfn.XLOOKUP(C21,[1]Timesheet!$B$7:$B$616,[1]Timesheet!$AV$7:$AV$616,0)-_xlfn.XLOOKUP(C21,[1]Timesheet!$B$7:$B$616,[1]Timesheet!$AX$7:$AX$616,0)+_xlfn.XLOOKUP(C21,[1]Timesheet!$B$7:$B$616,[1]Timesheet!$AW$7:$AW$616,0)-_xlfn.XLOOKUP(C21,[1]Timesheet!$B$7:$B$616,[1]Timesheet!$AY$7:$AY$616,0) -> 0 | DF21: =DE21*(-100000) -> 0 | DG21: =_xlfn.XLOOKUP(C21,[1]Timesheet!$B$7:$B$616,[1]Timesheet!$BV$7:$BV$616,0)+_xlfn.XLOOKUP(C21,[1]Timesheet!$B$7:$B$616,[1]Timesheet!$AX$7:$AX$616,0)++_xlfn.XLOOKUP(C21,[1]Timesheet!$B$7:$B$616,[1]Timesheet!$AY$7:$AY$616,0) -> 3 | DH21: =IF(DG21>2,-1000000,IF(DG21=2,-500000,IF(DG21=1,-200000,0))) -> -1000000 | DI21: =_xlfn.XLOOKUP(C21,[1]Timesheet!$B$7:$B$616,[1]Timesheet!$AZ$7:$AZ$616,0)+_xlfn.XLOOKUP(C21,[1]Timesheet!$B$7:$B$616,[1]Timesheet!$BA$7:$BA$616,0) -> 0 | DJ21: =IF(CW21="x",IF((ROUND(Y21*W21/$J$3,0))<0,0,ROUND(Y21*W21/$J$3,0)),IF(OR(CR21>0,CS21>0,CT21>0),W21/$J$3*(Y21+_xlfn.XLOOKUP(C21,[1]Timesheet!B:B,[1]Timesheet!BS:BS,0,,-1)+_xlfn.XLOOKUP(C21,[1]Timesheet!B:B,[1]Timesheet!BU:BU,0,,-1)),IF(OR(DH21<0,DF21<0),IF(DI21>0,W21/$J$3*($J$3-DI21),W21),W21/$J$3*(Y21+_xlfn.XLOOKUP(C21,[1]Timesheet!B:B,[1]Timesheet!BS:BS,0,,-1)+_xlfn.XLOOKUP(C21,[1]Timesheet!B:B,[1]Timesheet!BU:BU,0,,-1))))) -> 76923 | DK21: =DF21+DH21 -> -1000000 | DL21: =_xlfn.XLOOKUP(C21,[1]Timesheet!$B$7:$B$565,[1]Timesheet!$BB$7:$BB$565,0) -> 0 | DM21: =_xlfn.XLOOKUP(C21,[1]Timesheet!$B$7:$B$565,[1]Timesheet!$BC$7:$BC$565,0) -> 0 | DN21: =_xlfn.XLOOKUP(C21,[1]Timesheet!$B$7:$B$565,[1]Timesheet!$BF$7:$BF$565,0) -> 0 | DO21: =_xlfn.XLOOKUP(C21,[1]Timesheet!$B$7:$B$565,[1]Timesheet!$BJ$7:$BJ$565,0) -> 1 | DP21: =DN21+DO21 -> 1 | DQ21: =_xlfn.XLOOKUP(C21,[1]Timesheet!$B$7:$B$565,[1]Timesheet!$BT$7:$BT$565,0) -> 21 | DR21: =_xlfn.XLOOKUP(C21,[1]Timesheet!$B$7:$B$565,[1]Timesheet!$BM$7:$BM$565,0) -> 0 | DS21: =W21/$J$3*DR21 -> 0 | DT21: =ROUND(IF(BH21>0,L21*$DT$7,0),0) -> 0 | DU21: =ROUND(IF(BI21>0,L21*$DU$7,0),0) -> 0 | DV21: =ROUND(IF(BJ21>0,M21*$DV$7,0),0) -> 0 | DW21: =ROUND(IF(BK21>0,L21*$DW$7,0),0) -> 0 | DX21: =SUM(N21:X21) -> 6800000 | DY21: =SUM(O21:S21) -> 600000 | DZ21: =SUM(W21:X21) -> 1000000 | EA21: =_xlfn.XLOOKUP(C21,[1]Timesheet!$B$7:$B$565,[1]Timesheet!$BI$7:$BI$565,0) -> 3 | EB21: =IF(AC21>0,ROUND((BE21+CX21+CY21-AE21-AN21-AW21-AC21)*15%,0),0) -> 0 | EC21: =AC21 -> 0 | ED21: =EB21-EC21 -> 0 | EE21: =BE21+CX21+CY21-AE21-AN21-AW21-BL21 -> 0 | EF21: =ROUND((SUM(N21:P21)+W21+X21+T21+U21+V21)/($J$3*8)*_xlfn.XLOOKUP(C21,[1]Overtime!$B$9:$B$557,[1]Overtime!$AU$9:$AU$557,0),0) -> 0 | EG21: =ROUND(((SUM(N21:P21)+W21+X21+T21+U21+V21)/($J$3*8))*_xlfn.XLOOKUP(C21,[1]Overtime!$B$9:$B$557,[1]Overtime!$AY$9:$AY$557,0),0) -> 0 | EH21: =ROUND(EG21+EF21,0) -> 0 | EI21: =AL21-EF21 -> 0 | EJ21: =AM21-EG21 -> 0 | EK21: =ROUND((SUM(N21:P21)+W21+X21+T21+U21+V21)/($J$3*8)*_xlfn.XLOOKUP(C21,[1]Overtime!$B$9:$B$557,[1]Overtime!$AO$9:$AO$557,0)*1.5,0) -> 0 | EL21: =ROUND((SUM(N21:P21)+W21+X21+T21+U21+V21)/($J$3*8)*_xlfn.XLOOKUP(C21,[1]Overtime!$B$9:$B$557,[1]Overtime!$AP$9:$AP$557,0)*2,0) -> 0 | EM21: =AN21-EK21-EL21 -> 0 | EN21: =ROUND(Y21*W21/$J$3,0) -> 76923 | EO21: =DJ21-EN21 -> 0 | EP21: =IF(AI21=0,0,AI21-DK21-EN21) -> 0 | EQ21: 0 | ER21: =EQ21/4400000 -> 0
B22: =B21+1 -> 13 | C22: TIQN-2250 | D22: Nguyễn Đức Anh Toàn | E22: =IF(CW22="x","Probation",IF(CR22>0,"Resigned - Official","Official")) -> Probation | F22: =IF(H22="management","6421.11",0) -> 0 | G22: Warehouse | H22: Indirect | I22: Warehouse | J22: Logistics | K22: Warehouse worker | L22: =M22 -> 6500000 | M22: =N22+O22+P22+W22+X22+T22+U22+V22 -> 6500000 | N22: 4500000 | O22: 800000 | P22: 0 | Q22: 0 | R22: 300000 | S22: 0 | T22: 0 | U22: 0 | V22: 200000 | W22: 1000000 | X22: 0 | Y22: =_xlfn.XLOOKUP(C22,[1]Timesheet!$B$9:$B$25,[1]Timesheet!$AO$9:$AO$25,0,,1) -> 3.5 | Z22: =ROUND(N22/$J$3*Y22,0) -> 605769 | AA22: =ROUND(O22/$J$3*(Y22+_xlfn.XLOOKUP(C22,[1]Timesheet!B:B,[1]Timesheet!BS:BS,0)),0) -> 107692 | AB22: =ROUND(IF(Y22>=8,P22,(P22/$J$3)*(Y22+_xlfn.XLOOKUP(C22,[1]Timesheet!B:B,[1]Timesheet!BS:BS,0))),0) -> 0 | AC22: =ROUND(IF(Y22>=14,Q22,(Q22/2)),0) -> 0 | AD22: =IF(_xlfn.XLOOKUP(Salary!C22,[1]Bus!B:B,[1]Bus!G:G,"",,-1)=1,0,ROUND((R22/$J$3)*ROUND(Y22+_xlfn.XLOOKUP(C22,[1]Timesheet!B:B,[1]Timesheet!BS:BS,0,,-1),0),0)) -> 46154 | AE22: =IF(Y22>0,S22,0) -> 0 | AF22: =ROUND(IF(Y22>=8,T22,(T22/$J$3)*(Y22+_xlfn.XLOOKUP(C22,[1]Timesheet!B:B,[1]Timesheet!BS:BS,0))),0) -> 0 | AG22: =ROUND(IF(Y22>=8,U22,(U22/$J$3)*(Y22+_xlfn.XLOOKUP(C22,[1]Timesheet!B:B,[1]Timesheet!BS:BS,0))),0) -> 0 | AH22: =ROUND(IF(OR(CR22>0,Y22<8),(V22/$J$3)*(Y22+_xlfn.XLOOKUP(C22,[1]Timesheet!B:B,[1]Timesheet!BS:BS,0)),V22),0) -> 26923 | AI22: =ROUND(IF(DAY(CR22)=26,IF(Y22=0,0,IF(W22=0,0,IF(OR(-(DK22)>DJ22,-(DK22)=DJ22),0,DJ22+DK22+DS22))),IF(CR22>0,0,IF(Y22=0,0,IF(W22=0,0,IF(OR(-(DK22)>DJ22,-(DK22)=DJ22),0,DJ22+DK22+DS22))))),0) -> 0 | AJ22: =IF(Y22>0,ROUND(IF(LEN(CR22)>2,(X22/$J$3)*(Y22+_xlfn.XLOOKUP(C22,[1]Timesheet!B:B,[1]Timesheet!BS:BS,0)),X22),0),0) -> 0 | AK22: =_xlfn.XLOOKUP(C22,[1]Overtime!$B$7:$B$557,[1]Overtime!$AN$7:$AN$557,0) -> 0 | AL22: =ROUND(((SUM(N22:P22)+SUM(T22:X22))/($J$3*8))*_xlfn.XLOOKUP(C22,[1]Overtime!$B$9:$B$557,[1]Overtime!$AU$9:$AU$557,0),0) -> 0 | AM22: =ROUND(((SUM(N22:P22)+SUM(T22:X22))/($J$3*8))*_xlfn.XLOOKUP(C22,[1]Overtime!$B$9:$B$557,[1]Overtime!$AY$9:$AY$557,0),0) -> 0 | AN22: =ROUND(AM22+AL22,0) -> 0 | AR22: =ROUND(_xlfn.XLOOKUP(C22,[1]Timesheet!$B$9:$B$458,[1]Timesheet!$BQ$9:$BQ$458,,,-1)*SUM(Salary!N22:P22,Salary!T22:X22)*20%/Salary!$J$3,0) -> 0 | AS22: 0 | AT22: 0 | AV22: =IF(CV22="x",IF(IF(CR22>0,$CW$3-_xlfn.XLOOKUP(C22,[1]Timesheet!B:B,[1]Timesheet!BW:BW,0,,-1),$CW$3-_xlfn.XLOOKUP(C22,[1]Timesheet!B:B,[1]Timesheet!BW:BW,0,,-1)-$EB$3)<14,ROUND(L22*20.5%+M22*1%,0),0),0) -> 0 | AW22: =CK22 -> 0 | AX22: =CM22 -> 0 | AZ22: 0 | BE22: =ROUND(SUM(Z22:AJ22)+AN22+AX22+AT22+AO22+AR22+AS22+AW22+AY22+AV22+AP22+AU22+AQ22+AZ22+BA22,0) -> 786538 | BF22: =IF(OR(CW22="x",CR22>0),0,15500000) -> 0 | BG22: 0 | BJ22: =IF(CV22="x",0,ROUND(IF(BH22>0,M22*1%,0),0)) -> 0 | BK22: =IF(CV22="x",0,ROUND(IF(BH22>0,38948,0),0)) -> 0 | BL22: =ROUND(IF(AC22>0,IF(ROUND((BE22+CX22+CY22-AE22-AN22-AW22-AC22)*15%,0)>AC22,BE22+CX22+CY22-AE22-AN22-AW22,BE22+CX22+CY22-AE22-AN22-AW22-AC22+ROUND((BE22+CX22+CY22-AE22-AN22-AW22-AC22)*15%,0)),BE22+CX22+CY22-AE22-AN22-AW22),0) -> 786538 | BM22: =IF(OR(CW22="x",CR22>0),BL22,IF(BL22-BF22-BG22-SUM(BH22:BJ22)>0,BL22-BF22-BG22-SUM(BH22:BJ22),0)) -> 786538 | BN22: =IF(OR(CW22="x",CR22>0),ROUND(IF(BM22>4999999,BM22*10%,0),0),ROUND(IF(BM22>100000000,((BM22-100000000)*0.35+20500000),IF(AND(BM22>60000000,BM22<=100000000),((BM22-60000000)*0.3+8500000),IF(AND(BM22>30000000,BM22<=60000000),((BM22-30000000)*0.2+2500000),IF(AND(BM22>10000000,BM22<=30000000),((BM22-10000000)*0.1+500000),IF(BM22<0,0,(BM22*0.05)))))),0)) -> 0 | BO22: =SUM(BH22:BK22,BN22) -> 0 | BP22: =IF(CV22="x",0,ROUND(IF(BH22>0,L22*17.5%,0),0)) -> 0 | BQ22: =IF(CV22="x",0,ROUND(IF(BI22>0,L22*3%,0),0)) -> 0 | BR22: =IF(CV22="x",0,ROUND(IF(BJ22>0,M22*1%,0),0)) -> 0 | BS22: =IF(CV22="x",0,ROUND(IF(BK22>0,L22*2%,0),0)) -> 0 | BW22: 0 | CG22: =ROUND(BE22-BO22+BZ22-BT22-BU22-BX22-BV22+BW22+BY22+CA22-CB22,0) -> 786538 | CH22: =CG22+BN22+SUM(BH22:BK22)+SUM(BP22:BS22) -> 786538 | CI22: =IF(BH22=0,0,ROUND((SUM(N22:X22)-(R22+S22))/12,0)) -> 0 | CK22: =ROUND((M22/$CK$3*CJ22),0) -> 0 | CM22: =ROUND((M22/$J$3/8*CL22),0) -> 0 | CO22: =CK22+CM22 -> 0 | CP22: 46199 | CQ22: 46229 | CR22: 46204 | CS22: 0 | CT22: 0 | CV22: x | CW22: x | DC22: =_xlfn.XLOOKUP(C22,[1]Overtime!$B$8:$B$2327,[1]Overtime!$BA$8:$BA$2327,"",,-1) -> 0 | DD22: =_xlfn.XLOOKUP(C22,[1]Timesheet!$B$9:$B$2328,[1]Timesheet!$BS$9:$BS$2328,0,,-1) -> 0 | DE22: =_xlfn.XLOOKUP(C22,[1]Timesheet!$B$7:$B$616,[1]Timesheet!$BK$7:$BK$616,0)+_xlfn.XLOOKUP(C22,[1]Timesheet!$B$7:$B$616,[1]Timesheet!$AV$7:$AV$616,0)-_xlfn.XLOOKUP(C22,[1]Timesheet!$B$7:$B$616,[1]Timesheet!$AX$7:$AX$616,0)+_xlfn.XLOOKUP(C22,[1]Timesheet!$B$7:$B$616,[1]Timesheet!$AW$7:$AW$616,0)-_xlfn.XLOOKUP(C22,[1]Timesheet!$B$7:$B$616,[1]Timesheet!$AY$7:$AY$616,0) -> 1 | DF22: =DE22*(-100000) -> -100000 | DG22: =_xlfn.XLOOKUP(C22,[1]Timesheet!$B$7:$B$616,[1]Timesheet!$BV$7:$BV$616,0)+_xlfn.XLOOKUP(C22,[1]Timesheet!$B$7:$B$616,[1]Timesheet!$AX$7:$AX$616,0)++_xlfn.XLOOKUP(C22,[1]Timesheet!$B$7:$B$616,[1]Timesheet!$AY$7:$AY$616,0) -> 0 | DH22: =IF(DG22>2,-1000000,IF(DG22=2,-500000,IF(DG22=1,-200000,0))) -> 0 | DI22: =_xlfn.XLOOKUP(C22,[1]Timesheet!$B$7:$B$616,[1]Timesheet!$AZ$7:$AZ$616,0)+_xlfn.XLOOKUP(C22,[1]Timesheet!$B$7:$B$616,[1]Timesheet!$BA$7:$BA$616,0) -> 0 | DJ22: =IF(CW22="x",IF((ROUND(Y22*W22/$J$3,0))<0,0,ROUND(Y22*W22/$J$3,0)),IF(OR(CR22>0,CS22>0,CT22>0),W22/$J$3*(Y22+_xlfn.XLOOKUP(C22,[1]Timesheet!B:B,[1]Timesheet!BS:BS,0,,-1)+_xlfn.XLOOKUP(C22,[1]Timesheet!B:B,[1]Timesheet!BU:BU,0,,-1)),IF(OR(DH22<0,DF22<0),IF(DI22>0,W22/$J$3*($J$3-DI22),W22),W22/$J$3*(Y22+_xlfn.XLOOKUP(C22,[1]Timesheet!B:B,[1]Timesheet!BS:BS,0,,-1)+_xlfn.XLOOKUP(C22,[1]Timesheet!B:B,[1]Timesheet!BU:BU,0,,-1))))) -> 134615 | DK22: =DF22+DH22 -> -100000 | DL22: =_xlfn.XLOOKUP(C22,[1]Timesheet!$B$7:$B$565,[1]Timesheet!$BB$7:$BB$565,0) -> 0 | DM22: =_xlfn.XLOOKUP(C22,[1]Timesheet!$B$7:$B$565,[1]Timesheet!$BC$7:$BC$565,0) -> 0 | DN22: =_xlfn.XLOOKUP(C22,[1]Timesheet!$B$7:$B$565,[1]Timesheet!$BF$7:$BF$565,0) -> 0 | DO22: =_xlfn.XLOOKUP(C22,[1]Timesheet!$B$7:$B$565,[1]Timesheet!$BJ$7:$BJ$565,0) -> 0 | DP22: =DN22+DO22 -> 0 | DQ22: =_xlfn.XLOOKUP(C22,[1]Timesheet!$B$7:$B$565,[1]Timesheet!$BT$7:$BT$565,0) -> 21 | DR22: =_xlfn.XLOOKUP(C22,[1]Timesheet!$B$7:$B$565,[1]Timesheet!$BM$7:$BM$565,0) -> 0 | DS22: =W22/$J$3*DR22 -> 0 | DT22: =ROUND(IF(BH22>0,L22*$DT$7,0),0) -> 0 | DU22: =ROUND(IF(BI22>0,L22*$DU$7,0),0) -> 0 | DV22: =ROUND(IF(BJ22>0,M22*$DV$7,0),0) -> 0 | DW22: =ROUND(IF(BK22>0,L22*$DW$7,0),0) -> 0 | DX22: =SUM(N22:X22) -> 6800000 | DY22: =SUM(O22:S22) -> 1100000 | DZ22: =SUM(W22:X22) -> 1000000 | EA22: =_xlfn.XLOOKUP(C22,[1]Timesheet!$B$7:$B$565,[1]Timesheet!$BI$7:$BI$565,0) -> 0 | EB22: =IF(AC22>0,ROUND((BE22+CX22+CY22-AE22-AN22-AW22-AC22)*15%,0),0) -> 0 | EC22: =AC22 -> 0 | ED22: =EB22-EC22 -> 0 | EE22: =BE22+CX22+CY22-AE22-AN22-AW22-BL22 -> 0 | EF22: =ROUND((SUM(N22:P22)+W22+X22+T22+U22+V22)/($J$3*8)*_xlfn.XLOOKUP(C22,[1]Overtime!$B$9:$B$557,[1]Overtime!$AU$9:$AU$557,0),0) -> 0 | EG22: =ROUND(((SUM(N22:P22)+W22+X22+T22+U22+V22)/($J$3*8))*_xlfn.XLOOKUP(C22,[1]Overtime!$B$9:$B$557,[1]Overtime!$AY$9:$AY$557,0),0) -> 0 | EH22: =ROUND(EG22+EF22,0) -> 0 | EI22: =AL22-EF22 -> 0 | EJ22: =AM22-EG22 -> 0 | EK22: =ROUND((SUM(N22:P22)+W22+X22+T22+U22+V22)/($J$3*8)*_xlfn.XLOOKUP(C22,[1]Overtime!$B$9:$B$557,[1]Overtime!$AO$9:$AO$557,0)*1.5,0) -> 0 | EL22: =ROUND((SUM(N22:P22)+W22+X22+T22+U22+V22)/($J$3*8)*_xlfn.XLOOKUP(C22,[1]Overtime!$B$9:$B$557,[1]Overtime!$AP$9:$AP$557,0)*2,0) -> 0 | EM22: =AN22-EK22-EL22 -> 0 | EN22: =ROUND(Y22*W22/$J$3,0) -> 134615 | EO22: =DJ22-EN22 -> 0 | EP22: =IF(AI22=0,0,AI22-DK22-EN22) -> 0 | EQ22: 0 | ER22: =EQ22/4400000 -> 0
B23: =B22+1 -> 14 | C23: TIQN-2257 | D23: Nguyễn Thị Thu Nhị | E23: =IF(CW23="x","Probation",IF(CR23>0,"Resigned - Official","Official")) -> Probation | F23: =IF(H23="management","6421.11",0) -> 0 | G23: QA-QC | H23: Indirect | I23: QC | J23: QC | K23: QC worker | L23: =M23 -> 6300000 | M23: =N23+O23+P23+W23+X23+T23+U23+V23 -> 6300000 | N23: 5200000 | O23: 100000 | P23: 0 | Q23: 0 | R23: 300000 | S23: 0 | T23: 0 | U23: 0 | V23: 0 | W23: 1000000 | X23: 0 | Y23: =_xlfn.XLOOKUP(C23,[1]Timesheet!$B$9:$B$25,[1]Timesheet!$AO$9:$AO$25,0,,1) -> 3 | Z23: =ROUND(N23/$J$3*Y23,0) -> 600000 | AA23: =ROUND(O23/$J$3*(Y23+_xlfn.XLOOKUP(C23,[1]Timesheet!B:B,[1]Timesheet!BS:BS,0)),0) -> 11538 | AB23: =ROUND(IF(Y23>=8,P23,(P23/$J$3)*(Y23+_xlfn.XLOOKUP(C23,[1]Timesheet!B:B,[1]Timesheet!BS:BS,0))),0) -> 0 | AC23: =ROUND(IF(Y23>=14,Q23,(Q23/2)),0) -> 0 | AD23: =IF(_xlfn.XLOOKUP(Salary!C23,[1]Bus!B:B,[1]Bus!G:G,"",,-1)=1,0,ROUND((R23/$J$3)*ROUND(Y23+_xlfn.XLOOKUP(C23,[1]Timesheet!B:B,[1]Timesheet!BS:BS,0,,-1),0),0)) -> 34615 | AE23: =IF(Y23>0,S23,0) -> 0 | AF23: =ROUND(IF(Y23>=8,T23,(T23/$J$3)*(Y23+_xlfn.XLOOKUP(C23,[1]Timesheet!B:B,[1]Timesheet!BS:BS,0))),0) -> 0 | AG23: =ROUND(IF(Y23>=8,U23,(U23/$J$3)*(Y23+_xlfn.XLOOKUP(C23,[1]Timesheet!B:B,[1]Timesheet!BS:BS,0))),0) -> 0 | AH23: =ROUND(IF(OR(CR23>0,Y23<8),(V23/$J$3)*(Y23+_xlfn.XLOOKUP(C23,[1]Timesheet!B:B,[1]Timesheet!BS:BS,0)),V23),0) -> 0 | AI23: =ROUND(IF(DAY(CR23)=26,IF(Y23=0,0,IF(W23=0,0,IF(OR(-(DK23)>DJ23,-(DK23)=DJ23),0,DJ23+DK23+DS23))),IF(CR23>0,0,IF(Y23=0,0,IF(W23=0,0,IF(OR(-(DK23)>DJ23,-(DK23)=DJ23),0,DJ23+DK23+DS23))))),0) -> 0 | AJ23: =IF(Y23>0,ROUND(IF(LEN(CR23)>2,(X23/$J$3)*(Y23+_xlfn.XLOOKUP(C23,[1]Timesheet!B:B,[1]Timesheet!BS:BS,0)),X23),0),0) -> 0 | AK23: =_xlfn.XLOOKUP(C23,[1]Overtime!$B$7:$B$557,[1]Overtime!$AN$7:$AN$557,0) -> 0 | AL23: =ROUND(((SUM(N23:P23)+SUM(T23:X23))/($J$3*8))*_xlfn.XLOOKUP(C23,[1]Overtime!$B$9:$B$557,[1]Overtime!$AU$9:$AU$557,0),0) -> 0 | AM23: =ROUND(((SUM(N23:P23)+SUM(T23:X23))/($J$3*8))*_xlfn.XLOOKUP(C23,[1]Overtime!$B$9:$B$557,[1]Overtime!$AY$9:$AY$557,0),0) -> 0 | AN23: =ROUND(AM23+AL23,0) -> 0 | AR23: =ROUND(_xlfn.XLOOKUP(C23,[1]Timesheet!$B$9:$B$458,[1]Timesheet!$BQ$9:$BQ$458,,,-1)*SUM(Salary!N23:P23,Salary!T23:X23)*20%/Salary!$J$3,0) -> 0 | AS23: 20000 | AT23: 0 | AV23: =IF(CV23="x",IF(IF(CR23>0,$CW$3-_xlfn.XLOOKUP(C23,[1]Timesheet!B:B,[1]Timesheet!BW:BW,0,,-1),$CW$3-_xlfn.XLOOKUP(C23,[1]Timesheet!B:B,[1]Timesheet!BW:BW,0,,-1)-$EB$3)<14,ROUND(L23*20.5%+M23*1%,0),0),0) -> 0 | AW23: =CK23 -> 0 | AX23: =CM23 -> 45433 | AZ23: 0 | BE23: =ROUND(SUM(Z23:AJ23)+AN23+AX23+AT23+AO23+AR23+AS23+AW23+AY23+AV23+AP23+AU23+AQ23+AZ23+BA23,0) -> 711586 | BF23: =IF(OR(CW23="x",CR23>0),0,15500000) -> 0 | BG23: 0 | BJ23: =IF(CV23="x",0,ROUND(IF(BH23>0,M23*1%,0),0)) -> 0 | BK23: =IF(CV23="x",0,ROUND(IF(BH23>0,38948,0),0)) -> 0 | BL23: =ROUND(IF(AC23>0,IF(ROUND((BE23+CX23+CY23-AE23-AN23-AW23-AC23)*15%,0)>AC23,BE23+CX23+CY23-AE23-AN23-AW23,BE23+CX23+CY23-AE23-AN23-AW23-AC23+ROUND((BE23+CX23+CY23-AE23-AN23-AW23-AC23)*15%,0)),BE23+CX23+CY23-AE23-AN23-AW23),0) -> 711586 | BM23: =IF(OR(CW23="x",CR23>0),BL23,IF(BL23-BF23-BG23-SUM(BH23:BJ23)>0,BL23-BF23-BG23-SUM(BH23:BJ23),0)) -> 711586 | BN23: =IF(OR(CW23="x",CR23>0),ROUND(IF(BM23>4999999,BM23*10%,0),0),ROUND(IF(BM23>100000000,((BM23-100000000)*0.35+20500000),IF(AND(BM23>60000000,BM23<=100000000),((BM23-60000000)*0.3+8500000),IF(AND(BM23>30000000,BM23<=60000000),((BM23-30000000)*0.2+2500000),IF(AND(BM23>10000000,BM23<=30000000),((BM23-10000000)*0.1+500000),IF(BM23<0,0,(BM23*0.05)))))),0)) -> 0 | BO23: =SUM(BH23:BK23,BN23) -> 0 | BP23: =IF(CV23="x",0,ROUND(IF(BH23>0,L23*17.5%,0),0)) -> 0 | BQ23: =IF(CV23="x",0,ROUND(IF(BI23>0,L23*3%,0),0)) -> 0 | BR23: =IF(CV23="x",0,ROUND(IF(BJ23>0,M23*1%,0),0)) -> 0 | BS23: =IF(CV23="x",0,ROUND(IF(BK23>0,L23*2%,0),0)) -> 0 | BW23: 0 | CG23: =ROUND(BE23-BO23+BZ23-BT23-BU23-BX23-BV23+BW23+BY23+CA23-CB23,0) -> 711586 | CH23: =CG23+BN23+SUM(BH23:BK23)+SUM(BP23:BS23) -> 711586 | CI23: =IF(BH23=0,0,ROUND((SUM(N23:X23)-(R23+S23))/12,0)) -> 0 | CK23: =ROUND((M23/$CK$3*CJ23),0) -> 0 | CL23: 1.5 | CM23: =ROUND((M23/$J$3/8*CL23),0) -> 45433 | CO23: =CK23+CM23 -> 45433 | CP23: 46203 | CQ23: 46233 | CR23: 46206 | CS23: 0 | CT23: 0 | CV23: x | CW23: x | DC23: =_xlfn.XLOOKUP(C23,[1]Overtime!$B$8:$B$2327,[1]Overtime!$BA$8:$BA$2327,"",,-1) -> 0 | DD23: =_xlfn.XLOOKUP(C23,[1]Timesheet!$B$9:$B$2328,[1]Timesheet!$BS$9:$BS$2328,0,,-1) -> 0 | DE23: =_xlfn.XLOOKUP(C23,[1]Timesheet!$B$7:$B$616,[1]Timesheet!$BK$7:$BK$616,0)+_xlfn.XLOOKUP(C23,[1]Timesheet!$B$7:$B$616,[1]Timesheet!$AV$7:$AV$616,0)-_xlfn.XLOOKUP(C23,[1]Timesheet!$B$7:$B$616,[1]Timesheet!$AX$7:$AX$616,0)+_xlfn.XLOOKUP(C23,[1]Timesheet!$B$7:$B$616,[1]Timesheet!$AW$7:$AW$616,0)-_xlfn.XLOOKUP(C23,[1]Timesheet!$B$7:$B$616,[1]Timesheet!$AY$7:$AY$616,0) -> 0 | DF23: =DE23*(-100000) -> 0 | DG23: =_xlfn.XLOOKUP(C23,[1]Timesheet!$B$7:$B$616,[1]Timesheet!$BV$7:$BV$616,0)+_xlfn.XLOOKUP(C23,[1]Timesheet!$B$7:$B$616,[1]Timesheet!$AX$7:$AX$616,0)++_xlfn.XLOOKUP(C23,[1]Timesheet!$B$7:$B$616,[1]Timesheet!$AY$7:$AY$616,0) -> 0 | DH23: =IF(DG23>2,-1000000,IF(DG23=2,-500000,IF(DG23=1,-200000,0))) -> 0 | DI23: =_xlfn.XLOOKUP(C23,[1]Timesheet!$B$7:$B$616,[1]Timesheet!$AZ$7:$AZ$616,0)+_xlfn.XLOOKUP(C23,[1]Timesheet!$B$7:$B$616,[1]Timesheet!$BA$7:$BA$616,0) -> 0 | DJ23: =IF(CW23="x",IF((ROUND(Y23*W23/$J$3,0))<0,0,ROUND(Y23*W23/$J$3,0)),IF(OR(CR23>0,CS23>0,CT23>0),W23/$J$3*(Y23+_xlfn.XLOOKUP(C23,[1]Timesheet!B:B,[1]Timesheet!BS:BS,0,,-1)+_xlfn.XLOOKUP(C23,[1]Timesheet!B:B,[1]Timesheet!BU:BU,0,,-1)),IF(OR(DH23<0,DF23<0),IF(DI23>0,W23/$J$3*($J$3-DI23),W23),W23/$J$3*(Y23+_xlfn.XLOOKUP(C23,[1]Timesheet!B:B,[1]Timesheet!BS:BS,0,,-1)+_xlfn.XLOOKUP(C23,[1]Timesheet!B:B,[1]Timesheet!BU:BU,0,,-1))))) -> 115385 | DK23: =DF23+DH23 -> 0 | DL23: =_xlfn.XLOOKUP(C23,[1]Timesheet!$B$7:$B$565,[1]Timesheet!$BB$7:$BB$565,0) -> 0 | DM23: =_xlfn.XLOOKUP(C23,[1]Timesheet!$B$7:$B$565,[1]Timesheet!$BC$7:$BC$565,0) -> 0 | DN23: =_xlfn.XLOOKUP(C23,[1]Timesheet!$B$7:$B$565,[1]Timesheet!$BF$7:$BF$565,0) -> 0 | DO23: =_xlfn.XLOOKUP(C23,[1]Timesheet!$B$7:$B$565,[1]Timesheet!$BJ$7:$BJ$565,0) -> 0 | DP23: =DN23+DO23 -> 0 | DQ23: =_xlfn.XLOOKUP(C23,[1]Timesheet!$B$7:$B$565,[1]Timesheet!$BT$7:$BT$565,0) -> 19 | DR23: =_xlfn.XLOOKUP(C23,[1]Timesheet!$B$7:$B$565,[1]Timesheet!$BM$7:$BM$565,0) -> 0 | DS23: =W23/$J$3*DR23 -> 0 | DT23: =ROUND(IF(BH23>0,L23*$DT$7,0),0) -> 0 | DU23: =ROUND(IF(BI23>0,L23*$DU$7,0),0) -> 0 | DV23: =ROUND(IF(BJ23>0,M23*$DV$7,0),0) -> 0 | DW23: =ROUND(IF(BK23>0,L23*$DW$7,0),0) -> 0 | DX23: =SUM(N23:X23) -> 6600000 | DY23: =SUM(O23:S23) -> 400000 | DZ23: =SUM(W23:X23) -> 1000000 | EA23: =_xlfn.XLOOKUP(C23,[1]Timesheet!$B$7:$B$565,[1]Timesheet!$BI$7:$BI$565,0) -> 0 | EB23: =IF(AC23>0,ROUND((BE23+CX23+CY23-AE23-AN23-AW23-AC23)*15%,0),0) -> 0 | EC23: =AC23 -> 0 | ED23: =EB23-EC23 -> 0 | EE23: =BE23+CX23+CY23-AE23-AN23-AW23-BL23 -> 0 | EF23: =ROUND((SUM(N23:P23)+W23+X23+T23+U23+V23)/($J$3*8)*_xlfn.XLOOKUP(C23,[1]Overtime!$B$9:$B$557,[1]Overtime!$AU$9:$AU$557,0),0) -> 0 | EG23: =ROUND(((SUM(N23:P23)+W23+X23+T23+U23+V23)/($J$3*8))*_xlfn.XLOOKUP(C23,[1]Overtime!$B$9:$B$557,[1]Overtime!$AY$9:$AY$557,0),0) -> 0 | EH23: =ROUND(EG23+EF23,0) -> 0 | EI23: =AL23-EF23 -> 0 | EJ23: =AM23-EG23 -> 0 | EK23: =ROUND((SUM(N23:P23)+W23+X23+T23+U23+V23)/($J$3*8)*_xlfn.XLOOKUP(C23,[1]Overtime!$B$9:$B$557,[1]Overtime!$AO$9:$AO$557,0)*1.5,0) -> 0 | EL23: =ROUND((SUM(N23:P23)+W23+X23+T23+U23+V23)/($J$3*8)*_xlfn.XLOOKUP(C23,[1]Overtime!$B$9:$B$557,[1]Overtime!$AP$9:$AP$557,0)*2,0) -> 0 | EM23: =AN23-EK23-EL23 -> 0 | EN23: =ROUND(Y23*W23/$J$3,0) -> 115385 | EO23: =DJ23-EN23 -> 0 | EP23: =IF(AI23=0,0,AI23-DK23-EN23) -> 0 | EQ23: 0 | ER23: =EQ23/4400000 -> 0
B24: =B23+1 -> 15 | C24: TIQN-2268 | D24: Phạm Thị Lan | E24: =IF(CW24="x","Probation",IF(CR24>0,"Resigned - Official","Official")) -> Probation | F24: =IF(H24="management","6421.11",0) -> 0 | G24: Line technic | H24: Indirect | I24: Line Technic | J24: Technical & Develop | K24: Technical staff | L24: =M24 -> 9950000 | M24: =N24+O24+P24+W24+X24+T24+U24+V24 -> 9950000 | N24: 7450000 | O24: 1500000 | P24: 0 | Q24: 0 | R24: 300000 | S24: 0 | T24: 0 | U24: 0 | V24: 0 | W24: 1000000 | X24: 0 | Y24: =_xlfn.XLOOKUP(C24,[1]Timesheet!$B$9:$B$25,[1]Timesheet!$AO$9:$AO$25,0,,1) -> 2 | Z24: =ROUND(N24/$J$3*Y24,0) -> 573077 | AA24: =ROUND(O24/$J$3*(Y24+_xlfn.XLOOKUP(C24,[1]Timesheet!B:B,[1]Timesheet!BS:BS,0)),0) -> 115385 | AB24: =ROUND(IF(Y24>=8,P24,(P24/$J$3)*(Y24+_xlfn.XLOOKUP(C24,[1]Timesheet!B:B,[1]Timesheet!BS:BS,0))),0) -> 0 | AC24: =ROUND(IF(Y24>=14,Q24,(Q24/2)),0) -> 0 | AD24: =IF(_xlfn.XLOOKUP(Salary!C24,[1]Bus!B:B,[1]Bus!G:G,"",,-1)=1,0,ROUND((R24/$J$3)*ROUND(Y24+_xlfn.XLOOKUP(C24,[1]Timesheet!B:B,[1]Timesheet!BS:BS,0,,-1),0),0)) -> 23077 | AE24: =IF(Y24>0,S24,0) -> 0 | AF24: =ROUND(IF(Y24>=8,T24,(T24/$J$3)*(Y24+_xlfn.XLOOKUP(C24,[1]Timesheet!B:B,[1]Timesheet!BS:BS,0))),0) -> 0 | AG24: =ROUND(IF(Y24>=8,U24,(U24/$J$3)*(Y24+_xlfn.XLOOKUP(C24,[1]Timesheet!B:B,[1]Timesheet!BS:BS,0))),0) -> 0 | AH24: =ROUND(IF(OR(CR24>0,Y24<8),(V24/$J$3)*(Y24+_xlfn.XLOOKUP(C24,[1]Timesheet!B:B,[1]Timesheet!BS:BS,0)),V24),0) -> 0 | AI24: =ROUND(IF(DAY(CR24)=26,IF(Y24=0,0,IF(W24=0,0,IF(OR(-(DK24)>DJ24,-(DK24)=DJ24),0,DJ24+DK24+DS24))),IF(CR24>0,0,IF(Y24=0,0,IF(W24=0,0,IF(OR(-(DK24)>DJ24,-(DK24)=DJ24),0,DJ24+DK24+DS24))))),0) -> 0 | AJ24: =IF(Y24>0,ROUND(IF(LEN(CR24)>2,(X24/$J$3)*(Y24+_xlfn.XLOOKUP(C24,[1]Timesheet!B:B,[1]Timesheet!BS:BS,0)),X24),0),0) -> 0 | AK24: =_xlfn.XLOOKUP(C24,[1]Overtime!$B$7:$B$557,[1]Overtime!$AN$7:$AN$557,0) -> 0 | AL24: =ROUND(((SUM(N24:P24)+SUM(T24:X24))/($J$3*8))*_xlfn.XLOOKUP(C24,[1]Overtime!$B$9:$B$557,[1]Overtime!$AU$9:$AU$557,0),0) -> 0 | AM24: =ROUND(((SUM(N24:P24)+SUM(T24:X24))/($J$3*8))*_xlfn.XLOOKUP(C24,[1]Overtime!$B$9:$B$557,[1]Overtime!$AY$9:$AY$557,0),0) -> 0 | AN24: =ROUND(AM24+AL24,0) -> 0 | AR24: =ROUND(_xlfn.XLOOKUP(C24,[1]Timesheet!$B$9:$B$458,[1]Timesheet!$BQ$9:$BQ$458,,,-1)*SUM(Salary!N24:P24,Salary!T24:X24)*20%/Salary!$J$3,0) -> 0 | AS24: 0 | AT24: 0 | AV24: =IF(CV24="x",IF(IF(CR24>0,$CW$3-_xlfn.XLOOKUP(C24,[1]Timesheet!B:B,[1]Timesheet!BW:BW,0,,-1),$CW$3-_xlfn.XLOOKUP(C24,[1]Timesheet!B:B,[1]Timesheet!BW:BW,0,,-1)-$EB$3)<14,ROUND(L24*20.5%+M24*1%,0),0),0) -> 0 | AW24: =CK24 -> 0 | AX24: =CM24 -> 47837 | AZ24: 0 | BE24: =ROUND(SUM(Z24:AJ24)+AN24+AX24+AT24+AO24+AR24+AS24+AW24+AY24+AV24+AP24+AU24+AQ24+AZ24+BA24,0) -> 759376 | BF24: =IF(OR(CW24="x",CR24>0),0,15500000) -> 0 | BG24: 0 | BJ24: =IF(CV24="x",0,ROUND(IF(BH24>0,M24*1%,0),0)) -> 0 | BK24: =IF(CV24="x",0,ROUND(IF(BH24>0,38948,0),0)) -> 0 | BL24: =ROUND(IF(AC24>0,IF(ROUND((BE24+CX24+CY24-AE24-AN24-AW24-AC24)*15%,0)>AC24,BE24+CX24+CY24-AE24-AN24-AW24,BE24+CX24+CY24-AE24-AN24-AW24-AC24+ROUND((BE24+CX24+CY24-AE24-AN24-AW24-AC24)*15%,0)),BE24+CX24+CY24-AE24-AN24-AW24),0) -> 759376 | BM24: =IF(OR(CW24="x",CR24>0),BL24,IF(BL24-BF24-BG24-SUM(BH24:BJ24)>0,BL24-BF24-BG24-SUM(BH24:BJ24),0)) -> 759376 | BN24: =IF(OR(CW24="x",CR24>0),ROUND(IF(BM24>4999999,BM24*10%,0),0),ROUND(IF(BM24>100000000,((BM24-100000000)*0.35+20500000),IF(AND(BM24>60000000,BM24<=100000000),((BM24-60000000)*0.3+8500000),IF(AND(BM24>30000000,BM24<=60000000),((BM24-30000000)*0.2+2500000),IF(AND(BM24>10000000,BM24<=30000000),((BM24-10000000)*0.1+500000),IF(BM24<0,0,(BM24*0.05)))))),0)) -> 0 | BO24: =SUM(BH24:BK24,BN24) -> 0 | BP24: =IF(CV24="x",0,ROUND(IF(BH24>0,L24*17.5%,0),0)) -> 0 | BQ24: =IF(CV24="x",0,ROUND(IF(BI24>0,L24*3%,0),0)) -> 0 | BR24: =IF(CV24="x",0,ROUND(IF(BJ24>0,M24*1%,0),0)) -> 0 | BS24: =IF(CV24="x",0,ROUND(IF(BK24>0,L24*2%,0),0)) -> 0 | BW24: 0 | CG24: =ROUND(BE24-BO24+BZ24-BT24-BU24-BX24-BV24+BW24+BY24+CA24-CB24,0) -> 759376 | CH24: =CG24+BN24+SUM(BH24:BK24)+SUM(BP24:BS24) -> 759376 | CI24: =IF(BH24=0,0,ROUND((SUM(N24:X24)-(R24+S24))/12,0)) -> 0 | CK24: =ROUND((M24/$CK$3*CJ24),0) -> 0 | CL24: 1 | CM24: =ROUND((M24/$J$3/8*CL24),0) -> 47837 | CO24: =CK24+CM24 -> 47837 | CP24: 46206 | CQ24: 46236 | CR24: 46209 | CS24: 0 | CT24: 0 | CV24: x | CW24: x | DC24: =_xlfn.XLOOKUP(C24,[1]Overtime!$B$8:$B$2327,[1]Overtime!$BA$8:$BA$2327,"",,-1) -> 0 | DD24: =_xlfn.XLOOKUP(C24,[1]Timesheet!$B$9:$B$2328,[1]Timesheet!$BS$9:$BS$2328,0,,-1) -> 0 | DE24: =_xlfn.XLOOKUP(C24,[1]Timesheet!$B$7:$B$616,[1]Timesheet!$BK$7:$BK$616,0)+_xlfn.XLOOKUP(C24,[1]Timesheet!$B$7:$B$616,[1]Timesheet!$AV$7:$AV$616,0)-_xlfn.XLOOKUP(C24,[1]Timesheet!$B$7:$B$616,[1]Timesheet!$AX$7:$AX$616,0)+_xlfn.XLOOKUP(C24,[1]Timesheet!$B$7:$B$616,[1]Timesheet!$AW$7:$AW$616,0)-_xlfn.XLOOKUP(C24,[1]Timesheet!$B$7:$B$616,[1]Timesheet!$AY$7:$AY$616,0) -> 0 | DF24: =DE24*(-100000) -> 0 | DG24: =_xlfn.XLOOKUP(C24,[1]Timesheet!$B$7:$B$616,[1]Timesheet!$BV$7:$BV$616,0)+_xlfn.XLOOKUP(C24,[1]Timesheet!$B$7:$B$616,[1]Timesheet!$AX$7:$AX$616,0)++_xlfn.XLOOKUP(C24,[1]Timesheet!$B$7:$B$616,[1]Timesheet!$AY$7:$AY$616,0) -> 0 | DH24: =IF(DG24>2,-1000000,IF(DG24=2,-500000,IF(DG24=1,-200000,0))) -> 0 | DI24: =_xlfn.XLOOKUP(C24,[1]Timesheet!$B$7:$B$616,[1]Timesheet!$AZ$7:$AZ$616,0)+_xlfn.XLOOKUP(C24,[1]Timesheet!$B$7:$B$616,[1]Timesheet!$BA$7:$BA$616,0) -> 0 | DJ24: =IF(CW24="x",IF((ROUND(Y24*W24/$J$3,0))<0,0,ROUND(Y24*W24/$J$3,0)),IF(OR(CR24>0,CS24>0,CT24>0),W24/$J$3*(Y24+_xlfn.XLOOKUP(C24,[1]Timesheet!B:B,[1]Timesheet!BS:BS,0,,-1)+_xlfn.XLOOKUP(C24,[1]Timesheet!B:B,[1]Timesheet!BU:BU,0,,-1)),IF(OR(DH24<0,DF24<0),IF(DI24>0,W24/$J$3*($J$3-DI24),W24),W24/$J$3*(Y24+_xlfn.XLOOKUP(C24,[1]Timesheet!B:B,[1]Timesheet!BS:BS,0,,-1)+_xlfn.XLOOKUP(C24,[1]Timesheet!B:B,[1]Timesheet!BU:BU,0,,-1))))) -> 76923 | DK24: =DF24+DH24 -> 0 | DL24: =_xlfn.XLOOKUP(C24,[1]Timesheet!$B$7:$B$565,[1]Timesheet!$BB$7:$BB$565,0) -> 0 | DM24: =_xlfn.XLOOKUP(C24,[1]Timesheet!$B$7:$B$565,[1]Timesheet!$BC$7:$BC$565,0) -> 0 | DN24: =_xlfn.XLOOKUP(C24,[1]Timesheet!$B$7:$B$565,[1]Timesheet!$BF$7:$BF$565,0) -> 0 | DO24: =_xlfn.XLOOKUP(C24,[1]Timesheet!$B$7:$B$565,[1]Timesheet!$BJ$7:$BJ$565,0) -> 0 | DP24: =DN24+DO24 -> 0 | DQ24: =_xlfn.XLOOKUP(C24,[1]Timesheet!$B$7:$B$565,[1]Timesheet!$BT$7:$BT$565,0) -> 19 | DR24: =_xlfn.XLOOKUP(C24,[1]Timesheet!$B$7:$B$565,[1]Timesheet!$BM$7:$BM$565,0) -> 0 | DS24: =W24/$J$3*DR24 -> 0 | DT24: =ROUND(IF(BH24>0,L24*$DT$7,0),0) -> 0 | DU24: =ROUND(IF(BI24>0,L24*$DU$7,0),0) -> 0 | DV24: =ROUND(IF(BJ24>0,M24*$DV$7,0),0) -> 0 | DW24: =ROUND(IF(BK24>0,L24*$DW$7,0),0) -> 0 | DX24: =SUM(N24:X24) -> 10250000 | DY24: =SUM(O24:S24) -> 1800000 | DZ24: =SUM(W24:X24) -> 1000000 | EA24: =_xlfn.XLOOKUP(C24,[1]Timesheet!$B$7:$B$565,[1]Timesheet!$BI$7:$BI$565,0) -> 0 | EB24: =IF(AC24>0,ROUND((BE24+CX24+CY24-AE24-AN24-AW24-AC24)*15%,0),0) -> 0 | EC24: =AC24 -> 0 | ED24: =EB24-EC24 -> 0 | EE24: =BE24+CX24+CY24-AE24-AN24-AW24-BL24 -> 0 | EF24: =ROUND((SUM(N24:P24)+W24+X24+T24+U24+V24)/($J$3*8)*_xlfn.XLOOKUP(C24,[1]Overtime!$B$9:$B$557,[1]Overtime!$AU$9:$AU$557,0),0) -> 0 | EG24: =ROUND(((SUM(N24:P24)+W24+X24+T24+U24+V24)/($J$3*8))*_xlfn.XLOOKUP(C24,[1]Overtime!$B$9:$B$557,[1]Overtime!$AY$9:$AY$557,0),0) -> 0 | EH24: =ROUND(EG24+EF24,0) -> 0 | EI24: =AL24-EF24 -> 0 | EJ24: =AM24-EG24 -> 0 | EK24: =ROUND((SUM(N24:P24)+W24+X24+T24+U24+V24)/($J$3*8)*_xlfn.XLOOKUP(C24,[1]Overtime!$B$9:$B$557,[1]Overtime!$AO$9:$AO$557,0)*1.5,0) -> 0 | EL24: =ROUND((SUM(N24:P24)+W24+X24+T24+U24+V24)/($J$3*8)*_xlfn.XLOOKUP(C24,[1]Overtime!$B$9:$B$557,[1]Overtime!$AP$9:$AP$557,0)*2,0) -> 0 | EM24: =AN24-EK24-EL24 -> 0 | EN24: =ROUND(Y24*W24/$J$3,0) -> 76923 | EO24: =DJ24-EN24 -> 0 | EP24: =IF(AI24=0,0,AI24-DK24-EN24) -> 0 | EQ24: 0 | ER24: =EQ24/4400000 -> 0
B25: =B24+1 -> 16 | C25: TIQN-2280 | D25: Phạm Thị Thu Hiền | E25: =IF(CW25="x","Probation",IF(CR25>0,"Resigned - Official","Official")) -> Probation | F25: =IF(H25="management","6421.11",0) -> 0 | G25: QA-QC | H25: Indirect | I25: QC | J25: QC | K25: QC worker | L25: =M25 -> 6300000 | M25: =N25+O25+P25+W25+X25+T25+U25+V25 -> 6300000 | N25: 5200000 | O25: 100000 | P25: 0 | Q25: 0 | R25: 300000 | S25: 0 | T25: 0 | U25: 0 | V25: 0 | W25: 1000000 | X25: 0 | Y25: =_xlfn.XLOOKUP(C25,[1]Timesheet!$B$9:$B$25,[1]Timesheet!$AO$9:$AO$25,0,,1) -> 1 | Z25: =ROUND(N25/$J$3*Y25,0) -> 200000 | AA25: =ROUND(O25/$J$3*(Y25+_xlfn.XLOOKUP(C25,[1]Timesheet!B:B,[1]Timesheet!BS:BS,0)),0) -> 3846 | AB25: =ROUND(IF(Y25>=8,P25,(P25/$J$3)*(Y25+_xlfn.XLOOKUP(C25,[1]Timesheet!B:B,[1]Timesheet!BS:BS,0))),0) -> 0 | AC25: =ROUND(IF(Y25>=14,Q25,(Q25/2)),0) -> 0 | AD25: =IF(_xlfn.XLOOKUP(Salary!C25,[1]Bus!B:B,[1]Bus!G:G,"",,-1)=1,0,ROUND((R25/$J$3)*ROUND(Y25+_xlfn.XLOOKUP(C25,[1]Timesheet!B:B,[1]Timesheet!BS:BS,0,,-1),0),0)) -> 11538 | AE25: =IF(Y25>0,S25,0) -> 0 | AF25: =ROUND(IF(Y25>=8,T25,(T25/$J$3)*(Y25+_xlfn.XLOOKUP(C25,[1]Timesheet!B:B,[1]Timesheet!BS:BS,0))),0) -> 0 | AG25: =ROUND(IF(Y25>=8,U25,(U25/$J$3)*(Y25+_xlfn.XLOOKUP(C25,[1]Timesheet!B:B,[1]Timesheet!BS:BS,0))),0) -> 0 | AH25: =ROUND(IF(OR(CR25>0,Y25<8),(V25/$J$3)*(Y25+_xlfn.XLOOKUP(C25,[1]Timesheet!B:B,[1]Timesheet!BS:BS,0)),V25),0) -> 0 | AI25: =ROUND(IF(DAY(CR25)=26,IF(Y25=0,0,IF(W25=0,0,IF(OR(-(DK25)>DJ25,-(DK25)=DJ25),0,DJ25+DK25+DS25))),IF(CR25>0,0,IF(Y25=0,0,IF(W25=0,0,IF(OR(-(DK25)>DJ25,-(DK25)=DJ25),0,DJ25+DK25+DS25))))),0) -> 0 | AJ25: =IF(Y25>0,ROUND(IF(LEN(CR25)>2,(X25/$J$3)*(Y25+_xlfn.XLOOKUP(C25,[1]Timesheet!B:B,[1]Timesheet!BS:BS,0)),X25),0),0) -> 0 | AK25: =_xlfn.XLOOKUP(C25,[1]Overtime!$B$7:$B$557,[1]Overtime!$AN$7:$AN$557,0) -> 0 | AL25: =ROUND(((SUM(N25:P25)+SUM(T25:X25))/($J$3*8))*_xlfn.XLOOKUP(C25,[1]Overtime!$B$9:$B$557,[1]Overtime!$AU$9:$AU$557,0),0) -> 0 | AM25: =ROUND(((SUM(N25:P25)+SUM(T25:X25))/($J$3*8))*_xlfn.XLOOKUP(C25,[1]Overtime!$B$9:$B$557,[1]Overtime!$AY$9:$AY$557,0),0) -> 0 | AN25: =ROUND(AM25+AL25,0) -> 0 | AR25: =ROUND(_xlfn.XLOOKUP(C25,[1]Timesheet!$B$9:$B$458,[1]Timesheet!$BQ$9:$BQ$458,,,-1)*SUM(Salary!N25:P25,Salary!T25:X25)*20%/Salary!$J$3,0) -> 0 | AS25: 0 | AT25: 0 | AV25: =IF(CV25="x",IF(IF(CR25>0,$CW$3-_xlfn.XLOOKUP(C25,[1]Timesheet!B:B,[1]Timesheet!BW:BW,0,,-1),$CW$3-_xlfn.XLOOKUP(C25,[1]Timesheet!B:B,[1]Timesheet!BW:BW,0,,-1)-$EB$3)<14,ROUND(L25*20.5%+M25*1%,0),0),0) -> 0 | AW25: =CK25 -> 0 | AX25: =CM25 -> 15144 | AZ25: 0 | BE25: =ROUND(SUM(Z25:AJ25)+AN25+AX25+AT25+AO25+AR25+AS25+AW25+AY25+AV25+AP25+AU25+AQ25+AZ25+BA25,0) -> 230528 | BF25: =IF(OR(CW25="x",CR25>0),0,15500000) -> 0 | BG25: 0 | BJ25: =IF(CV25="x",0,ROUND(IF(BH25>0,M25*1%,0),0)) -> 0 | BK25: =IF(CV25="x",0,ROUND(IF(BH25>0,38948,0),0)) -> 0 | BL25: =ROUND(IF(AC25>0,IF(ROUND((BE25+CX25+CY25-AE25-AN25-AW25-AC25)*15%,0)>AC25,BE25+CX25+CY25-AE25-AN25-AW25,BE25+CX25+CY25-AE25-AN25-AW25-AC25+ROUND((BE25+CX25+CY25-AE25-AN25-AW25-AC25)*15%,0)),BE25+CX25+CY25-AE25-AN25-AW25),0) -> 230528 | BM25: =IF(OR(CW25="x",CR25>0),BL25,IF(BL25-BF25-BG25-SUM(BH25:BJ25)>0,BL25-BF25-BG25-SUM(BH25:BJ25),0)) -> 230528 | BN25: =IF(OR(CW25="x",CR25>0),ROUND(IF(BM25>4999999,BM25*10%,0),0),ROUND(IF(BM25>100000000,((BM25-100000000)*0.35+20500000),IF(AND(BM25>60000000,BM25<=100000000),((BM25-60000000)*0.3+8500000),IF(AND(BM25>30000000,BM25<=60000000),((BM25-30000000)*0.2+2500000),IF(AND(BM25>10000000,BM25<=30000000),((BM25-10000000)*0.1+500000),IF(BM25<0,0,(BM25*0.05)))))),0)) -> 0 | BO25: =SUM(BH25:BK25,BN25) -> 0 | BP25: =IF(CV25="x",0,ROUND(IF(BH25>0,L25*17.5%,0),0)) -> 0 | BQ25: =IF(CV25="x",0,ROUND(IF(BI25>0,L25*3%,0),0)) -> 0 | BR25: =IF(CV25="x",0,ROUND(IF(BJ25>0,M25*1%,0),0)) -> 0 | BS25: =IF(CV25="x",0,ROUND(IF(BK25>0,L25*2%,0),0)) -> 0 | BW25: 0 | CG25: =ROUND(BE25-BO25+BZ25-BT25-BU25-BX25-BV25+BW25+BY25+CA25-CB25,0) -> 230528 | CH25: =CG25+BN25+SUM(BH25:BK25)+SUM(BP25:BS25) -> 230528 | CI25: =IF(BH25=0,0,ROUND((SUM(N25:X25)-(R25+S25))/12,0)) -> 0 | CK25: =ROUND((M25/$CK$3*CJ25),0) -> 0 | CL25: 0.5 | CM25: =ROUND((M25/$J$3/8*CL25),0) -> 15144 | CO25: =CK25+CM25 -> 15144 | CP25: 46210 | CQ25: 46240 | CR25: 46211 | CS25: 0 | CT25: 0 | CV25: x | CW25: x | DC25: =_xlfn.XLOOKUP(C25,[1]Overtime!$B$8:$B$2327,[1]Overtime!$BA$8:$BA$2327,"",,-1) -> 0 | DD25: =_xlfn.XLOOKUP(C25,[1]Timesheet!$B$9:$B$2328,[1]Timesheet!$BS$9:$BS$2328,0,,-1) -> 0 | DE25: =_xlfn.XLOOKUP(C25,[1]Timesheet!$B$7:$B$616,[1]Timesheet!$BK$7:$BK$616,0)+_xlfn.XLOOKUP(C25,[1]Timesheet!$B$7:$B$616,[1]Timesheet!$AV$7:$AV$616,0)-_xlfn.XLOOKUP(C25,[1]Timesheet!$B$7:$B$616,[1]Timesheet!$AX$7:$AX$616,0)+_xlfn.XLOOKUP(C25,[1]Timesheet!$B$7:$B$616,[1]Timesheet!$AW$7:$AW$616,0)-_xlfn.XLOOKUP(C25,[1]Timesheet!$B$7:$B$616,[1]Timesheet!$AY$7:$AY$616,0) -> 0 | DF25: =DE25*(-100000) -> 0 | DG25: =_xlfn.XLOOKUP(C25,[1]Timesheet!$B$7:$B$616,[1]Timesheet!$BV$7:$BV$616,0)+_xlfn.XLOOKUP(C25,[1]Timesheet!$B$7:$B$616,[1]Timesheet!$AX$7:$AX$616,0)++_xlfn.XLOOKUP(C25,[1]Timesheet!$B$7:$B$616,[1]Timesheet!$AY$7:$AY$616,0) -> 0 | DH25: =IF(DG25>2,-1000000,IF(DG25=2,-500000,IF(DG25=1,-200000,0))) -> 0 | DI25: =_xlfn.XLOOKUP(C25,[1]Timesheet!$B$7:$B$616,[1]Timesheet!$AZ$7:$AZ$616,0)+_xlfn.XLOOKUP(C25,[1]Timesheet!$B$7:$B$616,[1]Timesheet!$BA$7:$BA$616,0) -> 0 | DJ25: =IF(CW25="x",IF((ROUND(Y25*W25/$J$3,0))<0,0,ROUND(Y25*W25/$J$3,0)),IF(OR(CR25>0,CS25>0,CT25>0),W25/$J$3*(Y25+_xlfn.XLOOKUP(C25,[1]Timesheet!B:B,[1]Timesheet!BS:BS,0,,-1)+_xlfn.XLOOKUP(C25,[1]Timesheet!B:B,[1]Timesheet!BU:BU,0,,-1)),IF(OR(DH25<0,DF25<0),IF(DI25>0,W25/$J$3*($J$3-DI25),W25),W25/$J$3*(Y25+_xlfn.XLOOKUP(C25,[1]Timesheet!B:B,[1]Timesheet!BS:BS,0,,-1)+_xlfn.XLOOKUP(C25,[1]Timesheet!B:B,[1]Timesheet!BU:BU,0,,-1))))) -> 38462 | DK25: =DF25+DH25 -> 0 | DL25: =_xlfn.XLOOKUP(C25,[1]Timesheet!$B$7:$B$565,[1]Timesheet!$BB$7:$BB$565,0) -> 0 | DM25: =_xlfn.XLOOKUP(C25,[1]Timesheet!$B$7:$B$565,[1]Timesheet!$BC$7:$BC$565,0) -> 0 | DN25: =_xlfn.XLOOKUP(C25,[1]Timesheet!$B$7:$B$565,[1]Timesheet!$BF$7:$BF$565,0) -> 0 | DO25: =_xlfn.XLOOKUP(C25,[1]Timesheet!$B$7:$B$565,[1]Timesheet!$BJ$7:$BJ$565,0) -> 0 | DP25: =DN25+DO25 -> 0 | DQ25: =_xlfn.XLOOKUP(C25,[1]Timesheet!$B$7:$B$565,[1]Timesheet!$BT$7:$BT$565,0) -> 20 | DR25: =_xlfn.XLOOKUP(C25,[1]Timesheet!$B$7:$B$565,[1]Timesheet!$BM$7:$BM$565,0) -> 0 | DS25: =W25/$J$3*DR25 -> 0 | DT25: =ROUND(IF(BH25>0,L25*$DT$7,0),0) -> 0 | DU25: =ROUND(IF(BI25>0,L25*$DU$7,0),0) -> 0 | DV25: =ROUND(IF(BJ25>0,M25*$DV$7,0),0) -> 0 | DW25: =ROUND(IF(BK25>0,L25*$DW$7,0),0) -> 0 | DX25: =SUM(N25:X25) -> 6600000 | DY25: =SUM(O25:S25) -> 400000 | DZ25: =SUM(W25:X25) -> 1000000 | EA25: =_xlfn.XLOOKUP(C25,[1]Timesheet!$B$7:$B$565,[1]Timesheet!$BI$7:$BI$565,0) -> 0 | EB25: =IF(AC25>0,ROUND((BE25+CX25+CY25-AE25-AN25-AW25-AC25)*15%,0),0) -> 0 | EC25: =AC25 -> 0 | ED25: =EB25-EC25 -> 0 | EE25: =BE25+CX25+CY25-AE25-AN25-AW25-BL25 -> 0 | EF25: =ROUND((SUM(N25:P25)+W25+X25+T25+U25+V25)/($J$3*8)*_xlfn.XLOOKUP(C25,[1]Overtime!$B$9:$B$557,[1]Overtime!$AU$9:$AU$557,0),0) -> 0 | EG25: =ROUND(((SUM(N25:P25)+W25+X25+T25+U25+V25)/($J$3*8))*_xlfn.XLOOKUP(C25,[1]Overtime!$B$9:$B$557,[1]Overtime!$AY$9:$AY$557,0),0) -> 0 | EH25: =ROUND(EG25+EF25,0) -> 0 | EI25: =AL25-EF25 -> 0 | EJ25: =AM25-EG25 -> 0 | EK25: =ROUND((SUM(N25:P25)+W25+X25+T25+U25+V25)/($J$3*8)*_xlfn.XLOOKUP(C25,[1]Overtime!$B$9:$B$557,[1]Overtime!$AO$9:$AO$557,0)*1.5,0) -> 0 | EL25: =ROUND((SUM(N25:P25)+W25+X25+T25+U25+V25)/($J$3*8)*_xlfn.XLOOKUP(C25,[1]Overtime!$B$9:$B$557,[1]Overtime!$AP$9:$AP$557,0)*2,0) -> 0 | EM25: =AN25-EK25-EL25 -> 0 | EN25: =ROUND(Y25*W25/$J$3,0) -> 38462 | EO25: =DJ25-EN25 -> 0 | EP25: =IF(AI25=0,0,AI25-DK25-EN25) -> 0 | EQ25: 0 | ER25: =EQ25/4400000 -> 0
B26: Total | L26: =L9+L8 -> 107550000 | M26: =M9+M8 -> 107550000 | N26: =N9+N8 -> 83950000 | O26: =O9+O8 -> 7400000 | P26: =P9+P8 -> 0 | Q26: =Q9+Q8 -> 0 | R26: =R9+R8 -> 4800000 | S26: =S9+S8 -> 0 | ... CY26: =CY9+CY8 -> 0 | DB26: =DB9+DB8 -> 0 | DC26: =DC9+DC8 -> 0 | DD26: =DD9+DD8 -> 0 | DE26: =DE9+DE8 -> 4 | DF26: =DF9+DF8 -> -400000 | DG26: =DG9+DG8 -> 31 | DH26: =DH9+DH8 -> -6400000 | DI26: =DI9+DI8 -> 0 | ... EP26: =EP9+EP8 -> 0 | EQ26: 1377200000 | ES26: 7824780959 | EU26: 8373653844
BL27: Quang Ngai, 09 Jul 2026
BL28: Quảng Ngãi, ngày 09 tháng 07 năm 2026
K29: Prepared by | Y29: Verified by | BL29: Approved by
K30: C&B Executive | Y30: Office Department Manager | BL30: Head of Branch
K35: Phạm Thị Kim Loan | Y35: Nguyễn Thị Yến Ni | BL35: KITAJIMA MOTOHARU
